Workbook
Name _ftn1: 'CIS CSAT Pro'!$G$20
Name _ftnref1: 'CIS CSAT Pro'!$G$8
Name _Hlk82606169: 'CIS CSAT Pro'!$G$14
Name AcceptableRisk: '2. Enterprise Parameters'!$E$35
Name AcceptableRisk1: 'Enterprise Parameters -EXAMPLE'!$E$35
Name Asset_Class: tblVCDBIndex[[#All],[Asset Class]]
Name Maturity_Score: tblMaturityScores[Maturity Scores]

Sheet Cover

Sheet Read_Me
A1: CIS RAM v2.2 for IG2
A2: The CIS RAM for IG2 Workbook protects most cells in the Risk Register and lookup tables to prevent users from accidentally changing the formulas and lookups that automate the risk analysis and make it simple. If users are confident in their use of Microsoft® Excel and wish to modify values, such as Risk Acceptance Criteria, they may “unprotect” the document by going to the “Review” tab in the Excel menu and selecting the “Unprotect sheet” button. However, guidance for maintenance of the Workbook, formulas, lookups, and protected cells is beyond the scope of this document.

Sheet Important Resources
D5: Remember to download the CIS Controls Version 8.1 Guide where you can learn more about: - This Version of the CIS Controls - The CIS Controls Ecosystem ("It's not about the list') - How to Get Started - Using or Transitioning from Prior Versions of the CIS Controls - Structure of the CIS Controls - Implementation Groups - Why is this Control critical - Procedures and tools
D6: https://www.cisecurity.org/controls/v8-1/
D7: https://www.cisecurity.org/controls/resources?crc=about-the-cis-critical-security-controls
D10: A free tool with a dynamic list of the CIS Safeguards that can be filtered by Implemtation Groups and mappings to multiple frameworks.
D11: https://www.cisecurity.org/controls/cis-controls-navigator
D16: Join our community where you can discuss the CIS Controls with our global army of experts and voluneers!
D17: https://workbench.cisecurity.org/dashboard
D19: CIS CSAT (Controls Self Assessment Tool)
D21: Overview: The CIS Controls® Self Assessment Tool, also known as CIS CSAT, enables organizations to assess and track their implementation of the CIS Controls for Versions 8 and 7.1. The CIS Controls are a prioritized set of consensus-developed security best practices used by organizations around the world to defend against cyber threats.
D23: TWO TYPES:
D25: CIS-Hosted CSAT: The CIS-hosted version of CIS CSAT is free to every organization for use in a non-commercial capacity to conduct CIS Controls assessments of their organization. (released January 2019)
D26: https://csat.cisecurity.org/
... D29: https://www.cisecurity.org/controls/cis-controls-self-assessment-tool-cis-csat/

Sheet 1. Impact Criteria Survey 
D2: Prompt | E2: Response
B3: 1 | C3: Mission | D3: How would you concisely describe the benefit that your enterprise provides your customers, clients, constituents, or the public? This is why they engage in this risk with you.
C5: Instructions: Imagine that your enterprise suffers a cybersecurity or information security incident. Describe in the spaces provided below how you would determine that the impacts to your mission were acceptable, or unacceptable.
C7: Impact Magnitude | D7: Prompt | E7: Response
C8: Negligible | D8: What observable evidence would you have that your mission - as you defined it above - would be unaffected? | E8: The mission would remain intact.
C9: Acceptable | D9: What observable evidence would you have that your mission would be compromised, but it would not require correction? | E9: This mission would not be perfectly achieved, but could be recovered within normal operations.
C10: Unacceptable | D10: What observable evidence would you have that your mission would be compromised in a way that would require correction, but the correction could be achieved through the normal course of business? | E10: This mission would not be achieved, and would require short-term, unplanned efforts, resources, or investments to recover.
C11: High | D11: What observable evidence would you have that your mission would be compromised so badly that extraordinary efforts would be required to restore it? | E11: This mission would not be achieved. If significant, unplanned efforts, resources, or investments are not made, the mission may not ever be achievable.
C12: Catastrophic | D12: What observable evidence would you have that your mission would be compromised so badly that it could not be achieved? | E12: The mission would not be achievable.
D15: Prompt | E15: Response
B16: 2 | C16: Operational Objectives | D16: What business or organizational goals does the enterprise attempt to achieve?
C18: Instructions: Imagine that your enterprise suffers a cybersecurity or information security incident. Describe in the spaces provided below how you would determine that the impacts to your operational objectives were acceptable, or unacceptable.
C20: Impact Magnitude | D20: Prompt | E20: Response
C21: Negligible | D21: What observable evidence would you have that your operational objectives - as you defined them above - would be unaffected? | E21: Growth plan would be intact.
C22: Acceptable | D22: What observable evidence would you have that your operational objectives would be compromised, but it would not require correction? | E22: Growth plan would be off target, but within variance.
C23: Unacceptable | D23: What observable evidence would you have that your operational objectives would be compromised in a way that would require correction, but the correction could be achieved through the normal course of business? | E23: Growth plan would be out of variance, but can be recovered within a fiscal year.
C24: High | D24: What observable evidence would you have that your operational objectives would be compromised so badly that extraordinary efforts would be required to restore them? | E24: Growth plan would be out of variance, and may require multiple years to correct.
C25: Catastrophic | D25: What observable evidence would you have that your operational objectives would be compromised so badly that they could not be achieved? | E25: We would not be able to grow.
D28: Prompt | E28: Response
B29: 3 | C29: Financial Objectives | D29: What are the unexpected cost outlays that your enterprise could or could not tolerate?
C31: Instructions: Imagine that your enterprise suffers a cybersecurity or information security incident. Describe in the spaces provided below how you would determine that the impacts to your financial objectives were acceptable, or unacceptable.
C33: Impact Magnitude | D33: Prompt | E33: Response
C34: Negligible | D34: What observable evidence would you have that your financial objectives - as you defined them above - would be unaffected?
C35: Acceptable | D35: What observable evidence would you have that your financial objectives would be compromised, but it would not require correction?
C36: Unacceptable | D36: What observable evidence would you have that your financial objectives would be compromised in a way that would require correction, but the correction could be achieved through the normal course of business?
C37: High | D37: What observable evidence would you have that your financial objectives would be compromised so badly that extraordinary efforts would be required to restore them?
C38: Catastrophic | D38: Leave this blank
D41: Prompt | E41: Response
B42: 4 | C42: Obligations | D42: What harm may foreseeably come to others as a result of a cybersecurity incident?
C44: Instructions: Imagine that your enterprise suffers a cybersecurity or information security incident. Describe in the spaces provided below how you would determine that the impacts to your obligations (harm, to others) were acceptable, or unacceptable.
C46: Impact Magnitude | D46: Prompt | E46: Response
C47: Negligible | D47: Describe a condition where others would not be harmed. | E47: No harm could foreseeably result.
C48: Acceptable | D48: Describe a condition where others would not be harmed to a degree that required correction or compensation. | E48: Any harm that could result would not require correction, repair, or compensation to make the harmed parties "whole."
C49: Unacceptable | D49: Describe a condition where one or few others would be harmed to a degree that you could correct. | E49: Correctible harm may occur to one or few others.
C50: High | D50: Describe a condition where many others would be harmed to a degree that you could correct, or where few others are harmed to a degree that others would always have a small degree of impairment. | E50: Correctible harm may occur to many others, or harm that can be partially corrected for a few others may occur.
C51: Catastrophic | D51: Describe a condition where others would be irreparably harmed. | E51: We would not be able to protect others from any degree of harm.

Sheet 2. Enterprise Parameters
B2: 1 | C2: Enterprise Risk Assessment Criteria | D2: Enterprise Name
D3: Scope
D4: Last Completed (Date)
B8: 2 | C8: Impact Criteria
C10: Impact Scores | D10: Mission | E10: Operational Objectives | F10: Financial Objectives | G10: Obligations
C11: Definition | F11: =IF(ISBLANK('1. Impact Criteria Survey '!E29),"",'1. Impact Criteria Survey '!E29)
C12: 1. Negligible | D12: The mission would remain intact. | E12: Growth plan would be intact. | F12: =IF(ISBLANK('1. Impact Criteria Survey '!E34),"",'1. Impact Criteria Survey '!E34) | G12: No harm could foreseeably result.
C13: 2. Acceptable | D13: This mission would not be perfectly achieved, but could be recovered within normal operations. | E13: Growth plan would be off target, but within variance. | F13: =IF(ISBLANK('1. Impact Criteria Survey '!E35),"",'1. Impact Criteria Survey '!E35) | G13: Any harm that could result would not require correction, repair, or compensation to make the harmed parties "whole."
C14: 3. Unacceptable | D14: This mission would not be achieved, and would require short-term, unplanned efforts, resources, or investments to recover. | E14: Growth plan would be out of variance, but can be recovered within a fiscal year. | F14: =IF(ISBLANK('1. Impact Criteria Survey '!E36),"",'1. Impact Criteria Survey '!E36) | G14: Correctible harm may occur to one or few others.
C15: 4. High | D15: This mission would not be achieved. If significant, unplanned efforts, resources, or investments are not made, the mission may not ever be achievable. | E15: Growth plan would be out of variance, and may require multiple years to correct. | F15: =IF(ISBLANK('1. Impact Criteria Survey '!E37),"",'1. Impact Criteria Survey '!E37) | G15: Correctible harm may occur to many others, or harm that can be partially corrected for a few others may occur.
C16: 5. Catastrophic | D16: The mission would not be achievable. | E16: We would not be able to grow. | F16: =IF(ISBLANK('1. Impact Criteria Survey '!E38),"",'1. Impact Criteria Survey '!E38) | G16: We would not be able to protect others from any degree of harm.
B20: 3 | C20: Expectancy Criteria
C22: Expectancy Score | D22: Expectancy | E22: Criteria
C23: 1 | D23: Remote | E23: Safeguard would reliably prevent the threat.
C24: 2 | D24: Unlikely | E24: Safeguard would reliably prevent most occurrences of the threat.
C25: 3 | D25: As likely as not | E25: Safeguard would prevent as many threat occurrences as it would miss.
C26: 4 | D26: Likely | E26: Safeguard would prevent few threat occurrences.
C27: 5 | D27: Certain | E27: Safeguard would not prevent threat occurrences.
B31: 4 | C31: Risk Acceptance Criteria
C33: We would start to invest against risks to prevent this expectancy and impact, or higher. | D33: Expectancy | E33: Impact
D35: Acceptable Risk is less than … | E35: =D34*E34 -> 0
B39: 5 | C39: Inherent Risk Criteria | D39: What is the highest impact to the Mission, Operational Objectives, Financial Objectives, and Obligations that each Asset Type could cause?
C41: Asset Class | D41: Mission Impact | E41: Operational Objectives Impact | F41: Financial Objectives Impact | G41: Obligations Impact
C42: Software
C43: Data
C44: Devices
C45: Network
C46: Users
C47: Documentation

Sheet 3. Risk Register Controls v8.1
B2: Enterprise Risk Assessment Criteria | C2: Enterprise Name | D2: =IF(ISBLANK('2. Enterprise Parameters'!E2),"",'2. Enterprise Parameters'!E2)
C3: Scope | D3: =IF(ISBLANK('2. Enterprise Parameters'!E3),"",'2. Enterprise Parameters'!E3)
C4: Last Completed (Date) | D4: =IF(ISBLANK('2. Enterprise Parameters'!E4),"",'2. Enterprise Parameters'!E4)
B8: Risk Register | C8: Risk Analysis | U8: Risk Register | V8: Risk Treatment | AL8: Reasonable Annual Cost
B10: Asset Class | C10: Asset Name | D10: CIS Safeguard | E10: CIS Safeguard Title | F10: IG1 | G10: IG2 | H10: NIST CSF Security Function | I10: Our Implementation | J10: Evidence of Implementation | K10: Vulnerabilities | L10: Safeguard Maturity Score | M10: VCDB Index | N10: Expectancy Score | O10: Impact to Mission | P10: Impact to Operational Objectives | Q10: Impact to Financial Objectives | R10: Impact to Obligations | S10: Risk Score | T10: Risk Level | U10: Risk Treatment Option | V10: Risk Treatment Safeguard | W10: Risk Treatment Safeguard Title | X10: Risk Treatment Safeguard Description | Y10: Our Planned Implementation | Z10: Risk Treatment Safeguard Maturity Score | AA10: Risk Treatment Safeguard Expectancy Score | AB10: Risk Treatment Safeguard Impact to Mission | AC10: Risk Treatment Safeguard Impact to Operational Objectives | AD10: Risk Treatment Safeguard Impact to Financial Objectives | AE10: Risk Treatment Safeguard Impact to Obligations | AF10: Risk Treatment Safeguard Risk Score | AG10: Reasonable and Acceptable | AH10: Risk Treatment Safeguard Cost | AI10: Implementation Quarter | AJ10: Implementation Year | AL10: Impact to Financial Objectives | AM10: Year | AN10: Reasonable?
B11: Devices | D11: 1.1 | E11: Establish and Maintain Detailed Enterprise Asset Inventory | F11: x | G11: x | H11: Identify | M11: =IFERROR(VLOOKUP(tblRiskRegister32[[#This Row],[Asset Class]],tblVCDBIndex[],4,FALSE),"") -> 4 | N11: =IFERROR(VLOOKUP(10*tblRiskRegister32[[#This Row],[Safeguard Maturity Score]]+tblRiskRegister32[[#This Row],[VCDB Index]],tblHITIndexWeightTable[],4,FALSE),"") | O11: =VLOOKUP(tblRiskRegister32[[#This Row],[Asset Class]],tblInherentImpacts30[],2,FALSE) -> 0 | P11: =VLOOKUP(tblRiskRegister32[[#This Row],[Asset Class]],tblInherentImpacts30[],3,FALSE) -> 0 | Q11: =VLOOKUP(tblRiskRegister32[[#This Row],[Asset Class]],tblInherentImpacts30[],4,FALSE) -> 0 | R11: =VLOOKUP(tblRiskRegister32[[#This Row],[Asset Class]],tblInherentImpacts30[],5,FALSE) -> 0 | S11: =IFERROR(MAX(tblRiskRegister32[[#This Row],[Impact to Mission]:[Impact to Obligations]])*tblRiskRegister32[[#This Row],[Expectancy Score]],"") | T11: =tblRiskRegister32[[#This Row],[Risk Score]] | V11: 1.1 | W11: Establish and Maintain Detailed Enterprise Asset Inventory | X11: Establish and maintain an accurate, detailed, and up-to-date inventory of all enterprise assets with the potential to store or process data, to include: end-user devices (including portable and mobile), network devices, non-computing/IoT devices, and servers. Ensure the inventory records the network address (if static), hardware address, machine name, enterprise asset owner, department for each asset, and whether the asset has been approved to connect to the network. For mobile end-user devices, MDM type tools can support this process, where appropriate. This inventory includes assets connected to the infrastructure physically, virtually, remotely, and those within cloud environments. Additionally, it includes assets that are regularly connected to the enterprise’s network infrastructure, even if they are not under control of the enterprise. Review and update the inventory of all enterprise assets bi-annually, or more frequently. | AA11: =IFERROR(VLOOKUP(10*tblRiskRegister32[[#This Row],[Risk Treatment Safeguard Maturity Score]]+tblRiskRegister32[[#This Row],[VCDB Index]],tblHITIndexWeightTable[],4,FALSE),"") | AB11: =VLOOKUP(tblRiskRegister32[[#This Row],[Asset Class]],tblInherentImpacts30[],2,FALSE) -> 0 | AC11: =VLOOKUP(tblRiskRegister32[[#This Row],[Asset Class]],tblInherentImpacts30[],3,FALSE) -> 0 | AD11: =VLOOKUP(tblRiskRegister32[[#This Row],[Asset Class]],tblInherentImpacts30[],4,FALSE) -> 0 | AE11: =VLOOKUP(tblRiskRegister32[[#This Row],[Asset Class]],tblInherentImpacts30[],5,FALSE) -> 0 | AF11: =IFERROR(MAX(tblRiskRegister32[[#This Row],[Risk Treatment Safeguard Impact to Mission]:[Risk Treatment Safeguard Impact to Obligations]])*tblRiskRegister32[[#This Row],[Risk Treatment Safeguard Expectancy Score]],"") | AG11: =IF(tblRiskRegister32[[#This Row],[Risk Score]]>=AcceptableRisk,IF(tblRiskRegister32[[#This Row],[Risk Treatment Safeguard Risk Score]]<AcceptableRisk, IF(tblRiskRegister32[[#This Row],[Risk Treatment Safeguard Risk Score]]<tblRiskRegister32[[#This Row],[Risk Score]],"Yes","No"),"No"),"Yes") -> No | AL11: =SUMIF(tblRiskRegister32[[#All],[Implementation Year]],"="&tblCostImpacts33[[#This Row],[Year]],tblRiskRegister32[[#All],[Risk Treatment Safeguard Cost]]) -> 0 | AM11: 2025 | AN11: =IF(tblCostImpacts33[[#This Row],[Impact to Financial Objectives]]<='2. Enterprise Parameters'!$F$13,"Yes","No") -> Yes
B12: Devices | D12: 1.2 | E12: Address Unauthorized Assets | F12: x | G12: x | H12: Respond | M12: =IFERROR(VLOOKUP(tblRiskRegister32[[#This Row],[Asset Class]],tblVCDBIndex[],4,FALSE),"") -> 4 | N12: =IFERROR(VLOOKUP(10*tblRiskRegister32[[#This Row],[Safeguard Maturity Score]]+tblRiskRegister32[[#This Row],[VCDB Index]],tblHITIndexWeightTable[],4,FALSE),"") | O12: =VLOOKUP(tblRiskRegister32[[#This Row],[Asset Class]],tblInherentImpacts30[],2,FALSE) -> 0 | P12: =VLOOKUP(tblRiskRegister32[[#This Row],[Asset Class]],tblInherentImpacts30[],3,FALSE) -> 0 | Q12: =VLOOKUP(tblRiskRegister32[[#This Row],[Asset Class]],tblInherentImpacts30[],4,FALSE) -> 0 | R12: =VLOOKUP(tblRiskRegister32[[#This Row],[Asset Class]],tblInherentImpacts30[],5,FALSE) -> 0 | S12: =IFERROR(MAX(tblRiskRegister32[[#This Row],[Impact to Mission]:[Impact to Obligations]])*tblRiskRegister32[[#This Row],[Expectancy Score]],"") | T12: =tblRiskRegister32[[#This Row],[Risk Score]] | V12: 1.2 | W12: Address Unauthorized Assets | X12: Ensure that a process exists to address unauthorized assets on a weekly basis. The enterprise may choose to remove the asset from the network, deny the asset from connecting remotely to the network, or quarantine the asset. | AA12: =IFERROR(VLOOKUP(10*tblRiskRegister32[[#This Row],[Risk Treatment Safeguard Maturity Score]]+tblRiskRegister32[[#This Row],[VCDB Index]],tblHITIndexWeightTable[],4,FALSE),"") | AB12: =VLOOKUP(tblRiskRegister32[[#This Row],[Asset Class]],tblInherentImpacts30[],2,FALSE) -> 0 | AC12: =VLOOKUP(tblRiskRegister32[[#This Row],[Asset Class]],tblInherentImpacts30[],3,FALSE) -> 0 | AD12: =VLOOKUP(tblRiskRegister32[[#This Row],[Asset Class]],tblInherentImpacts30[],4,FALSE) -> 0 | AE12: =VLOOKUP(tblRiskRegister32[[#This Row],[Asset Class]],tblInherentImpacts30[],5,FALSE) -> 0 | AF12: =IFERROR(MAX(tblRiskRegister32[[#This Row],[Risk Treatment Safeguard Impact to Mission]:[Risk Treatment Safeguard Impact to Obligations]])*tblRiskRegister32[[#This Row],[Risk Treatment Safeguard Expectancy Score]],"") | AG12: =IF(tblRiskRegister32[[#This Row],[Risk Score]]>=AcceptableRisk,IF(tblRiskRegister32[[#This Row],[Risk Treatment Safeguard Risk Score]]<AcceptableRisk, IF(tblRiskRegister32[[#This Row],[Risk Treatment Safeguard Risk Score]]<tblRiskRegister32[[#This Row],[Risk Score]],"Yes","No"),"No"),"Yes") -> No | AL12: =SUMIF(tblRiskRegister32[[#All],[Implementation Year]],"="&tblCostImpacts33[[#This Row],[Year]],tblRiskRegister32[[#All],[Risk Treatment Safeguard Cost]]) -> 0 | AM12: 2026 | AN12: =IF(tblCostImpacts33[[#This Row],[Impact to Financial Objectives]]<='2. Enterprise Parameters'!$F$13,"Yes","No") -> Yes
B13: Devices | D13: 1.3 | E13: Utilize an Active Discovery Tool | G13: x | H13: Detect | M13: =IFERROR(VLOOKUP(tblRiskRegister32[[#This Row],[Asset Class]],tblVCDBIndex[],4,FALSE),"") -> 4 | N13: =IFERROR(VLOOKUP(10*tblRiskRegister32[[#This Row],[Safeguard Maturity Score]]+tblRiskRegister32[[#This Row],[VCDB Index]],tblHITIndexWeightTable[],4,FALSE),"") | O13: =VLOOKUP(tblRiskRegister32[[#This Row],[Asset Class]],tblInherentImpacts30[],2,FALSE) -> 0 | P13: =VLOOKUP(tblRiskRegister32[[#This Row],[Asset Class]],tblInherentImpacts30[],3,FALSE) -> 0 | Q13: =VLOOKUP(tblRiskRegister32[[#This Row],[Asset Class]],tblInherentImpacts30[],4,FALSE) -> 0 | R13: =VLOOKUP(tblRiskRegister32[[#This Row],[Asset Class]],tblInherentImpacts30[],5,FALSE) -> 0 | S13: =IFERROR(MAX(tblRiskRegister32[[#This Row],[Impact to Mission]:[Impact to Obligations]])*tblRiskRegister32[[#This Row],[Expectancy Score]],"") | T13: =tblRiskRegister32[[#This Row],[Risk Score]] | V13: 1.3 | W13: Utilize an Active Discovery Tool | X13: Utilize an active discovery tool to identify assets connected to the enterprise’s network. Configure the active discovery tool to execute daily, or more frequently. | AA13: =IFERROR(VLOOKUP(10*tblRiskRegister32[[#This Row],[Risk Treatment Safeguard Maturity Score]]+tblRiskRegister32[[#This Row],[VCDB Index]],tblHITIndexWeightTable[],4,FALSE),"") | AB13: =VLOOKUP(tblRiskRegister32[[#This Row],[Asset Class]],tblInherentImpacts30[],2,FALSE) -> 0 | AC13: =VLOOKUP(tblRiskRegister32[[#This Row],[Asset Class]],tblInherentImpacts30[],3,FALSE) -> 0 | AD13: =VLOOKUP(tblRiskRegister32[[#This Row],[Asset Class]],tblInherentImpacts30[],4,FALSE) -> 0 | AE13: =VLOOKUP(tblRiskRegister32[[#This Row],[Asset Class]],tblInherentImpacts30[],5,FALSE) -> 0 | AF13: =IFERROR(MAX(tblRiskRegister32[[#This Row],[Risk Treatment Safeguard Impact to Mission]:[Risk Treatment Safeguard Impact to Obligations]])*tblRiskRegister32[[#This Row],[Risk Treatment Safeguard Expectancy Score]],"") | AG13: =IF(tblRiskRegister32[[#This Row],[Risk Score]]>=AcceptableRisk,IF(tblRiskRegister32[[#This Row],[Risk Treatment Safeguard Risk Score]]<AcceptableRisk, IF(tblRiskRegister32[[#This Row],[Risk Treatment Safeguard Risk Score]]<tblRiskRegister32[[#This Row],[Risk Score]],"Yes","No"),"No"),"Yes") -> No | AL13: =SUMIF(tblRiskRegister32[[#All],[Implementation Year]],"="&tblCostImpacts33[[#This Row],[Year]],tblRiskRegister32[[#All],[Risk Treatment Safeguard Cost]]) -> 0 | AM13: 2027 | AN13: =IF(tblCostImpacts33[[#This Row],[Impact to Financial Objectives]]<='2. Enterprise Parameters'!$F$13,"Yes","No") -> Yes
B14: Devices | D14: 1.4 | E14: Use Dynamic Host Configuration Protocol (DHCP) Logging to Update Enterprise Asset Inventory | G14: x | H14: Identify | M14: =IFERROR(VLOOKUP(tblRiskRegister32[[#This Row],[Asset Class]],tblVCDBIndex[],4,FALSE),"") -> 4 | N14: =IFERROR(VLOOKUP(10*tblRiskRegister32[[#This Row],[Safeguard Maturity Score]]+tblRiskRegister32[[#This Row],[VCDB Index]],tblHITIndexWeightTable[],4,FALSE),"") | O14: =VLOOKUP(tblRiskRegister32[[#This Row],[Asset Class]],tblInherentImpacts30[],2,FALSE) -> 0 | P14: =VLOOKUP(tblRiskRegister32[[#This Row],[Asset Class]],tblInherentImpacts30[],3,FALSE) -> 0 | Q14: =VLOOKUP(tblRiskRegister32[[#This Row],[Asset Class]],tblInherentImpacts30[],4,FALSE) -> 0 | R14: =VLOOKUP(tblRiskRegister32[[#This Row],[Asset Class]],tblInherentImpacts30[],5,FALSE) -> 0 | S14: =IFERROR(MAX(tblRiskRegister32[[#This Row],[Impact to Mission]:[Impact to Obligations]])*tblRiskRegister32[[#This Row],[Expectancy Score]],"") | T14: =tblRiskRegister32[[#This Row],[Risk Score]] | V14: 1.4 | W14: Use Dynamic Host Configuration Protocol (DHCP) Logging to Update Enterprise Asset Inventory | X14: Use DHCP logging on all DHCP servers or Internet Protocol (IP) address management tools to update the enterprise’s asset inventory. Review and use logs to update the enterprise’s asset inventory weekly, or more frequently. | AA14: =IFERROR(VLOOKUP(10*tblRiskRegister32[[#This Row],[Risk Treatment Safeguard Maturity Score]]+tblRiskRegister32[[#This Row],[VCDB Index]],tblHITIndexWeightTable[],4,FALSE),"") | AB14: =VLOOKUP(tblRiskRegister32[[#This Row],[Asset Class]],tblInherentImpacts30[],2,FALSE) -> 0 | AC14: =VLOOKUP(tblRiskRegister32[[#This Row],[Asset Class]],tblInherentImpacts30[],3,FALSE) -> 0 | AD14: =VLOOKUP(tblRiskRegister32[[#This Row],[Asset Class]],tblInherentImpacts30[],4,FALSE) -> 0 | AE14: =VLOOKUP(tblRiskRegister32[[#This Row],[Asset Class]],tblInherentImpacts30[],5,FALSE) -> 0 | AF14: =IFERROR(MAX(tblRiskRegister32[[#This Row],[Risk Treatment Safeguard Impact to Mission]:[Risk Treatment Safeguard Impact to Obligations]])*tblRiskRegister32[[#This Row],[Risk Treatment Safeguard Expectancy Score]],"") | AG14: =IF(tblRiskRegister32[[#This Row],[Risk Score]]>=AcceptableRisk,IF(tblRiskRegister32[[#This Row],[Risk Treatment Safeguard Risk Score]]<AcceptableRisk, IF(tblRiskRegister32[[#This Row],[Risk Treatment Safeguard Risk Score]]<tblRiskRegister32[[#This Row],[Risk Score]],"Yes","No"),"No"),"Yes") -> No | AL14: =SUMIF(tblRiskRegister32[[#All],[Implementation Year]],"="&tblCostImpacts33[[#This Row],[Year]],tblRiskRegister32[[#All],[Risk Treatment Safeguard Cost]]) -> 0 | AM14: 2028 | AN14: =IF(tblCostImpacts33[[#This Row],[Impact to Financial Objectives]]<='2. Enterprise Parameters'!$F$13,"Yes","No") -> Yes
B15: Software | D15: 2.1 | E15: Establish and Maintain a Software Inventory | F15: x | G15: x | H15: Identify | M15: =IFERROR(VLOOKUP(tblRiskRegister32[[#This Row],[Asset Class]],tblVCDBIndex[],4,FALSE),"") -> 2 | N15: =IFERROR(VLOOKUP(10*tblRiskRegister32[[#This Row],[Safeguard Maturity Score]]+tblRiskRegister32[[#This Row],[VCDB Index]],tblHITIndexWeightTable[],4,FALSE),"") | O15: =VLOOKUP(tblRiskRegister32[[#This Row],[Asset Class]],tblInherentImpacts30[],2,FALSE) -> 0 | P15: =VLOOKUP(tblRiskRegister32[[#This Row],[Asset Class]],tblInherentImpacts30[],3,FALSE) -> 0 | Q15: =VLOOKUP(tblRiskRegister32[[#This Row],[Asset Class]],tblInherentImpacts30[],4,FALSE) -> 0 | R15: =VLOOKUP(tblRiskRegister32[[#This Row],[Asset Class]],tblInherentImpacts30[],5,FALSE) -> 0 | S15: =IFERROR(MAX(tblRiskRegister32[[#This Row],[Impact to Mission]:[Impact to Obligations]])*tblRiskRegister32[[#This Row],[Expectancy Score]],"") | T15: =tblRiskRegister32[[#This Row],[Risk Score]] | V15: 2.1 | W15: Establish and Maintain a Software Inventory | X15: Establish and maintain a detailed inventory of all licensed software installed on enterprise assets. The software inventory must document the title, publisher, initial install/use date, and business purpose for each entry; where appropriate, include the Uniform Resource Locator (URL), app store(s), version(s), deployment mechanism, decommission date, and number of licenses. Review and update the software inventory bi-annually, or more frequently. | AA15: =IFERROR(VLOOKUP(10*tblRiskRegister32[[#This Row],[Risk Treatment Safeguard Maturity Score]]+tblRiskRegister32[[#This Row],[VCDB Index]],tblHITIndexWeightTable[],4,FALSE),"") | AB15: =VLOOKUP(tblRiskRegister32[[#This Row],[Asset Class]],tblInherentImpacts30[],2,FALSE) -> 0 | AC15: =VLOOKUP(tblRiskRegister32[[#This Row],[Asset Class]],tblInherentImpacts30[],3,FALSE) -> 0 | AD15: =VLOOKUP(tblRiskRegister32[[#This Row],[Asset Class]],tblInherentImpacts30[],4,FALSE) -> 0 | AE15: =VLOOKUP(tblRiskRegister32[[#This Row],[Asset Class]],tblInherentImpacts30[],5,FALSE) -> 0 | AF15: =IFERROR(MAX(tblRiskRegister32[[#This Row],[Risk Treatment Safeguard Impact to Mission]:[Risk Treatment Safeguard Impact to Obligations]])*tblRiskRegister32[[#This Row],[Risk Treatment Safeguard Expectancy Score]],"") | AG15: =IF(tblRiskRegister32[[#This Row],[Risk Score]]>=AcceptableRisk,IF(tblRiskRegister32[[#This Row],[Risk Treatment Safeguard Risk Score]]<AcceptableRisk, IF(tblRiskRegister32[[#This Row],[Risk Treatment Safeguard Risk Score]]<tblRiskRegister32[[#This Row],[Risk Score]],"Yes","No"),"No"),"Yes") -> No | AL15: =SUMIF(tblRiskRegister32[[#All],[Implementation Year]],"="&tblCostImpacts33[[#This Row],[Year]],tblRiskRegister32[[#All],[Risk Treatment Safeguard Cost]]) -> 0 | AM15: 2029 | AN15: =IF(tblCostImpacts33[[#This Row],[Impact to Financial Objectives]]<='2. Enterprise Parameters'!$F$13,"Yes","No") -> Yes
B16: Software | D16: 2.2 | E16: Ensure Authorized Software is Currently Supported | F16: x | G16: x | H16: Identify | M16: =IFERROR(VLOOKUP(tblRiskRegister32[[#This Row],[Asset Class]],tblVCDBIndex[],4,FALSE),"") -> 2 | N16: =IFERROR(VLOOKUP(10*tblRiskRegister32[[#This Row],[Safeguard Maturity Score]]+tblRiskRegister32[[#This Row],[VCDB Index]],tblHITIndexWeightTable[],4,FALSE),"") | O16: =VLOOKUP(tblRiskRegister32[[#This Row],[Asset Class]],tblInherentImpacts30[],2,FALSE) -> 0 | P16: =VLOOKUP(tblRiskRegister32[[#This Row],[Asset Class]],tblInherentImpacts30[],3,FALSE) -> 0 | Q16: =VLOOKUP(tblRiskRegister32[[#This Row],[Asset Class]],tblInherentImpacts30[],4,FALSE) -> 0 | R16: =VLOOKUP(tblRiskRegister32[[#This Row],[Asset Class]],tblInherentImpacts30[],5,FALSE) -> 0 | S16: =IFERROR(MAX(tblRiskRegister32[[#This Row],[Impact to Mission]:[Impact to Obligations]])*tblRiskRegister32[[#This Row],[Expectancy Score]],"") | T16: =tblRiskRegister32[[#This Row],[Risk Score]] | V16: 2.2 | W16: Ensure Authorized Software is Currently Supported | X16: Ensure that only currently supported software is designated as authorized in the software inventory for enterprise assets. If software is unsupported, yet necessary for the fulfillment of the enterprise’s mission, document an exception detailing mitigating controls and residual risk acceptance. For any unsupported software without an exception documentation, designate as unauthorized. Review the software list to verify software support at least monthly, or more frequently. | AA16: =IFERROR(VLOOKUP(10*tblRiskRegister32[[#This Row],[Risk Treatment Safeguard Maturity Score]]+tblRiskRegister32[[#This Row],[VCDB Index]],tblHITIndexWeightTable[],4,FALSE),"") | AB16: =VLOOKUP(tblRiskRegister32[[#This Row],[Asset Class]],tblInherentImpacts30[],2,FALSE) -> 0 | AC16: =VLOOKUP(tblRiskRegister32[[#This Row],[Asset Class]],tblInherentImpacts30[],3,FALSE) -> 0 | AD16: =VLOOKUP(tblRiskRegister32[[#This Row],[Asset Class]],tblInherentImpacts30[],4,FALSE) -> 0 | AE16: =VLOOKUP(tblRiskRegister32[[#This Row],[Asset Class]],tblInherentImpacts30[],5,FALSE) -> 0 | AF16: =IFERROR(MAX(tblRiskRegister32[[#This Row],[Risk Treatment Safeguard Impact to Mission]:[Risk Treatment Safeguard Impact to Obligations]])*tblRiskRegister32[[#This Row],[Risk Treatment Safeguard Expectancy Score]],"") | AG16: =IF(tblRiskRegister32[[#This Row],[Risk Score]]>=AcceptableRisk,IF(tblRiskRegister32[[#This Row],[Risk Treatment Safeguard Risk Score]]<AcceptableRisk, IF(tblRiskRegister32[[#This Row],[Risk Treatment Safeguard Risk Score]]<tblRiskRegister32[[#This Row],[Risk Score]],"Yes","No"),"No"),"Yes") -> No | AL16: =SUMIF(tblRiskRegister32[[#All],[Implementation Year]],"="&tblCostImpacts33[[#This Row],[Year]],tblRiskRegister32[[#All],[Risk Treatment Safeguard Cost]]) -> 0 | AM16: 2030 | AN16: =IF(tblCostImpacts33[[#This Row],[Impact to Financial Objectives]]<='2. Enterprise Parameters'!$F$13,"Yes","No") -> Yes
B17: Software | D17: 2.3 | E17: Address Unauthorized Software | F17: x | G17: x | H17: Respond | M17: =IFERROR(VLOOKUP(tblRiskRegister32[[#This Row],[Asset Class]],tblVCDBIndex[],4,FALSE),"") -> 2 | N17: =IFERROR(VLOOKUP(10*tblRiskRegister32[[#This Row],[Safeguard Maturity Score]]+tblRiskRegister32[[#This Row],[VCDB Index]],tblHITIndexWeightTable[],4,FALSE),"") | O17: =VLOOKUP(tblRiskRegister32[[#This Row],[Asset Class]],tblInherentImpacts30[],2,FALSE) -> 0 | P17: =VLOOKUP(tblRiskRegister32[[#This Row],[Asset Class]],tblInherentImpacts30[],3,FALSE) -> 0 | Q17: =VLOOKUP(tblRiskRegister32[[#This Row],[Asset Class]],tblInherentImpacts30[],4,FALSE) -> 0 | R17: =VLOOKUP(tblRiskRegister32[[#This Row],[Asset Class]],tblInherentImpacts30[],5,FALSE) -> 0 | S17: =IFERROR(MAX(tblRiskRegister32[[#This Row],[Impact to Mission]:[Impact to Obligations]])*tblRiskRegister32[[#This Row],[Expectancy Score]],"") | T17: =tblRiskRegister32[[#This Row],[Risk Score]] | V17: 2.3 | W17: Address Unauthorized Software | X17: Ensure that unauthorized software is either removed from use on enterprise assets or receives a documented exception. Review monthly, or more frequently. | AA17: =IFERROR(VLOOKUP(10*tblRiskRegister32[[#This Row],[Risk Treatment Safeguard Maturity Score]]+tblRiskRegister32[[#This Row],[VCDB Index]],tblHITIndexWeightTable[],4,FALSE),"") | AB17: =VLOOKUP(tblRiskRegister32[[#This Row],[Asset Class]],tblInherentImpacts30[],2,FALSE) -> 0 | AC17: =VLOOKUP(tblRiskRegister32[[#This Row],[Asset Class]],tblInherentImpacts30[],3,FALSE) -> 0 | AD17: =VLOOKUP(tblRiskRegister32[[#This Row],[Asset Class]],tblInherentImpacts30[],4,FALSE) -> 0 | AE17: =VLOOKUP(tblRiskRegister32[[#This Row],[Asset Class]],tblInherentImpacts30[],5,FALSE) -> 0 | AF17: =IFERROR(MAX(tblRiskRegister32[[#This Row],[Risk Treatment Safeguard Impact to Mission]:[Risk Treatment Safeguard Impact to Obligations]])*tblRiskRegister32[[#This Row],[Risk Treatment Safeguard Expectancy Score]],"") | AG17: =IF(tblRiskRegister32[[#This Row],[Risk Score]]>=AcceptableRisk,IF(tblRiskRegister32[[#This Row],[Risk Treatment Safeguard Risk Score]]<AcceptableRisk, IF(tblRiskRegister32[[#This Row],[Risk Treatment Safeguard Risk Score]]<tblRiskRegister32[[#This Row],[Risk Score]],"Yes","No"),"No"),"Yes") -> No | AL17: =SUMIF(tblRiskRegister32[[#All],[Implementation Year]],"="&tblCostImpacts33[[#This Row],[Year]],tblRiskRegister32[[#All],[Risk Treatment Safeguard Cost]]) -> 0 | AM17: 2031 | AN17: =IF(tblCostImpacts33[[#This Row],[Impact to Financial Objectives]]<='2. Enterprise Parameters'!$F$13,"Yes","No") -> Yes
B18: Software | D18: 2.4 | E18: Utilize Automated Software Inventory Tools | G18: x | H18: Detect | M18: =IFERROR(VLOOKUP(tblRiskRegister32[[#This Row],[Asset Class]],tblVCDBIndex[],4,FALSE),"") -> 2 | N18: =IFERROR(VLOOKUP(10*tblRiskRegister32[[#This Row],[Safeguard Maturity Score]]+tblRiskRegister32[[#This Row],[VCDB Index]],tblHITIndexWeightTable[],4,FALSE),"") | O18: =VLOOKUP(tblRiskRegister32[[#This Row],[Asset Class]],tblInherentImpacts30[],2,FALSE) -> 0 | P18: =VLOOKUP(tblRiskRegister32[[#This Row],[Asset Class]],tblInherentImpacts30[],3,FALSE) -> 0 | Q18: =VLOOKUP(tblRiskRegister32[[#This Row],[Asset Class]],tblInherentImpacts30[],4,FALSE) -> 0 | R18: =VLOOKUP(tblRiskRegister32[[#This Row],[Asset Class]],tblInherentImpacts30[],5,FALSE) -> 0 | S18: =IFERROR(MAX(tblRiskRegister32[[#This Row],[Impact to Mission]:[Impact to Obligations]])*tblRiskRegister32[[#This Row],[Expectancy Score]],"") | T18: =tblRiskRegister32[[#This Row],[Risk Score]] | V18: 2.4 | W18: Utilize Automated Software Inventory Tools | X18: Utilize software inventory tools, when possible, throughout the enterprise to automate the discovery and documentation of installed software. | AA18: =IFERROR(VLOOKUP(10*tblRiskRegister32[[#This Row],[Risk Treatment Safeguard Maturity Score]]+tblRiskRegister32[[#This Row],[VCDB Index]],tblHITIndexWeightTable[],4,FALSE),"") | AB18: =VLOOKUP(tblRiskRegister32[[#This Row],[Asset Class]],tblInherentImpacts30[],2,FALSE) -> 0 | AC18: =VLOOKUP(tblRiskRegister32[[#This Row],[Asset Class]],tblInherentImpacts30[],3,FALSE) -> 0 | AD18: =VLOOKUP(tblRiskRegister32[[#This Row],[Asset Class]],tblInherentImpacts30[],4,FALSE) -> 0 | AE18: =VLOOKUP(tblRiskRegister32[[#This Row],[Asset Class]],tblInherentImpacts30[],5,FALSE) -> 0 | AF18: =IFERROR(MAX(tblRiskRegister32[[#This Row],[Risk Treatment Safeguard Impact to Mission]:[Risk Treatment Safeguard Impact to Obligations]])*tblRiskRegister32[[#This Row],[Risk Treatment Safeguard Expectancy Score]],"") | AG18: =IF(tblRiskRegister32[[#This Row],[Risk Score]]>=AcceptableRisk,IF(tblRiskRegister32[[#This Row],[Risk Treatment Safeguard Risk Score]]<AcceptableRisk, IF(tblRiskRegister32[[#This Row],[Risk Treatment Safeguard Risk Score]]<tblRiskRegister32[[#This Row],[Risk Score]],"Yes","No"),"No"),"Yes") -> No | AL18: =SUMIF(tblRiskRegister32[[#All],[Implementation Year]],"="&tblCostImpacts33[[#This Row],[Year]],tblRiskRegister32[[#All],[Risk Treatment Safeguard Cost]]) -> 0 | AM18: 2032 | AN18: =IF(tblCostImpacts33[[#This Row],[Impact to Financial Objectives]]<='2. Enterprise Parameters'!$F$13,"Yes","No") -> Yes
B19: Software | D19: 2.5 | E19: Allowlist Authorized Software | G19: x | H19: Protect | M19: =IFERROR(VLOOKUP(tblRiskRegister32[[#This Row],[Asset Class]],tblVCDBIndex[],4,FALSE),"") -> 2 | N19: =IFERROR(VLOOKUP(10*tblRiskRegister32[[#This Row],[Safeguard Maturity Score]]+tblRiskRegister32[[#This Row],[VCDB Index]],tblHITIndexWeightTable[],4,FALSE),"") | O19: =VLOOKUP(tblRiskRegister32[[#This Row],[Asset Class]],tblInherentImpacts30[],2,FALSE) -> 0 | P19: =VLOOKUP(tblRiskRegister32[[#This Row],[Asset Class]],tblInherentImpacts30[],3,FALSE) -> 0 | Q19: =VLOOKUP(tblRiskRegister32[[#This Row],[Asset Class]],tblInherentImpacts30[],4,FALSE) -> 0 | R19: =VLOOKUP(tblRiskRegister32[[#This Row],[Asset Class]],tblInherentImpacts30[],5,FALSE) -> 0 | S19: =IFERROR(MAX(tblRiskRegister32[[#This Row],[Impact to Mission]:[Impact to Obligations]])*tblRiskRegister32[[#This Row],[Expectancy Score]],"") | T19: =tblRiskRegister32[[#This Row],[Risk Score]] | V19: 2.5 | W19: Allowlist Authorized Software | X19: Use technical controls, such as application allowlisting, to ensure that only authorized software can execute or be accessed. Reassess bi-annually, or more frequently. | AA19: =IFERROR(VLOOKUP(10*tblRiskRegister32[[#This Row],[Risk Treatment Safeguard Maturity Score]]+tblRiskRegister32[[#This Row],[VCDB Index]],tblHITIndexWeightTable[],4,FALSE),"") | AB19: =VLOOKUP(tblRiskRegister32[[#This Row],[Asset Class]],tblInherentImpacts30[],2,FALSE) -> 0 | AC19: =VLOOKUP(tblRiskRegister32[[#This Row],[Asset Class]],tblInherentImpacts30[],3,FALSE) -> 0 | AD19: =VLOOKUP(tblRiskRegister32[[#This Row],[Asset Class]],tblInherentImpacts30[],4,FALSE) -> 0 | AE19: =VLOOKUP(tblRiskRegister32[[#This Row],[Asset Class]],tblInherentImpacts30[],5,FALSE) -> 0 | AF19: =IFERROR(MAX(tblRiskRegister32[[#This Row],[Risk Treatment Safeguard Impact to Mission]:[Risk Treatment Safeguard Impact to Obligations]])*tblRiskRegister32[[#This Row],[Risk Treatment Safeguard Expectancy Score]],"") | AG19: =IF(tblRiskRegister32[[#This Row],[Risk Score]]>=AcceptableRisk,IF(tblRiskRegister32[[#This Row],[Risk Treatment Safeguard Risk Score]]<AcceptableRisk, IF(tblRiskRegister32[[#This Row],[Risk Treatment Safeguard Risk Score]]<tblRiskRegister32[[#This Row],[Risk Score]],"Yes","No"),"No"),"Yes") -> No | AL19: =SUMIF(tblRiskRegister32[[#All],[Implementation Year]],"="&tblCostImpacts33[[#This Row],[Year]],tblRiskRegister32[[#All],[Risk Treatment Safeguard Cost]]) -> 0 | AM19: 2033 | AN19: =IF(tblCostImpacts33[[#This Row],[Impact to Financial Objectives]]<='2. Enterprise Parameters'!$F$13,"Yes","No") -> Yes
B20: Software | D20: 2.6 | E20: Allowlist Authorized Libraries | G20: x | H20: Protect | M20: =IFERROR(VLOOKUP(tblRiskRegister32[[#This Row],[Asset Class]],tblVCDBIndex[],4,FALSE),"") -> 2 | N20: =IFERROR(VLOOKUP(10*tblRiskRegister32[[#This Row],[Safeguard Maturity Score]]+tblRiskRegister32[[#This Row],[VCDB Index]],tblHITIndexWeightTable[],4,FALSE),"") | O20: =VLOOKUP(tblRiskRegister32[[#This Row],[Asset Class]],tblInherentImpacts30[],2,FALSE) -> 0 | P20: =VLOOKUP(tblRiskRegister32[[#This Row],[Asset Class]],tblInherentImpacts30[],3,FALSE) -> 0 | Q20: =VLOOKUP(tblRiskRegister32[[#This Row],[Asset Class]],tblInherentImpacts30[],4,FALSE) -> 0 | R20: =VLOOKUP(tblRiskRegister32[[#This Row],[Asset Class]],tblInherentImpacts30[],5,FALSE) -> 0 | S20: =IFERROR(MAX(tblRiskRegister32[[#This Row],[Impact to Mission]:[Impact to Obligations]])*tblRiskRegister32[[#This Row],[Expectancy Score]],"") | T20: =tblRiskRegister32[[#This Row],[Risk Score]] | V20: 4.1 | W20: Establish and Maintain a Secure Configuration Process | X20: Use technical controls to ensure that only authorized software libraries, such as specific .dll, .ocx, and .so files, are allowed to load into a system process. Block unauthorized libraries from loading into a system process. Reassess bi-annually, or more frequently. | AA20: =IFERROR(VLOOKUP(10*tblRiskRegister32[[#This Row],[Risk Treatment Safeguard Maturity Score]]+tblRiskRegister32[[#This Row],[VCDB Index]],tblHITIndexWeightTable[],4,FALSE),"") | AB20: =VLOOKUP(tblRiskRegister32[[#This Row],[Asset Class]],tblInherentImpacts30[],2,FALSE) -> 0 | AC20: =VLOOKUP(tblRiskRegister32[[#This Row],[Asset Class]],tblInherentImpacts30[],3,FALSE) -> 0 | AD20: =VLOOKUP(tblRiskRegister32[[#This Row],[Asset Class]],tblInherentImpacts30[],4,FALSE) -> 0 | AE20: =VLOOKUP(tblRiskRegister32[[#This Row],[Asset Class]],tblInherentImpacts30[],5,FALSE) -> 0 | AF20: =IFERROR(MAX(tblRiskRegister32[[#This Row],[Risk Treatment Safeguard Impact to Mission]:[Risk Treatment Safeguard Impact to Obligations]])*tblRiskRegister32[[#This Row],[Risk Treatment Safeguard Expectancy Score]],"") | AG20: =IF(tblRiskRegister32[[#This Row],[Risk Score]]>=AcceptableRisk,IF(tblRiskRegister32[[#This Row],[Risk Treatment Safeguard Risk Score]]<AcceptableRisk, IF(tblRiskRegister32[[#This Row],[Risk Treatment Safeguard Risk Score]]<tblRiskRegister32[[#This Row],[Risk Score]],"Yes","No"),"No"),"Yes") -> No | AL20: =SUMIF(tblRiskRegister32[[#All],[Implementation Year]],"="&tblCostImpacts33[[#This Row],[Year]],tblRiskRegister32[[#All],[Risk Treatment Safeguard Cost]]) -> 0 | AM20: 2034 | AN20: =IF(tblCostImpacts33[[#This Row],[Impact to Financial Objectives]]<='2. Enterprise Parameters'!$F$13,"Yes","No") -> Yes
B21: Data | D21: 3.1 | E21: Establish and Maintain a Data Management Process | F21: x | G21: x | H21: Govern | M21: =IFERROR(VLOOKUP(tblRiskRegister32[[#This Row],[Asset Class]],tblVCDBIndex[],4,FALSE),"") -> 2 | N21: =IFERROR(VLOOKUP(10*tblRiskRegister32[[#This Row],[Safeguard Maturity Score]]+tblRiskRegister32[[#This Row],[VCDB Index]],tblHITIndexWeightTable[],4,FALSE),"") | O21: =VLOOKUP(tblRiskRegister32[[#This Row],[Asset Class]],tblInherentImpacts30[],2,FALSE) -> 0 | P21: =VLOOKUP(tblRiskRegister32[[#This Row],[Asset Class]],tblInherentImpacts30[],3,FALSE) -> 0 | Q21: =VLOOKUP(tblRiskRegister32[[#This Row],[Asset Class]],tblInherentImpacts30[],4,FALSE) -> 0 | R21: =VLOOKUP(tblRiskRegister32[[#This Row],[Asset Class]],tblInherentImpacts30[],5,FALSE) -> 0 | S21: =IFERROR(MAX(tblRiskRegister32[[#This Row],[Impact to Mission]:[Impact to Obligations]])*tblRiskRegister32[[#This Row],[Expectancy Score]],"") | T21: =tblRiskRegister32[[#This Row],[Risk Score]] | V21: 3.1 | W21: Establish and Maintain a Data Management Process | X21: Establish and maintain a documented data management process. In the process, address data sensitivity, data owner, handling of data, data retention limits, and disposal requirements, based on sensitivity and retention standards for the enterprise. Review and update documentation annually, or when significant enterprise changes occur that could impact this Safeguard. | AA21: =IFERROR(VLOOKUP(10*tblRiskRegister32[[#This Row],[Risk Treatment Safeguard Maturity Score]]+tblRiskRegister32[[#This Row],[VCDB Index]],tblHITIndexWeightTable[],4,FALSE),"") | AB21: =VLOOKUP(tblRiskRegister32[[#This Row],[Asset Class]],tblInherentImpacts30[],2,FALSE) -> 0 | AC21: =VLOOKUP(tblRiskRegister32[[#This Row],[Asset Class]],tblInherentImpacts30[],3,FALSE) -> 0 | AD21: =VLOOKUP(tblRiskRegister32[[#This Row],[Asset Class]],tblInherentImpacts30[],4,FALSE) -> 0 | AE21: =VLOOKUP(tblRiskRegister32[[#This Row],[Asset Class]],tblInherentImpacts30[],5,FALSE) -> 0 | AF21: =IFERROR(MAX(tblRiskRegister32[[#This Row],[Risk Treatment Safeguard Impact to Mission]:[Risk Treatment Safeguard Impact to Obligations]])*tblRiskRegister32[[#This Row],[Risk Treatment Safeguard Expectancy Score]],"") | AG21: =IF(tblRiskRegister32[[#This Row],[Risk Score]]>=AcceptableRisk,IF(tblRiskRegister32[[#This Row],[Risk Treatment Safeguard Risk Score]]<AcceptableRisk, IF(tblRiskRegister32[[#This Row],[Risk Treatment Safeguard Risk Score]]<tblRiskRegister32[[#This Row],[Risk Score]],"Yes","No"),"No"),"Yes") -> No
B22: Data | D22: 3.2 | E22: Establish and Maintain a Data Inventory | F22: x | G22: x | H22: Identify | M22: =IFERROR(VLOOKUP(tblRiskRegister32[[#This Row],[Asset Class]],tblVCDBIndex[],4,FALSE),"") -> 2 | N22: =IFERROR(VLOOKUP(10*tblRiskRegister32[[#This Row],[Safeguard Maturity Score]]+tblRiskRegister32[[#This Row],[VCDB Index]],tblHITIndexWeightTable[],4,FALSE),"") | O22: =VLOOKUP(tblRiskRegister32[[#This Row],[Asset Class]],tblInherentImpacts30[],2,FALSE) -> 0 | P22: =VLOOKUP(tblRiskRegister32[[#This Row],[Asset Class]],tblInherentImpacts30[],3,FALSE) -> 0 | Q22: =VLOOKUP(tblRiskRegister32[[#This Row],[Asset Class]],tblInherentImpacts30[],4,FALSE) -> 0 | R22: =VLOOKUP(tblRiskRegister32[[#This Row],[Asset Class]],tblInherentImpacts30[],5,FALSE) -> 0 | S22: =IFERROR(MAX(tblRiskRegister32[[#This Row],[Impact to Mission]:[Impact to Obligations]])*tblRiskRegister32[[#This Row],[Expectancy Score]],"") | T22: =tblRiskRegister32[[#This Row],[Risk Score]] | V22: 3.2 | W22: Establish and Maintain a Data Inventory | X22: Establish and maintain a data inventory based on the enterprise’s data management process. Inventory sensitive data, at a minimum. Review and update inventory annually, at a minimum, with a priority on sensitive data. | AA22: =IFERROR(VLOOKUP(10*tblRiskRegister32[[#This Row],[Risk Treatment Safeguard Maturity Score]]+tblRiskRegister32[[#This Row],[VCDB Index]],tblHITIndexWeightTable[],4,FALSE),"") | AB22: =VLOOKUP(tblRiskRegister32[[#This Row],[Asset Class]],tblInherentImpacts30[],2,FALSE) -> 0 | AC22: =VLOOKUP(tblRiskRegister32[[#This Row],[Asset Class]],tblInherentImpacts30[],3,FALSE) -> 0 | AD22: =VLOOKUP(tblRiskRegister32[[#This Row],[Asset Class]],tblInherentImpacts30[],4,FALSE) -> 0 | AE22: =VLOOKUP(tblRiskRegister32[[#This Row],[Asset Class]],tblInherentImpacts30[],5,FALSE) -> 0 | AF22: =IFERROR(MAX(tblRiskRegister32[[#This Row],[Risk Treatment Safeguard Impact to Mission]:[Risk Treatment Safeguard Impact to Obligations]])*tblRiskRegister32[[#This Row],[Risk Treatment Safeguard Expectancy Score]],"") | AG22: =IF(tblRiskRegister32[[#This Row],[Risk Score]]>=AcceptableRisk,IF(tblRiskRegister32[[#This Row],[Risk Treatment Safeguard Risk Score]]<AcceptableRisk, IF(tblRiskRegister32[[#This Row],[Risk Treatment Safeguard Risk Score]]<tblRiskRegister32[[#This Row],[Risk Score]],"Yes","No"),"No"),"Yes") -> No
B23: Data | D23: 3.3 | E23: Configure Data Access Control Lists | F23: x | G23: x | H23: Protect | M23: =IFERROR(VLOOKUP(tblRiskRegister32[[#This Row],[Asset Class]],tblVCDBIndex[],4,FALSE),"") -> 2 | N23: =IFERROR(VLOOKUP(10*tblRiskRegister32[[#This Row],[Safeguard Maturity Score]]+tblRiskRegister32[[#This Row],[VCDB Index]],tblHITIndexWeightTable[],4,FALSE),"") | O23: =VLOOKUP(tblRiskRegister32[[#This Row],[Asset Class]],tblInherentImpacts30[],2,FALSE) -> 0 | P23: =VLOOKUP(tblRiskRegister32[[#This Row],[Asset Class]],tblInherentImpacts30[],3,FALSE) -> 0 | Q23: =VLOOKUP(tblRiskRegister32[[#This Row],[Asset Class]],tblInherentImpacts30[],4,FALSE) -> 0 | R23: =VLOOKUP(tblRiskRegister32[[#This Row],[Asset Class]],tblInherentImpacts30[],5,FALSE) -> 0 | S23: =IFERROR(MAX(tblRiskRegister32[[#This Row],[Impact to Mission]:[Impact to Obligations]])*tblRiskRegister32[[#This Row],[Expectancy Score]],"") | T23: =tblRiskRegister32[[#This Row],[Risk Score]] | V23: 3.3 | W23: Configure Data Access Control Lists | X23: Configure data access control lists based on a user’s need to know. Apply data access control lists, also known as access permissions, to local and remote file systems, databases, and applications. | AA23: =IFERROR(VLOOKUP(10*tblRiskRegister32[[#This Row],[Risk Treatment Safeguard Maturity Score]]+tblRiskRegister32[[#This Row],[VCDB Index]],tblHITIndexWeightTable[],4,FALSE),"") | AB23: =VLOOKUP(tblRiskRegister32[[#This Row],[Asset Class]],tblInherentImpacts30[],2,FALSE) -> 0 | AC23: =VLOOKUP(tblRiskRegister32[[#This Row],[Asset Class]],tblInherentImpacts30[],3,FALSE) -> 0 | AD23: =VLOOKUP(tblRiskRegister32[[#This Row],[Asset Class]],tblInherentImpacts30[],4,FALSE) -> 0 | AE23: =VLOOKUP(tblRiskRegister32[[#This Row],[Asset Class]],tblInherentImpacts30[],5,FALSE) -> 0 | AF23: =IFERROR(MAX(tblRiskRegister32[[#This Row],[Risk Treatment Safeguard Impact to Mission]:[Risk Treatment Safeguard Impact to Obligations]])*tblRiskRegister32[[#This Row],[Risk Treatment Safeguard Expectancy Score]],"") | AG23: =IF(tblRiskRegister32[[#This Row],[Risk Score]]>=AcceptableRisk,IF(tblRiskRegister32[[#This Row],[Risk Treatment Safeguard Risk Score]]<AcceptableRisk, IF(tblRiskRegister32[[#This Row],[Risk Treatment Safeguard Risk Score]]<tblRiskRegister32[[#This Row],[Risk Score]],"Yes","No"),"No"),"Yes") -> No
B24: Data | D24: 3.4 | E24: Enforce Data Retention | F24: x | G24: x | H24: Protect | M24: =IFERROR(VLOOKUP(tblRiskRegister32[[#This Row],[Asset Class]],tblVCDBIndex[],4,FALSE),"") -> 2 | N24: =IFERROR(VLOOKUP(10*tblRiskRegister32[[#This Row],[Safeguard Maturity Score]]+tblRiskRegister32[[#This Row],[VCDB Index]],tblHITIndexWeightTable[],4,FALSE),"") | O24: =VLOOKUP(tblRiskRegister32[[#This Row],[Asset Class]],tblInherentImpacts30[],2,FALSE) -> 0 | P24: =VLOOKUP(tblRiskRegister32[[#This Row],[Asset Class]],tblInherentImpacts30[],3,FALSE) -> 0 | Q24: =VLOOKUP(tblRiskRegister32[[#This Row],[Asset Class]],tblInherentImpacts30[],4,FALSE) -> 0 | R24: =VLOOKUP(tblRiskRegister32[[#This Row],[Asset Class]],tblInherentImpacts30[],5,FALSE) -> 0 | S24: =IFERROR(MAX(tblRiskRegister32[[#This Row],[Impact to Mission]:[Impact to Obligations]])*tblRiskRegister32[[#This Row],[Expectancy Score]],"") | T24: =tblRiskRegister32[[#This Row],[Risk Score]] | V24: 3.4 | W24: Enforce Data Retention | X24: Retain data according to the enterprise’s documented data management process. Data retention must include both minimum and maximum timelines. | AA24: =IFERROR(VLOOKUP(10*tblRiskRegister32[[#This Row],[Risk Treatment Safeguard Maturity Score]]+tblRiskRegister32[[#This Row],[VCDB Index]],tblHITIndexWeightTable[],4,FALSE),"") | AB24: =VLOOKUP(tblRiskRegister32[[#This Row],[Asset Class]],tblInherentImpacts30[],2,FALSE) -> 0 | AC24: =VLOOKUP(tblRiskRegister32[[#This Row],[Asset Class]],tblInherentImpacts30[],3,FALSE) -> 0 | AD24: =VLOOKUP(tblRiskRegister32[[#This Row],[Asset Class]],tblInherentImpacts30[],4,FALSE) -> 0 | AE24: =VLOOKUP(tblRiskRegister32[[#This Row],[Asset Class]],tblInherentImpacts30[],5,FALSE) -> 0 | AF24: =IFERROR(MAX(tblRiskRegister32[[#This Row],[Risk Treatment Safeguard Impact to Mission]:[Risk Treatment Safeguard Impact to Obligations]])*tblRiskRegister32[[#This Row],[Risk Treatment Safeguard Expectancy Score]],"") | AG24: =IF(tblRiskRegister32[[#This Row],[Risk Score]]>=AcceptableRisk,IF(tblRiskRegister32[[#This Row],[Risk Treatment Safeguard Risk Score]]<AcceptableRisk, IF(tblRiskRegister32[[#This Row],[Risk Treatment Safeguard Risk Score]]<tblRiskRegister32[[#This Row],[Risk Score]],"Yes","No"),"No"),"Yes") -> No
B25: Data | D25: 3.5 | E25: Securely Dispose of Data | F25: x | G25: x | H25: Protect | M25: =IFERROR(VLOOKUP(tblRiskRegister32[[#This Row],[Asset Class]],tblVCDBIndex[],4,FALSE),"") -> 2 | N25: =IFERROR(VLOOKUP(10*tblRiskRegister32[[#This Row],[Safeguard Maturity Score]]+tblRiskRegister32[[#This Row],[VCDB Index]],tblHITIndexWeightTable[],4,FALSE),"") | O25: =VLOOKUP(tblRiskRegister32[[#This Row],[Asset Class]],tblInherentImpacts30[],2,FALSE) -> 0 | P25: =VLOOKUP(tblRiskRegister32[[#This Row],[Asset Class]],tblInherentImpacts30[],3,FALSE) -> 0 | Q25: =VLOOKUP(tblRiskRegister32[[#This Row],[Asset Class]],tblInherentImpacts30[],4,FALSE) -> 0 | R25: =VLOOKUP(tblRiskRegister32[[#This Row],[Asset Class]],tblInherentImpacts30[],5,FALSE) -> 0 | S25: =IFERROR(MAX(tblRiskRegister32[[#This Row],[Impact to Mission]:[Impact to Obligations]])*tblRiskRegister32[[#This Row],[Expectancy Score]],"") | T25: =tblRiskRegister32[[#This Row],[Risk Score]] | V25: 3.5 | W25: Securely Dispose of Data | X25: Securely dispose of data as outlined in the enterprise’s documented data management process. Ensure the disposal process and method are commensurate with the data sensitivity. | AA25: =IFERROR(VLOOKUP(10*tblRiskRegister32[[#This Row],[Risk Treatment Safeguard Maturity Score]]+tblRiskRegister32[[#This Row],[VCDB Index]],tblHITIndexWeightTable[],4,FALSE),"") | AB25: =VLOOKUP(tblRiskRegister32[[#This Row],[Asset Class]],tblInherentImpacts30[],2,FALSE) -> 0 | AC25: =VLOOKUP(tblRiskRegister32[[#This Row],[Asset Class]],tblInherentImpacts30[],3,FALSE) -> 0 | AD25: =VLOOKUP(tblRiskRegister32[[#This Row],[Asset Class]],tblInherentImpacts30[],4,FALSE) -> 0 | AE25: =VLOOKUP(tblRiskRegister32[[#This Row],[Asset Class]],tblInherentImpacts30[],5,FALSE) -> 0 | AF25: =IFERROR(MAX(tblRiskRegister32[[#This Row],[Risk Treatment Safeguard Impact to Mission]:[Risk Treatment Safeguard Impact to Obligations]])*tblRiskRegister32[[#This Row],[Risk Treatment Safeguard Expectancy Score]],"") | AG25: =IF(tblRiskRegister32[[#This Row],[Risk Score]]>=AcceptableRisk,IF(tblRiskRegister32[[#This Row],[Risk Treatment Safeguard Risk Score]]<AcceptableRisk, IF(tblRiskRegister32[[#This Row],[Risk Treatment Safeguard Risk Score]]<tblRiskRegister32[[#This Row],[Risk Score]],"Yes","No"),"No"),"Yes") -> No
B26: Data | D26: 3.6 | E26: Encrypt Data on End-User Devices | F26: x | G26: x | H26: Protect | M26: =IFERROR(VLOOKUP(tblRiskRegister32[[#This Row],[Asset Class]],tblVCDBIndex[],4,FALSE),"") -> 2 | N26: =IFERROR(VLOOKUP(10*tblRiskRegister32[[#This Row],[Safeguard Maturity Score]]+tblRiskRegister32[[#This Row],[VCDB Index]],tblHITIndexWeightTable[],4,FALSE),"") | O26: =VLOOKUP(tblRiskRegister32[[#This Row],[Asset Class]],tblInherentImpacts30[],2,FALSE) -> 0 | P26: =VLOOKUP(tblRiskRegister32[[#This Row],[Asset Class]],tblInherentImpacts30[],3,FALSE) -> 0 | Q26: =VLOOKUP(tblRiskRegister32[[#This Row],[Asset Class]],tblInherentImpacts30[],4,FALSE) -> 0 | R26: =VLOOKUP(tblRiskRegister32[[#This Row],[Asset Class]],tblInherentImpacts30[],5,FALSE) -> 0 | S26: =IFERROR(MAX(tblRiskRegister32[[#This Row],[Impact to Mission]:[Impact to Obligations]])*tblRiskRegister32[[#This Row],[Expectancy Score]],"") | T26: =tblRiskRegister32[[#This Row],[Risk Score]] | V26: 3.6 | W26: Encrypt Data on End-User Devices | X26: Encrypt data on end-user devices containing sensitive data. Example implementations can include: Windows BitLocker®, Apple FileVault®, Linux® dm-crypt. | AA26: =IFERROR(VLOOKUP(10*tblRiskRegister32[[#This Row],[Risk Treatment Safeguard Maturity Score]]+tblRiskRegister32[[#This Row],[VCDB Index]],tblHITIndexWeightTable[],4,FALSE),"") | AB26: =VLOOKUP(tblRiskRegister32[[#This Row],[Asset Class]],tblInherentImpacts30[],2,FALSE) -> 0 | AC26: =VLOOKUP(tblRiskRegister32[[#This Row],[Asset Class]],tblInherentImpacts30[],3,FALSE) -> 0 | AD26: =VLOOKUP(tblRiskRegister32[[#This Row],[Asset Class]],tblInherentImpacts30[],4,FALSE) -> 0 | AE26: =VLOOKUP(tblRiskRegister32[[#This Row],[Asset Class]],tblInherentImpacts30[],5,FALSE) -> 0 | AF26: =IFERROR(MAX(tblRiskRegister32[[#This Row],[Risk Treatment Safeguard Impact to Mission]:[Risk Treatment Safeguard Impact to Obligations]])*tblRiskRegister32[[#This Row],[Risk Treatment Safeguard Expectancy Score]],"") | AG26: =IF(tblRiskRegister32[[#This Row],[Risk Score]]>=AcceptableRisk,IF(tblRiskRegister32[[#This Row],[Risk Treatment Safeguard Risk Score]]<AcceptableRisk, IF(tblRiskRegister32[[#This Row],[Risk Treatment Safeguard Risk Score]]<tblRiskRegister32[[#This Row],[Risk Score]],"Yes","No"),"No"),"Yes") -> No
B27: Data | D27: 3.7 | E27: Establish and Maintain a Data Classification Scheme | G27: x | H27: Identify | M27: =IFERROR(VLOOKUP(tblRiskRegister32[[#This Row],[Asset Class]],tblVCDBIndex[],4,FALSE),"") -> 2 | N27: =IFERROR(VLOOKUP(10*tblRiskRegister32[[#This Row],[Safeguard Maturity Score]]+tblRiskRegister32[[#This Row],[VCDB Index]],tblHITIndexWeightTable[],4,FALSE),"") | O27: =VLOOKUP(tblRiskRegister32[[#This Row],[Asset Class]],tblInherentImpacts30[],2,FALSE) -> 0 | P27: =VLOOKUP(tblRiskRegister32[[#This Row],[Asset Class]],tblInherentImpacts30[],3,FALSE) -> 0 | Q27: =VLOOKUP(tblRiskRegister32[[#This Row],[Asset Class]],tblInherentImpacts30[],4,FALSE) -> 0 | R27: =VLOOKUP(tblRiskRegister32[[#This Row],[Asset Class]],tblInherentImpacts30[],5,FALSE) -> 0 | S27: =IFERROR(MAX(tblRiskRegister32[[#This Row],[Impact to Mission]:[Impact to Obligations]])*tblRiskRegister32[[#This Row],[Expectancy Score]],"") | T27: =tblRiskRegister32[[#This Row],[Risk Score]] | V27: 3.7 | W27: Establish and Maintain a Data Classification Scheme | X27: Establish and maintain an overall data classification scheme for the enterprise. Enterprises may use labels, such as “Sensitive,” “Confidential,” and “Public,” and classify their data according to those labels. Review and update the classification scheme annually, or when significant enterprise changes occur that could impact this Safeguard. | AA27: =IFERROR(VLOOKUP(10*tblRiskRegister32[[#This Row],[Risk Treatment Safeguard Maturity Score]]+tblRiskRegister32[[#This Row],[VCDB Index]],tblHITIndexWeightTable[],4,FALSE),"") | AB27: =VLOOKUP(tblRiskRegister32[[#This Row],[Asset Class]],tblInherentImpacts30[],2,FALSE) -> 0 | AC27: =VLOOKUP(tblRiskRegister32[[#This Row],[Asset Class]],tblInherentImpacts30[],3,FALSE) -> 0 | AD27: =VLOOKUP(tblRiskRegister32[[#This Row],[Asset Class]],tblInherentImpacts30[],4,FALSE) -> 0 | AE27: =VLOOKUP(tblRiskRegister32[[#This Row],[Asset Class]],tblInherentImpacts30[],5,FALSE) -> 0 | AF27: =IFERROR(MAX(tblRiskRegister32[[#This Row],[Risk Treatment Safeguard Impact to Mission]:[Risk Treatment Safeguard Impact to Obligations]])*tblRiskRegister32[[#This Row],[Risk Treatment Safeguard Expectancy Score]],"") | AG27: =IF(tblRiskRegister32[[#This Row],[Risk Score]]>=AcceptableRisk,IF(tblRiskRegister32[[#This Row],[Risk Treatment Safeguard Risk Score]]<AcceptableRisk, IF(tblRiskRegister32[[#This Row],[Risk Treatment Safeguard Risk Score]]<tblRiskRegister32[[#This Row],[Risk Score]],"Yes","No"),"No"),"Yes") -> No
B28: Data | D28: 3.8 | E28: Document Data Flows | G28: x | H28: Identify | M28: =IFERROR(VLOOKUP(tblRiskRegister32[[#This Row],[Asset Class]],tblVCDBIndex[],4,FALSE),"") -> 2 | N28: =IFERROR(VLOOKUP(10*tblRiskRegister32[[#This Row],[Safeguard Maturity Score]]+tblRiskRegister32[[#This Row],[VCDB Index]],tblHITIndexWeightTable[],4,FALSE),"") | O28: =VLOOKUP(tblRiskRegister32[[#This Row],[Asset Class]],tblInherentImpacts30[],2,FALSE) -> 0 | P28: =VLOOKUP(tblRiskRegister32[[#This Row],[Asset Class]],tblInherentImpacts30[],3,FALSE) -> 0 | Q28: =VLOOKUP(tblRiskRegister32[[#This Row],[Asset Class]],tblInherentImpacts30[],4,FALSE) -> 0 | R28: =VLOOKUP(tblRiskRegister32[[#This Row],[Asset Class]],tblInherentImpacts30[],5,FALSE) -> 0 | S28: =IFERROR(MAX(tblRiskRegister32[[#This Row],[Impact to Mission]:[Impact to Obligations]])*tblRiskRegister32[[#This Row],[Expectancy Score]],"") | T28: =tblRiskRegister32[[#This Row],[Risk Score]] | V28: 3.8 | W28: Document Data Flows | X28: Document data flows. Data flow documentation includes service provider data flows and should be based on the enterprise’s data management process. Review and update documentation annually, or when significant enterprise changes occur that could impact this Safeguard. | AA28: =IFERROR(VLOOKUP(10*tblRiskRegister32[[#This Row],[Risk Treatment Safeguard Maturity Score]]+tblRiskRegister32[[#This Row],[VCDB Index]],tblHITIndexWeightTable[],4,FALSE),"") | AB28: =VLOOKUP(tblRiskRegister32[[#This Row],[Asset Class]],tblInherentImpacts30[],2,FALSE) -> 0 | AC28: =VLOOKUP(tblRiskRegister32[[#This Row],[Asset Class]],tblInherentImpacts30[],3,FALSE) -> 0 | AD28: =VLOOKUP(tblRiskRegister32[[#This Row],[Asset Class]],tblInherentImpacts30[],4,FALSE) -> 0 | AE28: =VLOOKUP(tblRiskRegister32[[#This Row],[Asset Class]],tblInherentImpacts30[],5,FALSE) -> 0 | AF28: =IFERROR(MAX(tblRiskRegister32[[#This Row],[Risk Treatment Safeguard Impact to Mission]:[Risk Treatment Safeguard Impact to Obligations]])*tblRiskRegister32[[#This Row],[Risk Treatment Safeguard Expectancy Score]],"") | AG28: =IF(tblRiskRegister32[[#This Row],[Risk Score]]>=AcceptableRisk,IF(tblRiskRegister32[[#This Row],[Risk Treatment Safeguard Risk Score]]<AcceptableRisk, IF(tblRiskRegister32[[#This Row],[Risk Treatment Safeguard Risk Score]]<tblRiskRegister32[[#This Row],[Risk Score]],"Yes","No"),"No"),"Yes") -> No
B29: Data | D29: 3.9 | E29: Encrypt Data on Removable Media | G29: x | H29: Protect | M29: =IFERROR(VLOOKUP(tblRiskRegister32[[#This Row],[Asset Class]],tblVCDBIndex[],4,FALSE),"") -> 2 | N29: =IFERROR(VLOOKUP(10*tblRiskRegister32[[#This Row],[Safeguard Maturity Score]]+tblRiskRegister32[[#This Row],[VCDB Index]],tblHITIndexWeightTable[],4,FALSE),"") | O29: =VLOOKUP(tblRiskRegister32[[#This Row],[Asset Class]],tblInherentImpacts30[],2,FALSE) -> 0 | P29: =VLOOKUP(tblRiskRegister32[[#This Row],[Asset Class]],tblInherentImpacts30[],3,FALSE) -> 0 | Q29: =VLOOKUP(tblRiskRegister32[[#This Row],[Asset Class]],tblInherentImpacts30[],4,FALSE) -> 0 | R29: =VLOOKUP(tblRiskRegister32[[#This Row],[Asset Class]],tblInherentImpacts30[],5,FALSE) -> 0 | S29: =IFERROR(MAX(tblRiskRegister32[[#This Row],[Impact to Mission]:[Impact to Obligations]])*tblRiskRegister32[[#This Row],[Expectancy Score]],"") | T29: =tblRiskRegister32[[#This Row],[Risk Score]] | V29: 3.9 | W29: Encrypt Data on Removable Media | X29: Encrypt data on removable media. | AA29: =IFERROR(VLOOKUP(10*tblRiskRegister32[[#This Row],[Risk Treatment Safeguard Maturity Score]]+tblRiskRegister32[[#This Row],[VCDB Index]],tblHITIndexWeightTable[],4,FALSE),"") | AB29: =VLOOKUP(tblRiskRegister32[[#This Row],[Asset Class]],tblInherentImpacts30[],2,FALSE) -> 0 | AC29: =VLOOKUP(tblRiskRegister32[[#This Row],[Asset Class]],tblInherentImpacts30[],3,FALSE) -> 0 | AD29: =VLOOKUP(tblRiskRegister32[[#This Row],[Asset Class]],tblInherentImpacts30[],4,FALSE) -> 0 | AE29: =VLOOKUP(tblRiskRegister32[[#This Row],[Asset Class]],tblInherentImpacts30[],5,FALSE) -> 0 | AF29: =IFERROR(MAX(tblRiskRegister32[[#This Row],[Risk Treatment Safeguard Impact to Mission]:[Risk Treatment Safeguard Impact to Obligations]])*tblRiskRegister32[[#This Row],[Risk Treatment Safeguard Expectancy Score]],"") | AG29: =IF(tblRiskRegister32[[#This Row],[Risk Score]]>=AcceptableRisk,IF(tblRiskRegister32[[#This Row],[Risk Treatment Safeguard Risk Score]]<AcceptableRisk, IF(tblRiskRegister32[[#This Row],[Risk Treatment Safeguard Risk Score]]<tblRiskRegister32[[#This Row],[Risk Score]],"Yes","No"),"No"),"Yes") -> No
B30: Data | D30: 3.1 | E30: Encrypt Sensitive Data in Transit | G30: x | H30: Protect | M30: =IFERROR(VLOOKUP(tblRiskRegister32[[#This Row],[Asset Class]],tblVCDBIndex[],4,FALSE),"") -> 2 | N30: =IFERROR(VLOOKUP(10*tblRiskRegister32[[#This Row],[Safeguard Maturity Score]]+tblRiskRegister32[[#This Row],[VCDB Index]],tblHITIndexWeightTable[],4,FALSE),"") | O30: =VLOOKUP(tblRiskRegister32[[#This Row],[Asset Class]],tblInherentImpacts30[],2,FALSE) -> 0 | P30: =VLOOKUP(tblRiskRegister32[[#This Row],[Asset Class]],tblInherentImpacts30[],3,FALSE) -> 0 | Q30: =VLOOKUP(tblRiskRegister32[[#This Row],[Asset Class]],tblInherentImpacts30[],4,FALSE) -> 0 | R30: =VLOOKUP(tblRiskRegister32[[#This Row],[Asset Class]],tblInherentImpacts30[],5,FALSE) -> 0 | S30: =IFERROR(MAX(tblRiskRegister32[[#This Row],[Impact to Mission]:[Impact to Obligations]])*tblRiskRegister32[[#This Row],[Expectancy Score]],"") | T30: =tblRiskRegister32[[#This Row],[Risk Score]] | V30: 3.1 | W30: Encrypt Sensitive Data in Transit | X30: Encrypt sensitive data in transit. Example implementations can include: Transport Layer Security (TLS) and Open Secure Shell (OpenSSH). | AA30: =IFERROR(VLOOKUP(10*tblRiskRegister32[[#This Row],[Risk Treatment Safeguard Maturity Score]]+tblRiskRegister32[[#This Row],[VCDB Index]],tblHITIndexWeightTable[],4,FALSE),"") | AB30: =VLOOKUP(tblRiskRegister32[[#This Row],[Asset Class]],tblInherentImpacts30[],2,FALSE) -> 0 | AC30: =VLOOKUP(tblRiskRegister32[[#This Row],[Asset Class]],tblInherentImpacts30[],3,FALSE) -> 0 | AD30: =VLOOKUP(tblRiskRegister32[[#This Row],[Asset Class]],tblInherentImpacts30[],4,FALSE) -> 0 | AE30: =VLOOKUP(tblRiskRegister32[[#This Row],[Asset Class]],tblInherentImpacts30[],5,FALSE) -> 0 | AF30: =IFERROR(MAX(tblRiskRegister32[[#This Row],[Risk Treatment Safeguard Impact to Mission]:[Risk Treatment Safeguard Impact to Obligations]])*tblRiskRegister32[[#This Row],[Risk Treatment Safeguard Expectancy Score]],"") | AG30: =IF(tblRiskRegister32[[#This Row],[Risk Score]]>=AcceptableRisk,IF(tblRiskRegister32[[#This Row],[Risk Treatment Safeguard Risk Score]]<AcceptableRisk, IF(tblRiskRegister32[[#This Row],[Risk Treatment Safeguard Risk Score]]<tblRiskRegister32[[#This Row],[Risk Score]],"Yes","No"),"No"),"Yes") -> No
B31: Data | D31: 3.11 | E31: Encrypt Sensitive Data at Rest | G31: x | H31: Protect | M31: =IFERROR(VLOOKUP(tblRiskRegister32[[#This Row],[Asset Class]],tblVCDBIndex[],4,FALSE),"") -> 2 | N31: =IFERROR(VLOOKUP(10*tblRiskRegister32[[#This Row],[Safeguard Maturity Score]]+tblRiskRegister32[[#This Row],[VCDB Index]],tblHITIndexWeightTable[],4,FALSE),"") | O31: =VLOOKUP(tblRiskRegister32[[#This Row],[Asset Class]],tblInherentImpacts30[],2,FALSE) -> 0 | P31: =VLOOKUP(tblRiskRegister32[[#This Row],[Asset Class]],tblInherentImpacts30[],3,FALSE) -> 0 | Q31: =VLOOKUP(tblRiskRegister32[[#This Row],[Asset Class]],tblInherentImpacts30[],4,FALSE) -> 0 | R31: =VLOOKUP(tblRiskRegister32[[#This Row],[Asset Class]],tblInherentImpacts30[],5,FALSE) -> 0 | S31: =IFERROR(MAX(tblRiskRegister32[[#This Row],[Impact to Mission]:[Impact to Obligations]])*tblRiskRegister32[[#This Row],[Expectancy Score]],"") | T31: =tblRiskRegister32[[#This Row],[Risk Score]] | V31: 3.11 | W31: Encrypt Sensitive Data at Rest | X31: Encrypt sensitive data at rest on servers, applications, and databases. Storage-layer encryption, also known as server-side encryption, meets the minimum requirement of this Safeguard. Additional encryption methods may include application-layer encryption, also known as client-side encryption, where access to the data storage device(s) does not permit access to the plain-text data. | AA31: =IFERROR(VLOOKUP(10*tblRiskRegister32[[#This Row],[Risk Treatment Safeguard Maturity Score]]+tblRiskRegister32[[#This Row],[VCDB Index]],tblHITIndexWeightTable[],4,FALSE),"") | AB31: =VLOOKUP(tblRiskRegister32[[#This Row],[Asset Class]],tblInherentImpacts30[],2,FALSE) -> 0 | AC31: =VLOOKUP(tblRiskRegister32[[#This Row],[Asset Class]],tblInherentImpacts30[],3,FALSE) -> 0 | AD31: =VLOOKUP(tblRiskRegister32[[#This Row],[Asset Class]],tblInherentImpacts30[],4,FALSE) -> 0 | AE31: =VLOOKUP(tblRiskRegister32[[#This Row],[Asset Class]],tblInherentImpacts30[],5,FALSE) -> 0 | AF31: =IFERROR(MAX(tblRiskRegister32[[#This Row],[Risk Treatment Safeguard Impact to Mission]:[Risk Treatment Safeguard Impact to Obligations]])*tblRiskRegister32[[#This Row],[Risk Treatment Safeguard Expectancy Score]],"") | AG31: =IF(tblRiskRegister32[[#This Row],[Risk Score]]>=AcceptableRisk,IF(tblRiskRegister32[[#This Row],[Risk Treatment Safeguard Risk Score]]<AcceptableRisk, IF(tblRiskRegister32[[#This Row],[Risk Treatment Safeguard Risk Score]]<tblRiskRegister32[[#This Row],[Risk Score]],"Yes","No"),"No"),"Yes") -> No
B32: Data | D32: 3.12 | E32: Segment Data Processing and Storage Based on Sensitivity | G32: x | H32: Protect | M32: =IFERROR(VLOOKUP(tblRiskRegister32[[#This Row],[Asset Class]],tblVCDBIndex[],4,FALSE),"") -> 2 | N32: =IFERROR(VLOOKUP(10*tblRiskRegister32[[#This Row],[Safeguard Maturity Score]]+tblRiskRegister32[[#This Row],[VCDB Index]],tblHITIndexWeightTable[],4,FALSE),"") | O32: =VLOOKUP(tblRiskRegister32[[#This Row],[Asset Class]],tblInherentImpacts30[],2,FALSE) -> 0 | P32: =VLOOKUP(tblRiskRegister32[[#This Row],[Asset Class]],tblInherentImpacts30[],3,FALSE) -> 0 | Q32: =VLOOKUP(tblRiskRegister32[[#This Row],[Asset Class]],tblInherentImpacts30[],4,FALSE) -> 0 | R32: =VLOOKUP(tblRiskRegister32[[#This Row],[Asset Class]],tblInherentImpacts30[],5,FALSE) -> 0 | S32: =IFERROR(MAX(tblRiskRegister32[[#This Row],[Impact to Mission]:[Impact to Obligations]])*tblRiskRegister32[[#This Row],[Expectancy Score]],"") | T32: =tblRiskRegister32[[#This Row],[Risk Score]] | V32: 3.12 | W32: Segment Data Processing and Storage Based on Sensitivity | X32: Segment data processing and storage based on the sensitivity of the data. Do not process sensitive data on enterprise assets intended for lower sensitivity data. | AA32: =IFERROR(VLOOKUP(10*tblRiskRegister32[[#This Row],[Risk Treatment Safeguard Maturity Score]]+tblRiskRegister32[[#This Row],[VCDB Index]],tblHITIndexWeightTable[],4,FALSE),"") | AB32: =VLOOKUP(tblRiskRegister32[[#This Row],[Asset Class]],tblInherentImpacts30[],2,FALSE) -> 0 | AC32: =VLOOKUP(tblRiskRegister32[[#This Row],[Asset Class]],tblInherentImpacts30[],3,FALSE) -> 0 | AD32: =VLOOKUP(tblRiskRegister32[[#This Row],[Asset Class]],tblInherentImpacts30[],4,FALSE) -> 0 | AE32: =VLOOKUP(tblRiskRegister32[[#This Row],[Asset Class]],tblInherentImpacts30[],5,FALSE) -> 0 | AF32: =IFERROR(MAX(tblRiskRegister32[[#This Row],[Risk Treatment Safeguard Impact to Mission]:[Risk Treatment Safeguard Impact to Obligations]])*tblRiskRegister32[[#This Row],[Risk Treatment Safeguard Expectancy Score]],"") | AG32: =IF(tblRiskRegister32[[#This Row],[Risk Score]]>=AcceptableRisk,IF(tblRiskRegister32[[#This Row],[Risk Treatment Safeguard Risk Score]]<AcceptableRisk, IF(tblRiskRegister32[[#This Row],[Risk Treatment Safeguard Risk Score]]<tblRiskRegister32[[#This Row],[Risk Score]],"Yes","No"),"No"),"Yes") -> No
B33: Documentation | D33: 4.1 | E33: Establish and Maintain a Secure Configuration Process | F33: x | G33: x | H33: Govern | M33: =IFERROR(VLOOKUP(tblRiskRegister32[[#This Row],[Asset Class]],tblVCDBIndex[],4,FALSE),"") -> 2 | N33: =IFERROR(VLOOKUP(10*tblRiskRegister32[[#This Row],[Safeguard Maturity Score]]+tblRiskRegister32[[#This Row],[VCDB Index]],tblHITIndexWeightTable[],4,FALSE),"") | O33: =VLOOKUP(tblRiskRegister32[[#This Row],[Asset Class]],tblInherentImpacts30[],2,FALSE) -> 0 | P33: =VLOOKUP(tblRiskRegister32[[#This Row],[Asset Class]],tblInherentImpacts30[],3,FALSE) -> 0 | Q33: =VLOOKUP(tblRiskRegister32[[#This Row],[Asset Class]],tblInherentImpacts30[],4,FALSE) -> 0 | R33: =VLOOKUP(tblRiskRegister32[[#This Row],[Asset Class]],tblInherentImpacts30[],5,FALSE) -> 0 | S33: =IFERROR(MAX(tblRiskRegister32[[#This Row],[Impact to Mission]:[Impact to Obligations]])*tblRiskRegister32[[#This Row],[Expectancy Score]],"") | T33: =tblRiskRegister32[[#This Row],[Risk Score]] | V33: 4.1 | W33: Establish and Maintain a Secure Configuration Process | X33: Establish and maintain a documented secure configuration process for enterprise assets (end-user devices, including portable and mobile, non-computing/IoT devices, and servers) and software (operating systems and applications). Review and update documentation annually, or when significant enterprise changes occur that could impact this Safeguard. | AA33: =IFERROR(VLOOKUP(10*tblRiskRegister32[[#This Row],[Risk Treatment Safeguard Maturity Score]]+tblRiskRegister32[[#This Row],[VCDB Index]],tblHITIndexWeightTable[],4,FALSE),"") | AB33: =VLOOKUP(tblRiskRegister32[[#This Row],[Asset Class]],tblInherentImpacts30[],2,FALSE) -> 0 | AC33: =VLOOKUP(tblRiskRegister32[[#This Row],[Asset Class]],tblInherentImpacts30[],3,FALSE) -> 0 | AD33: =VLOOKUP(tblRiskRegister32[[#This Row],[Asset Class]],tblInherentImpacts30[],4,FALSE) -> 0 | AE33: =VLOOKUP(tblRiskRegister32[[#This Row],[Asset Class]],tblInherentImpacts30[],5,FALSE) -> 0 | AF33: =IFERROR(MAX(tblRiskRegister32[[#This Row],[Risk Treatment Safeguard Impact to Mission]:[Risk Treatment Safeguard Impact to Obligations]])*tblRiskRegister32[[#This Row],[Risk Treatment Safeguard Expectancy Score]],"") | AG33: =IF(tblRiskRegister32[[#This Row],[Risk Score]]>=AcceptableRisk,IF(tblRiskRegister32[[#This Row],[Risk Treatment Safeguard Risk Score]]<AcceptableRisk, IF(tblRiskRegister32[[#This Row],[Risk Treatment Safeguard Risk Score]]<tblRiskRegister32[[#This Row],[Risk Score]],"Yes","No"),"No"),"Yes") -> No
B34: Documentation | D34: 4.2 | E34: Establish and Maintain a Secure Configuration Process for Network Infrastructure | F34: x | G34: x | H34: Govern | M34: =IFERROR(VLOOKUP(tblRiskRegister32[[#This Row],[Asset Class]],tblVCDBIndex[],4,FALSE),"") -> 2 | N34: =IFERROR(VLOOKUP(10*tblRiskRegister32[[#This Row],[Safeguard Maturity Score]]+tblRiskRegister32[[#This Row],[VCDB Index]],tblHITIndexWeightTable[],4,FALSE),"") | O34: =VLOOKUP(tblRiskRegister32[[#This Row],[Asset Class]],tblInherentImpacts30[],2,FALSE) -> 0 | P34: =VLOOKUP(tblRiskRegister32[[#This Row],[Asset Class]],tblInherentImpacts30[],3,FALSE) -> 0 | Q34: =VLOOKUP(tblRiskRegister32[[#This Row],[Asset Class]],tblInherentImpacts30[],4,FALSE) -> 0 | R34: =VLOOKUP(tblRiskRegister32[[#This Row],[Asset Class]],tblInherentImpacts30[],5,FALSE) -> 0 | S34: =IFERROR(MAX(tblRiskRegister32[[#This Row],[Impact to Mission]:[Impact to Obligations]])*tblRiskRegister32[[#This Row],[Expectancy Score]],"") | T34: =tblRiskRegister32[[#This Row],[Risk Score]] | V34: 4.2 | W34: Establish and Maintain a Secure Configuration Process for Network Infrastructure | X34: Establish and maintain a documented secure configuration process for network devices. Review and update documentation annually, or when significant enterprise changes occur that could impact this Safeguard. | AA34: =IFERROR(VLOOKUP(10*tblRiskRegister32[[#This Row],[Risk Treatment Safeguard Maturity Score]]+tblRiskRegister32[[#This Row],[VCDB Index]],tblHITIndexWeightTable[],4,FALSE),"") | AB34: =VLOOKUP(tblRiskRegister32[[#This Row],[Asset Class]],tblInherentImpacts30[],2,FALSE) -> 0 | AC34: =VLOOKUP(tblRiskRegister32[[#This Row],[Asset Class]],tblInherentImpacts30[],3,FALSE) -> 0 | AD34: =VLOOKUP(tblRiskRegister32[[#This Row],[Asset Class]],tblInherentImpacts30[],4,FALSE) -> 0 | AE34: =VLOOKUP(tblRiskRegister32[[#This Row],[Asset Class]],tblInherentImpacts30[],5,FALSE) -> 0 | AF34: =IFERROR(MAX(tblRiskRegister32[[#This Row],[Risk Treatment Safeguard Impact to Mission]:[Risk Treatment Safeguard Impact to Obligations]])*tblRiskRegister32[[#This Row],[Risk Treatment Safeguard Expectancy Score]],"") | AG34: =IF(tblRiskRegister32[[#This Row],[Risk Score]]>=AcceptableRisk,IF(tblRiskRegister32[[#This Row],[Risk Treatment Safeguard Risk Score]]<AcceptableRisk, IF(tblRiskRegister32[[#This Row],[Risk Treatment Safeguard Risk Score]]<tblRiskRegister32[[#This Row],[Risk Score]],"Yes","No"),"No"),"Yes") -> No
B35: Devices | D35: 4.3 | E35: Configure Automatic Session Locking on Enterprise Assets | F35: x | G35: x | H35: Protect | M35: =IFERROR(VLOOKUP(tblRiskRegister32[[#This Row],[Asset Class]],tblVCDBIndex[],4,FALSE),"") -> 4 | N35: =IFERROR(VLOOKUP(10*tblRiskRegister32[[#This Row],[Safeguard Maturity Score]]+tblRiskRegister32[[#This Row],[VCDB Index]],tblHITIndexWeightTable[],4,FALSE),"") | O35: =VLOOKUP(tblRiskRegister32[[#This Row],[Asset Class]],tblInherentImpacts30[],2,FALSE) -> 0 | P35: =VLOOKUP(tblRiskRegister32[[#This Row],[Asset Class]],tblInherentImpacts30[],3,FALSE) -> 0 | Q35: =VLOOKUP(tblRiskRegister32[[#This Row],[Asset Class]],tblInherentImpacts30[],4,FALSE) -> 0 | R35: =VLOOKUP(tblRiskRegister32[[#This Row],[Asset Class]],tblInherentImpacts30[],5,FALSE) -> 0 | S35: =IFERROR(MAX(tblRiskRegister32[[#This Row],[Impact to Mission]:[Impact to Obligations]])*tblRiskRegister32[[#This Row],[Expectancy Score]],"") | T35: =tblRiskRegister32[[#This Row],[Risk Score]] | V35: 4.3 | W35: Configure Automatic Session Locking on Enterprise Assets | X35: Configure automatic session locking on enterprise assets after a defined period of inactivity. For general purpose operating systems, the period must not exceed 15 minutes. For mobile end-user devices, the period must not exceed 2 minutes. | AA35: =IFERROR(VLOOKUP(10*tblRiskRegister32[[#This Row],[Risk Treatment Safeguard Maturity Score]]+tblRiskRegister32[[#This Row],[VCDB Index]],tblHITIndexWeightTable[],4,FALSE),"") | AB35: =VLOOKUP(tblRiskRegister32[[#This Row],[Asset Class]],tblInherentImpacts30[],2,FALSE) -> 0 | AC35: =VLOOKUP(tblRiskRegister32[[#This Row],[Asset Class]],tblInherentImpacts30[],3,FALSE) -> 0 | AD35: =VLOOKUP(tblRiskRegister32[[#This Row],[Asset Class]],tblInherentImpacts30[],4,FALSE) -> 0 | AE35: =VLOOKUP(tblRiskRegister32[[#This Row],[Asset Class]],tblInherentImpacts30[],5,FALSE) -> 0 | AF35: =IFERROR(MAX(tblRiskRegister32[[#This Row],[Risk Treatment Safeguard Impact to Mission]:[Risk Treatment Safeguard Impact to Obligations]])*tblRiskRegister32[[#This Row],[Risk Treatment Safeguard Expectancy Score]],"") | AG35: =IF(tblRiskRegister32[[#This Row],[Risk Score]]>=AcceptableRisk,IF(tblRiskRegister32[[#This Row],[Risk Treatment Safeguard Risk Score]]<AcceptableRisk, IF(tblRiskRegister32[[#This Row],[Risk Treatment Safeguard Risk Score]]<tblRiskRegister32[[#This Row],[Risk Score]],"Yes","No"),"No"),"Yes") -> No
B36: Devices | D36: 4.4 | E36: Implement and Manage a Firewall on Servers | F36: x | G36: x | H36: Protect | M36: =IFERROR(VLOOKUP(tblRiskRegister32[[#This Row],[Asset Class]],tblVCDBIndex[],4,FALSE),"") -> 4 | N36: =IFERROR(VLOOKUP(10*tblRiskRegister32[[#This Row],[Safeguard Maturity Score]]+tblRiskRegister32[[#This Row],[VCDB Index]],tblHITIndexWeightTable[],4,FALSE),"") | O36: =VLOOKUP(tblRiskRegister32[[#This Row],[Asset Class]],tblInherentImpacts30[],2,FALSE) -> 0 | P36: =VLOOKUP(tblRiskRegister32[[#This Row],[Asset Class]],tblInherentImpacts30[],3,FALSE) -> 0 | Q36: =VLOOKUP(tblRiskRegister32[[#This Row],[Asset Class]],tblInherentImpacts30[],4,FALSE) -> 0 | R36: =VLOOKUP(tblRiskRegister32[[#This Row],[Asset Class]],tblInherentImpacts30[],5,FALSE) -> 0 | S36: =IFERROR(MAX(tblRiskRegister32[[#This Row],[Impact to Mission]:[Impact to Obligations]])*tblRiskRegister32[[#This Row],[Expectancy Score]],"") | T36: =tblRiskRegister32[[#This Row],[Risk Score]] | V36: 4.4 | W36: Implement and Manage a Firewall on Servers | X36: Implement and manage a firewall on servers, where supported. Example implementations include a virtual firewall, operating system firewall, or a third-party firewall agent. | AA36: =IFERROR(VLOOKUP(10*tblRiskRegister32[[#This Row],[Risk Treatment Safeguard Maturity Score]]+tblRiskRegister32[[#This Row],[VCDB Index]],tblHITIndexWeightTable[],4,FALSE),"") | AB36: =VLOOKUP(tblRiskRegister32[[#This Row],[Asset Class]],tblInherentImpacts30[],2,FALSE) -> 0 | AC36: =VLOOKUP(tblRiskRegister32[[#This Row],[Asset Class]],tblInherentImpacts30[],3,FALSE) -> 0 | AD36: =VLOOKUP(tblRiskRegister32[[#This Row],[Asset Class]],tblInherentImpacts30[],4,FALSE) -> 0 | AE36: =VLOOKUP(tblRiskRegister32[[#This Row],[Asset Class]],tblInherentImpacts30[],5,FALSE) -> 0 | AF36: =IFERROR(MAX(tblRiskRegister32[[#This Row],[Risk Treatment Safeguard Impact to Mission]:[Risk Treatment Safeguard Impact to Obligations]])*tblRiskRegister32[[#This Row],[Risk Treatment Safeguard Expectancy Score]],"") | AG36: =IF(tblRiskRegister32[[#This Row],[Risk Score]]>=AcceptableRisk,IF(tblRiskRegister32[[#This Row],[Risk Treatment Safeguard Risk Score]]<AcceptableRisk, IF(tblRiskRegister32[[#This Row],[Risk Treatment Safeguard Risk Score]]<tblRiskRegister32[[#This Row],[Risk Score]],"Yes","No"),"No"),"Yes") -> No
B37: Devices | D37: 4.5 | E37: Implement and Manage a Firewall on End-User Devices | F37: x | G37: x | H37: Protect | M37: =IFERROR(VLOOKUP(tblRiskRegister32[[#This Row],[Asset Class]],tblVCDBIndex[],4,FALSE),"") -> 4 | N37: =IFERROR(VLOOKUP(10*tblRiskRegister32[[#This Row],[Safeguard Maturity Score]]+tblRiskRegister32[[#This Row],[VCDB Index]],tblHITIndexWeightTable[],4,FALSE),"") | O37: =VLOOKUP(tblRiskRegister32[[#This Row],[Asset Class]],tblInherentImpacts30[],2,FALSE) -> 0 | P37: =VLOOKUP(tblRiskRegister32[[#This Row],[Asset Class]],tblInherentImpacts30[],3,FALSE) -> 0 | Q37: =VLOOKUP(tblRiskRegister32[[#This Row],[Asset Class]],tblInherentImpacts30[],4,FALSE) -> 0 | R37: =VLOOKUP(tblRiskRegister32[[#This Row],[Asset Class]],tblInherentImpacts30[],5,FALSE) -> 0 | S37: =IFERROR(MAX(tblRiskRegister32[[#This Row],[Impact to Mission]:[Impact to Obligations]])*tblRiskRegister32[[#This Row],[Expectancy Score]],"") | T37: =tblRiskRegister32[[#This Row],[Risk Score]] | V37: 4.5 | W37: Implement and Manage a Firewall on End-User Devices | X37: Implement and manage a host-based firewall or port-filtering tool on end-user devices, with a default-deny rule that drops all traffic except those services and ports that are explicitly allowed. | AA37: =IFERROR(VLOOKUP(10*tblRiskRegister32[[#This Row],[Risk Treatment Safeguard Maturity Score]]+tblRiskRegister32[[#This Row],[VCDB Index]],tblHITIndexWeightTable[],4,FALSE),"") | AB37: =VLOOKUP(tblRiskRegister32[[#This Row],[Asset Class]],tblInherentImpacts30[],2,FALSE) -> 0 | AC37: =VLOOKUP(tblRiskRegister32[[#This Row],[Asset Class]],tblInherentImpacts30[],3,FALSE) -> 0 | AD37: =VLOOKUP(tblRiskRegister32[[#This Row],[Asset Class]],tblInherentImpacts30[],4,FALSE) -> 0 | AE37: =VLOOKUP(tblRiskRegister32[[#This Row],[Asset Class]],tblInherentImpacts30[],5,FALSE) -> 0 | AF37: =IFERROR(MAX(tblRiskRegister32[[#This Row],[Risk Treatment Safeguard Impact to Mission]:[Risk Treatment Safeguard Impact to Obligations]])*tblRiskRegister32[[#This Row],[Risk Treatment Safeguard Expectancy Score]],"") | AG37: =IF(tblRiskRegister32[[#This Row],[Risk Score]]>=AcceptableRisk,IF(tblRiskRegister32[[#This Row],[Risk Treatment Safeguard Risk Score]]<AcceptableRisk, IF(tblRiskRegister32[[#This Row],[Risk Treatment Safeguard Risk Score]]<tblRiskRegister32[[#This Row],[Risk Score]],"Yes","No"),"No"),"Yes") -> No
B38: Devices | D38: 4.6 | E38: Securely Manage Enterprise Assets and Software | F38: x | G38: x | H38: Protect | M38: =IFERROR(VLOOKUP(tblRiskRegister32[[#This Row],[Asset Class]],tblVCDBIndex[],4,FALSE),"") -> 4 | N38: =IFERROR(VLOOKUP(10*tblRiskRegister32[[#This Row],[Safeguard Maturity Score]]+tblRiskRegister32[[#This Row],[VCDB Index]],tblHITIndexWeightTable[],4,FALSE),"") | O38: =VLOOKUP(tblRiskRegister32[[#This Row],[Asset Class]],tblInherentImpacts30[],2,FALSE) -> 0 | P38: =VLOOKUP(tblRiskRegister32[[#This Row],[Asset Class]],tblInherentImpacts30[],3,FALSE) -> 0 | Q38: =VLOOKUP(tblRiskRegister32[[#This Row],[Asset Class]],tblInherentImpacts30[],4,FALSE) -> 0 | R38: =VLOOKUP(tblRiskRegister32[[#This Row],[Asset Class]],tblInherentImpacts30[],5,FALSE) -> 0 | S38: =IFERROR(MAX(tblRiskRegister32[[#This Row],[Impact to Mission]:[Impact to Obligations]])*tblRiskRegister32[[#This Row],[Expectancy Score]],"") | T38: =tblRiskRegister32[[#This Row],[Risk Score]] | V38: 4.6 | W38: Securely Manage Enterprise Assets and Software | X38: Securely manage enterprise assets and software. Example implementations include managing configuration through version-controlled Infrastructure-as-Code (IaC) and accessing administrative interfaces over secure network protocols, such as Secure Shell (SSH) and Hypertext Transfer Protocol Secure (HTTPS). Do not use insecure management protocols, such as Telnet (Teletype Network) and HTTP, unless operationally essential. | AA38: =IFERROR(VLOOKUP(10*tblRiskRegister32[[#This Row],[Risk Treatment Safeguard Maturity Score]]+tblRiskRegister32[[#This Row],[VCDB Index]],tblHITIndexWeightTable[],4,FALSE),"") | AB38: =VLOOKUP(tblRiskRegister32[[#This Row],[Asset Class]],tblInherentImpacts30[],2,FALSE) -> 0 | AC38: =VLOOKUP(tblRiskRegister32[[#This Row],[Asset Class]],tblInherentImpacts30[],3,FALSE) -> 0 | AD38: =VLOOKUP(tblRiskRegister32[[#This Row],[Asset Class]],tblInherentImpacts30[],4,FALSE) -> 0 | AE38: =VLOOKUP(tblRiskRegister32[[#This Row],[Asset Class]],tblInherentImpacts30[],5,FALSE) -> 0 | AF38: =IFERROR(MAX(tblRiskRegister32[[#This Row],[Risk Treatment Safeguard Impact to Mission]:[Risk Treatment Safeguard Impact to Obligations]])*tblRiskRegister32[[#This Row],[Risk Treatment Safeguard Expectancy Score]],"") | AG38: =IF(tblRiskRegister32[[#This Row],[Risk Score]]>=AcceptableRisk,IF(tblRiskRegister32[[#This Row],[Risk Treatment Safeguard Risk Score]]<AcceptableRisk, IF(tblRiskRegister32[[#This Row],[Risk Treatment Safeguard Risk Score]]<tblRiskRegister32[[#This Row],[Risk Score]],"Yes","No"),"No"),"Yes") -> No
B39: Users | D39: 4.7 | E39: Manage Default Accounts on Enterprise Assets and Software | F39: x | G39: x | H39: Protect | M39: =IFERROR(VLOOKUP(tblRiskRegister32[[#This Row],[Asset Class]],tblVCDBIndex[],4,FALSE),"") -> 2 | N39: =IFERROR(VLOOKUP(10*tblRiskRegister32[[#This Row],[Safeguard Maturity Score]]+tblRiskRegister32[[#This Row],[VCDB Index]],tblHITIndexWeightTable[],4,FALSE),"") | O39: =VLOOKUP(tblRiskRegister32[[#This Row],[Asset Class]],tblInherentImpacts30[],2,FALSE) -> 0 | P39: =VLOOKUP(tblRiskRegister32[[#This Row],[Asset Class]],tblInherentImpacts30[],3,FALSE) -> 0 | Q39: =VLOOKUP(tblRiskRegister32[[#This Row],[Asset Class]],tblInherentImpacts30[],4,FALSE) -> 0 | R39: =VLOOKUP(tblRiskRegister32[[#This Row],[Asset Class]],tblInherentImpacts30[],5,FALSE) -> 0 | S39: =IFERROR(MAX(tblRiskRegister32[[#This Row],[Impact to Mission]:[Impact to Obligations]])*tblRiskRegister32[[#This Row],[Expectancy Score]],"") | T39: =tblRiskRegister32[[#This Row],[Risk Score]] | V39: 4.7 | W39: Manage Default Accounts on Enterprise Assets and Software | X39: Manage default accounts on enterprise assets and software, such as root, administrator, and other pre-configured vendor accounts. Example implementations can include: disabling default accounts or making them unusable. | AA39: =IFERROR(VLOOKUP(10*tblRiskRegister32[[#This Row],[Risk Treatment Safeguard Maturity Score]]+tblRiskRegister32[[#This Row],[VCDB Index]],tblHITIndexWeightTable[],4,FALSE),"") | AB39: =VLOOKUP(tblRiskRegister32[[#This Row],[Asset Class]],tblInherentImpacts30[],2,FALSE) -> 0 | AC39: =VLOOKUP(tblRiskRegister32[[#This Row],[Asset Class]],tblInherentImpacts30[],3,FALSE) -> 0 | AD39: =VLOOKUP(tblRiskRegister32[[#This Row],[Asset Class]],tblInherentImpacts30[],4,FALSE) -> 0 | AE39: =VLOOKUP(tblRiskRegister32[[#This Row],[Asset Class]],tblInherentImpacts30[],5,FALSE) -> 0 | AF39: =IFERROR(MAX(tblRiskRegister32[[#This Row],[Risk Treatment Safeguard Impact to Mission]:[Risk Treatment Safeguard Impact to Obligations]])*tblRiskRegister32[[#This Row],[Risk Treatment Safeguard Expectancy Score]],"") | AG39: =IF(tblRiskRegister32[[#This Row],[Risk Score]]>=AcceptableRisk,IF(tblRiskRegister32[[#This Row],[Risk Treatment Safeguard Risk Score]]<AcceptableRisk, IF(tblRiskRegister32[[#This Row],[Risk Treatment Safeguard Risk Score]]<tblRiskRegister32[[#This Row],[Risk Score]],"Yes","No"),"No"),"Yes") -> No
B40: Devices | D40: 4.8 | E40: Uninstall or Disable Unnecessary Services on Enterprise Assets and Software | G40: x | H40: Protect | M40: =IFERROR(VLOOKUP(tblRiskRegister32[[#This Row],[Asset Class]],tblVCDBIndex[],4,FALSE),"") -> 4 | N40: =IFERROR(VLOOKUP(10*tblRiskRegister32[[#This Row],[Safeguard Maturity Score]]+tblRiskRegister32[[#This Row],[VCDB Index]],tblHITIndexWeightTable[],4,FALSE),"") | O40: =VLOOKUP(tblRiskRegister32[[#This Row],[Asset Class]],tblInherentImpacts30[],2,FALSE) -> 0 | P40: =VLOOKUP(tblRiskRegister32[[#This Row],[Asset Class]],tblInherentImpacts30[],3,FALSE) -> 0 | Q40: =VLOOKUP(tblRiskRegister32[[#This Row],[Asset Class]],tblInherentImpacts30[],4,FALSE) -> 0 | R40: =VLOOKUP(tblRiskRegister32[[#This Row],[Asset Class]],tblInherentImpacts30[],5,FALSE) -> 0 | S40: =IFERROR(MAX(tblRiskRegister32[[#This Row],[Impact to Mission]:[Impact to Obligations]])*tblRiskRegister32[[#This Row],[Expectancy Score]],"") | T40: =tblRiskRegister32[[#This Row],[Risk Score]] | V40: 4.8 | W40: Uninstall or Disable Unnecessary Services on Enterprise Assets and Software | X40: Uninstall or disable unnecessary services on enterprise assets and software, such as an unused file sharing service, web application module, or service function. | AA40: =IFERROR(VLOOKUP(10*tblRiskRegister32[[#This Row],[Risk Treatment Safeguard Maturity Score]]+tblRiskRegister32[[#This Row],[VCDB Index]],tblHITIndexWeightTable[],4,FALSE),"") | AB40: =VLOOKUP(tblRiskRegister32[[#This Row],[Asset Class]],tblInherentImpacts30[],2,FALSE) -> 0 | AC40: =VLOOKUP(tblRiskRegister32[[#This Row],[Asset Class]],tblInherentImpacts30[],3,FALSE) -> 0 | AD40: =VLOOKUP(tblRiskRegister32[[#This Row],[Asset Class]],tblInherentImpacts30[],4,FALSE) -> 0 | AE40: =VLOOKUP(tblRiskRegister32[[#This Row],[Asset Class]],tblInherentImpacts30[],5,FALSE) -> 0 | AF40: =IFERROR(MAX(tblRiskRegister32[[#This Row],[Risk Treatment Safeguard Impact to Mission]:[Risk Treatment Safeguard Impact to Obligations]])*tblRiskRegister32[[#This Row],[Risk Treatment Safeguard Expectancy Score]],"") | AG40: =IF(tblRiskRegister32[[#This Row],[Risk Score]]>=AcceptableRisk,IF(tblRiskRegister32[[#This Row],[Risk Treatment Safeguard Risk Score]]<AcceptableRisk, IF(tblRiskRegister32[[#This Row],[Risk Treatment Safeguard Risk Score]]<tblRiskRegister32[[#This Row],[Risk Score]],"Yes","No"),"No"),"Yes") -> No
B41: Devices | D41: 4.9 | E41: Configure Trusted DNS Servers on Enterprise Assets | G41: x | H41: Protect | M41: =IFERROR(VLOOKUP(tblRiskRegister32[[#This Row],[Asset Class]],tblVCDBIndex[],4,FALSE),"") -> 4 | N41: =IFERROR(VLOOKUP(10*tblRiskRegister32[[#This Row],[Safeguard Maturity Score]]+tblRiskRegister32[[#This Row],[VCDB Index]],tblHITIndexWeightTable[],4,FALSE),"") | O41: =VLOOKUP(tblRiskRegister32[[#This Row],[Asset Class]],tblInherentImpacts30[],2,FALSE) -> 0 | P41: =VLOOKUP(tblRiskRegister32[[#This Row],[Asset Class]],tblInherentImpacts30[],3,FALSE) -> 0 | Q41: =VLOOKUP(tblRiskRegister32[[#This Row],[Asset Class]],tblInherentImpacts30[],4,FALSE) -> 0 | R41: =VLOOKUP(tblRiskRegister32[[#This Row],[Asset Class]],tblInherentImpacts30[],5,FALSE) -> 0 | S41: =IFERROR(MAX(tblRiskRegister32[[#This Row],[Impact to Mission]:[Impact to Obligations]])*tblRiskRegister32[[#This Row],[Expectancy Score]],"") | T41: =tblRiskRegister32[[#This Row],[Risk Score]] | V41: 4.9 | W41: Configure Trusted DNS Servers on Enterprise Assets | X41: Configure trusted DNS servers on network infrastructure. Example implementations include configuring network devices to use enterprise-controlled DNS servers and/or reputable externally accessible DNS servers. | AA41: =IFERROR(VLOOKUP(10*tblRiskRegister32[[#This Row],[Risk Treatment Safeguard Maturity Score]]+tblRiskRegister32[[#This Row],[VCDB Index]],tblHITIndexWeightTable[],4,FALSE),"") | AB41: =VLOOKUP(tblRiskRegister32[[#This Row],[Asset Class]],tblInherentImpacts30[],2,FALSE) -> 0 | AC41: =VLOOKUP(tblRiskRegister32[[#This Row],[Asset Class]],tblInherentImpacts30[],3,FALSE) -> 0 | AD41: =VLOOKUP(tblRiskRegister32[[#This Row],[Asset Class]],tblInherentImpacts30[],4,FALSE) -> 0 | AE41: =VLOOKUP(tblRiskRegister32[[#This Row],[Asset Class]],tblInherentImpacts30[],5,FALSE) -> 0 | AF41: =IFERROR(MAX(tblRiskRegister32[[#This Row],[Risk Treatment Safeguard Impact to Mission]:[Risk Treatment Safeguard Impact to Obligations]])*tblRiskRegister32[[#This Row],[Risk Treatment Safeguard Expectancy Score]],"") | AG41: =IF(tblRiskRegister32[[#This Row],[Risk Score]]>=AcceptableRisk,IF(tblRiskRegister32[[#This Row],[Risk Treatment Safeguard Risk Score]]<AcceptableRisk, IF(tblRiskRegister32[[#This Row],[Risk Treatment Safeguard Risk Score]]<tblRiskRegister32[[#This Row],[Risk Score]],"Yes","No"),"No"),"Yes") -> No
B42: Devices | D42: 4.1 | E42: Enforce Automatic Device Lockout on Portable End-User Devices | G42: x | H42: Protect | M42: =IFERROR(VLOOKUP(tblRiskRegister32[[#This Row],[Asset Class]],tblVCDBIndex[],4,FALSE),"") -> 4 | N42: =IFERROR(VLOOKUP(10*tblRiskRegister32[[#This Row],[Safeguard Maturity Score]]+tblRiskRegister32[[#This Row],[VCDB Index]],tblHITIndexWeightTable[],4,FALSE),"") | O42: =VLOOKUP(tblRiskRegister32[[#This Row],[Asset Class]],tblInherentImpacts30[],2,FALSE) -> 0 | P42: =VLOOKUP(tblRiskRegister32[[#This Row],[Asset Class]],tblInherentImpacts30[],3,FALSE) -> 0 | Q42: =VLOOKUP(tblRiskRegister32[[#This Row],[Asset Class]],tblInherentImpacts30[],4,FALSE) -> 0 | R42: =VLOOKUP(tblRiskRegister32[[#This Row],[Asset Class]],tblInherentImpacts30[],5,FALSE) -> 0 | S42: =IFERROR(MAX(tblRiskRegister32[[#This Row],[Impact to Mission]:[Impact to Obligations]])*tblRiskRegister32[[#This Row],[Expectancy Score]],"") | T42: =tblRiskRegister32[[#This Row],[Risk Score]] | V42: 4.1 | W42: Enforce Automatic Device Lockout on Portable End-User Devices | X42: Enforce automatic device lockout following a predetermined threshold of local failed authentication attempts on portable end-user devices, where supported. For laptops, do not allow more than 20 failed authentication attempts; for tablets and smartphones, no more than 10 failed authentication attempts. Example implementations include Microsoft® InTune Device Lock and Apple® Configuration Profile maxFailedAttempts. | AA42: =IFERROR(VLOOKUP(10*tblRiskRegister32[[#This Row],[Risk Treatment Safeguard Maturity Score]]+tblRiskRegister32[[#This Row],[VCDB Index]],tblHITIndexWeightTable[],4,FALSE),"") | AB42: =VLOOKUP(tblRiskRegister32[[#This Row],[Asset Class]],tblInherentImpacts30[],2,FALSE) -> 0 | AC42: =VLOOKUP(tblRiskRegister32[[#This Row],[Asset Class]],tblInherentImpacts30[],3,FALSE) -> 0 | AD42: =VLOOKUP(tblRiskRegister32[[#This Row],[Asset Class]],tblInherentImpacts30[],4,FALSE) -> 0 | AE42: =VLOOKUP(tblRiskRegister32[[#This Row],[Asset Class]],tblInherentImpacts30[],5,FALSE) -> 0 | AF42: =IFERROR(MAX(tblRiskRegister32[[#This Row],[Risk Treatment Safeguard Impact to Mission]:[Risk Treatment Safeguard Impact to Obligations]])*tblRiskRegister32[[#This Row],[Risk Treatment Safeguard Expectancy Score]],"") | AG42: =IF(tblRiskRegister32[[#This Row],[Risk Score]]>=AcceptableRisk,IF(tblRiskRegister32[[#This Row],[Risk Treatment Safeguard Risk Score]]<AcceptableRisk, IF(tblRiskRegister32[[#This Row],[Risk Treatment Safeguard Risk Score]]<tblRiskRegister32[[#This Row],[Risk Score]],"Yes","No"),"No"),"Yes") -> No
B43: Data | D43: 4.11 | E43: Enforce Remote Wipe Capability on Portable End-User Devices | G43: x | H43: Protect | M43: =IFERROR(VLOOKUP(tblRiskRegister32[[#This Row],[Asset Class]],tblVCDBIndex[],4,FALSE),"") -> 2 | N43: =IFERROR(VLOOKUP(10*tblRiskRegister32[[#This Row],[Safeguard Maturity Score]]+tblRiskRegister32[[#This Row],[VCDB Index]],tblHITIndexWeightTable[],4,FALSE),"") | O43: =VLOOKUP(tblRiskRegister32[[#This Row],[Asset Class]],tblInherentImpacts30[],2,FALSE) -> 0 | P43: =VLOOKUP(tblRiskRegister32[[#This Row],[Asset Class]],tblInherentImpacts30[],3,FALSE) -> 0 | Q43: =VLOOKUP(tblRiskRegister32[[#This Row],[Asset Class]],tblInherentImpacts30[],4,FALSE) -> 0 | R43: =VLOOKUP(tblRiskRegister32[[#This Row],[Asset Class]],tblInherentImpacts30[],5,FALSE) -> 0 | S43: =IFERROR(MAX(tblRiskRegister32[[#This Row],[Impact to Mission]:[Impact to Obligations]])*tblRiskRegister32[[#This Row],[Expectancy Score]],"") | T43: =tblRiskRegister32[[#This Row],[Risk Score]] | V43: 4.11 | W43: Enforce Remote Wipe Capability on Portable End-User Devices | X43: Remotely wipe enterprise data from enterprise-owned portable end-user devices when deemed appropriate such as lost or stolen devices, or when an individual no longer supports the enterprise. | AA43: =IFERROR(VLOOKUP(10*tblRiskRegister32[[#This Row],[Risk Treatment Safeguard Maturity Score]]+tblRiskRegister32[[#This Row],[VCDB Index]],tblHITIndexWeightTable[],4,FALSE),"") | AB43: =VLOOKUP(tblRiskRegister32[[#This Row],[Asset Class]],tblInherentImpacts30[],2,FALSE) -> 0 | AC43: =VLOOKUP(tblRiskRegister32[[#This Row],[Asset Class]],tblInherentImpacts30[],3,FALSE) -> 0 | AD43: =VLOOKUP(tblRiskRegister32[[#This Row],[Asset Class]],tblInherentImpacts30[],4,FALSE) -> 0 | AE43: =VLOOKUP(tblRiskRegister32[[#This Row],[Asset Class]],tblInherentImpacts30[],5,FALSE) -> 0 | AF43: =IFERROR(MAX(tblRiskRegister32[[#This Row],[Risk Treatment Safeguard Impact to Mission]:[Risk Treatment Safeguard Impact to Obligations]])*tblRiskRegister32[[#This Row],[Risk Treatment Safeguard Expectancy Score]],"") | AG43: =IF(tblRiskRegister32[[#This Row],[Risk Score]]>=AcceptableRisk,IF(tblRiskRegister32[[#This Row],[Risk Treatment Safeguard Risk Score]]<AcceptableRisk, IF(tblRiskRegister32[[#This Row],[Risk Treatment Safeguard Risk Score]]<tblRiskRegister32[[#This Row],[Risk Score]],"Yes","No"),"No"),"Yes") -> No
B44: Users | D44: 5.1 | E44: Establish and Maintain an Inventory of Accounts | F44: x | G44: x | H44: Identify | M44: =IFERROR(VLOOKUP(tblRiskRegister32[[#This Row],[Asset Class]],tblVCDBIndex[],4,FALSE),"") -> 2 | N44: =IFERROR(VLOOKUP(10*tblRiskRegister32[[#This Row],[Safeguard Maturity Score]]+tblRiskRegister32[[#This Row],[VCDB Index]],tblHITIndexWeightTable[],4,FALSE),"") | O44: =VLOOKUP(tblRiskRegister32[[#This Row],[Asset Class]],tblInherentImpacts30[],2,FALSE) -> 0 | P44: =VLOOKUP(tblRiskRegister32[[#This Row],[Asset Class]],tblInherentImpacts30[],3,FALSE) -> 0 | Q44: =VLOOKUP(tblRiskRegister32[[#This Row],[Asset Class]],tblInherentImpacts30[],4,FALSE) -> 0 | R44: =VLOOKUP(tblRiskRegister32[[#This Row],[Asset Class]],tblInherentImpacts30[],5,FALSE) -> 0 | S44: =IFERROR(MAX(tblRiskRegister32[[#This Row],[Impact to Mission]:[Impact to Obligations]])*tblRiskRegister32[[#This Row],[Expectancy Score]],"") | T44: =tblRiskRegister32[[#This Row],[Risk Score]] | V44: 5.1 | W44: Establish and Maintain an Inventory of Accounts | X44: Establish and maintain an inventory of all accounts managed in the enterprise. The inventory must at a minimum include user, administrator, and service accounts. The inventory, at a minimum, should contain the person’s name, username, start/stop dates, and department. Validate that all active accounts are authorized, on a recurring schedule at a minimum quarterly, or more frequently. | AA44: =IFERROR(VLOOKUP(10*tblRiskRegister32[[#This Row],[Risk Treatment Safeguard Maturity Score]]+tblRiskRegister32[[#This Row],[VCDB Index]],tblHITIndexWeightTable[],4,FALSE),"") | AB44: =VLOOKUP(tblRiskRegister32[[#This Row],[Asset Class]],tblInherentImpacts30[],2,FALSE) -> 0 | AC44: =VLOOKUP(tblRiskRegister32[[#This Row],[Asset Class]],tblInherentImpacts30[],3,FALSE) -> 0 | AD44: =VLOOKUP(tblRiskRegister32[[#This Row],[Asset Class]],tblInherentImpacts30[],4,FALSE) -> 0 | AE44: =VLOOKUP(tblRiskRegister32[[#This Row],[Asset Class]],tblInherentImpacts30[],5,FALSE) -> 0 | AF44: =IFERROR(MAX(tblRiskRegister32[[#This Row],[Risk Treatment Safeguard Impact to Mission]:[Risk Treatment Safeguard Impact to Obligations]])*tblRiskRegister32[[#This Row],[Risk Treatment Safeguard Expectancy Score]],"") | AG44: =IF(tblRiskRegister32[[#This Row],[Risk Score]]>=AcceptableRisk,IF(tblRiskRegister32[[#This Row],[Risk Treatment Safeguard Risk Score]]<AcceptableRisk, IF(tblRiskRegister32[[#This Row],[Risk Treatment Safeguard Risk Score]]<tblRiskRegister32[[#This Row],[Risk Score]],"Yes","No"),"No"),"Yes") -> No
B45: Users | D45: 5.2 | E45: Use Unique Passwords | F45: x | G45: x | H45: Protect | M45: =IFERROR(VLOOKUP(tblRiskRegister32[[#This Row],[Asset Class]],tblVCDBIndex[],4,FALSE),"") -> 2 | N45: =IFERROR(VLOOKUP(10*tblRiskRegister32[[#This Row],[Safeguard Maturity Score]]+tblRiskRegister32[[#This Row],[VCDB Index]],tblHITIndexWeightTable[],4,FALSE),"") | O45: =VLOOKUP(tblRiskRegister32[[#This Row],[Asset Class]],tblInherentImpacts30[],2,FALSE) -> 0 | P45: =VLOOKUP(tblRiskRegister32[[#This Row],[Asset Class]],tblInherentImpacts30[],3,FALSE) -> 0 | Q45: =VLOOKUP(tblRiskRegister32[[#This Row],[Asset Class]],tblInherentImpacts30[],4,FALSE) -> 0 | R45: =VLOOKUP(tblRiskRegister32[[#This Row],[Asset Class]],tblInherentImpacts30[],5,FALSE) -> 0 | S45: =IFERROR(MAX(tblRiskRegister32[[#This Row],[Impact to Mission]:[Impact to Obligations]])*tblRiskRegister32[[#This Row],[Expectancy Score]],"") | T45: =tblRiskRegister32[[#This Row],[Risk Score]] | V45: 5.2 | W45: Use Unique Passwords | X45: Use unique passwords for all enterprise assets. Best practice implementation includes, at a minimum, an 8-character password for accounts using Multi-Factor Authentication (MFA) and a 14-character password for accounts not using MFA. | AA45: =IFERROR(VLOOKUP(10*tblRiskRegister32[[#This Row],[Risk Treatment Safeguard Maturity Score]]+tblRiskRegister32[[#This Row],[VCDB Index]],tblHITIndexWeightTable[],4,FALSE),"") | AB45: =VLOOKUP(tblRiskRegister32[[#This Row],[Asset Class]],tblInherentImpacts30[],2,FALSE) -> 0 | AC45: =VLOOKUP(tblRiskRegister32[[#This Row],[Asset Class]],tblInherentImpacts30[],3,FALSE) -> 0 | AD45: =VLOOKUP(tblRiskRegister32[[#This Row],[Asset Class]],tblInherentImpacts30[],4,FALSE) -> 0 | AE45: =VLOOKUP(tblRiskRegister32[[#This Row],[Asset Class]],tblInherentImpacts30[],5,FALSE) -> 0 | AF45: =IFERROR(MAX(tblRiskRegister32[[#This Row],[Risk Treatment Safeguard Impact to Mission]:[Risk Treatment Safeguard Impact to Obligations]])*tblRiskRegister32[[#This Row],[Risk Treatment Safeguard Expectancy Score]],"") | AG45: =IF(tblRiskRegister32[[#This Row],[Risk Score]]>=AcceptableRisk,IF(tblRiskRegister32[[#This Row],[Risk Treatment Safeguard Risk Score]]<AcceptableRisk, IF(tblRiskRegister32[[#This Row],[Risk Treatment Safeguard Risk Score]]<tblRiskRegister32[[#This Row],[Risk Score]],"Yes","No"),"No"),"Yes") -> No
B46: Users | D46: 5.3 | E46: Disable Dormant Accounts | F46: x | G46: x | H46: Protect | M46: =IFERROR(VLOOKUP(tblRiskRegister32[[#This Row],[Asset Class]],tblVCDBIndex[],4,FALSE),"") -> 2 | N46: =IFERROR(VLOOKUP(10*tblRiskRegister32[[#This Row],[Safeguard Maturity Score]]+tblRiskRegister32[[#This Row],[VCDB Index]],tblHITIndexWeightTable[],4,FALSE),"") | O46: =VLOOKUP(tblRiskRegister32[[#This Row],[Asset Class]],tblInherentImpacts30[],2,FALSE) -> 0 | P46: =VLOOKUP(tblRiskRegister32[[#This Row],[Asset Class]],tblInherentImpacts30[],3,FALSE) -> 0 | Q46: =VLOOKUP(tblRiskRegister32[[#This Row],[Asset Class]],tblInherentImpacts30[],4,FALSE) -> 0 | R46: =VLOOKUP(tblRiskRegister32[[#This Row],[Asset Class]],tblInherentImpacts30[],5,FALSE) -> 0 | S46: =IFERROR(MAX(tblRiskRegister32[[#This Row],[Impact to Mission]:[Impact to Obligations]])*tblRiskRegister32[[#This Row],[Expectancy Score]],"") | T46: =tblRiskRegister32[[#This Row],[Risk Score]] | V46: 5.3 | W46: Disable Dormant Accounts | X46: Delete or disable any dormant accounts after a period of 45 days of inactivity, where supported. | AA46: =IFERROR(VLOOKUP(10*tblRiskRegister32[[#This Row],[Risk Treatment Safeguard Maturity Score]]+tblRiskRegister32[[#This Row],[VCDB Index]],tblHITIndexWeightTable[],4,FALSE),"") | AB46: =VLOOKUP(tblRiskRegister32[[#This Row],[Asset Class]],tblInherentImpacts30[],2,FALSE) -> 0 | AC46: =VLOOKUP(tblRiskRegister32[[#This Row],[Asset Class]],tblInherentImpacts30[],3,FALSE) -> 0 | AD46: =VLOOKUP(tblRiskRegister32[[#This Row],[Asset Class]],tblInherentImpacts30[],4,FALSE) -> 0 | AE46: =VLOOKUP(tblRiskRegister32[[#This Row],[Asset Class]],tblInherentImpacts30[],5,FALSE) -> 0 | AF46: =IFERROR(MAX(tblRiskRegister32[[#This Row],[Risk Treatment Safeguard Impact to Mission]:[Risk Treatment Safeguard Impact to Obligations]])*tblRiskRegister32[[#This Row],[Risk Treatment Safeguard Expectancy Score]],"") | AG46: =IF(tblRiskRegister32[[#This Row],[Risk Score]]>=AcceptableRisk,IF(tblRiskRegister32[[#This Row],[Risk Treatment Safeguard Risk Score]]<AcceptableRisk, IF(tblRiskRegister32[[#This Row],[Risk Treatment Safeguard Risk Score]]<tblRiskRegister32[[#This Row],[Risk Score]],"Yes","No"),"No"),"Yes") -> No
B47: Users | D47: 5.4 | E47: Restrict Administrator Privileges to Dedicated Administrator Accounts | F47: x | G47: x | H47: Protect | M47: =IFERROR(VLOOKUP(tblRiskRegister32[[#This Row],[Asset Class]],tblVCDBIndex[],4,FALSE),"") -> 2 | N47: =IFERROR(VLOOKUP(10*tblRiskRegister32[[#This Row],[Safeguard Maturity Score]]+tblRiskRegister32[[#This Row],[VCDB Index]],tblHITIndexWeightTable[],4,FALSE),"") | O47: =VLOOKUP(tblRiskRegister32[[#This Row],[Asset Class]],tblInherentImpacts30[],2,FALSE) -> 0 | P47: =VLOOKUP(tblRiskRegister32[[#This Row],[Asset Class]],tblInherentImpacts30[],3,FALSE) -> 0 | Q47: =VLOOKUP(tblRiskRegister32[[#This Row],[Asset Class]],tblInherentImpacts30[],4,FALSE) -> 0 | R47: =VLOOKUP(tblRiskRegister32[[#This Row],[Asset Class]],tblInherentImpacts30[],5,FALSE) -> 0 | S47: =IFERROR(MAX(tblRiskRegister32[[#This Row],[Impact to Mission]:[Impact to Obligations]])*tblRiskRegister32[[#This Row],[Expectancy Score]],"") | T47: =tblRiskRegister32[[#This Row],[Risk Score]] | V47: 5.4 | W47: Restrict Administrator Privileges to Dedicated Administrator Accounts | X47: Restrict administrator privileges to dedicated administrator accounts on enterprise assets. Conduct general computing activities, such as internet browsing, email, and productivity suite use, from the user’s primary, non-privileged account. | AA47: =IFERROR(VLOOKUP(10*tblRiskRegister32[[#This Row],[Risk Treatment Safeguard Maturity Score]]+tblRiskRegister32[[#This Row],[VCDB Index]],tblHITIndexWeightTable[],4,FALSE),"") | AB47: =VLOOKUP(tblRiskRegister32[[#This Row],[Asset Class]],tblInherentImpacts30[],2,FALSE) -> 0 | AC47: =VLOOKUP(tblRiskRegister32[[#This Row],[Asset Class]],tblInherentImpacts30[],3,FALSE) -> 0 | AD47: =VLOOKUP(tblRiskRegister32[[#This Row],[Asset Class]],tblInherentImpacts30[],4,FALSE) -> 0 | AE47: =VLOOKUP(tblRiskRegister32[[#This Row],[Asset Class]],tblInherentImpacts30[],5,FALSE) -> 0 | AF47: =IFERROR(MAX(tblRiskRegister32[[#This Row],[Risk Treatment Safeguard Impact to Mission]:[Risk Treatment Safeguard Impact to Obligations]])*tblRiskRegister32[[#This Row],[Risk Treatment Safeguard Expectancy Score]],"") | AG47: =IF(tblRiskRegister32[[#This Row],[Risk Score]]>=AcceptableRisk,IF(tblRiskRegister32[[#This Row],[Risk Treatment Safeguard Risk Score]]<AcceptableRisk, IF(tblRiskRegister32[[#This Row],[Risk Treatment Safeguard Risk Score]]<tblRiskRegister32[[#This Row],[Risk Score]],"Yes","No"),"No"),"Yes") -> No
B48: Users | D48: 5.5 | E48: Establish and Maintain an Inventory of Service Accounts | G48: x | H48: Identify | M48: =IFERROR(VLOOKUP(tblRiskRegister32[[#This Row],[Asset Class]],tblVCDBIndex[],4,FALSE),"") -> 2 | N48: =IFERROR(VLOOKUP(10*tblRiskRegister32[[#This Row],[Safeguard Maturity Score]]+tblRiskRegister32[[#This Row],[VCDB Index]],tblHITIndexWeightTable[],4,FALSE),"") | O48: =VLOOKUP(tblRiskRegister32[[#This Row],[Asset Class]],tblInherentImpacts30[],2,FALSE) -> 0 | P48: =VLOOKUP(tblRiskRegister32[[#This Row],[Asset Class]],tblInherentImpacts30[],3,FALSE) -> 0 | Q48: =VLOOKUP(tblRiskRegister32[[#This Row],[Asset Class]],tblInherentImpacts30[],4,FALSE) -> 0 | R48: =VLOOKUP(tblRiskRegister32[[#This Row],[Asset Class]],tblInherentImpacts30[],5,FALSE) -> 0 | S48: =IFERROR(MAX(tblRiskRegister32[[#This Row],[Impact to Mission]:[Impact to Obligations]])*tblRiskRegister32[[#This Row],[Expectancy Score]],"") | T48: =tblRiskRegister32[[#This Row],[Risk Score]] | V48: 5.5 | W48: Establish and Maintain an Inventory of Service Accounts | X48: Establish and maintain an inventory of service accounts. The inventory, at a minimum, must contain department owner, review date, and purpose. Perform service account reviews to validate that all active accounts are authorized, on a recurring schedule at a minimum quarterly, or more frequently. | AA48: =IFERROR(VLOOKUP(10*tblRiskRegister32[[#This Row],[Risk Treatment Safeguard Maturity Score]]+tblRiskRegister32[[#This Row],[VCDB Index]],tblHITIndexWeightTable[],4,FALSE),"") | AB48: =VLOOKUP(tblRiskRegister32[[#This Row],[Asset Class]],tblInherentImpacts30[],2,FALSE) -> 0 | AC48: =VLOOKUP(tblRiskRegister32[[#This Row],[Asset Class]],tblInherentImpacts30[],3,FALSE) -> 0 | AD48: =VLOOKUP(tblRiskRegister32[[#This Row],[Asset Class]],tblInherentImpacts30[],4,FALSE) -> 0 | AE48: =VLOOKUP(tblRiskRegister32[[#This Row],[Asset Class]],tblInherentImpacts30[],5,FALSE) -> 0 | AF48: =IFERROR(MAX(tblRiskRegister32[[#This Row],[Risk Treatment Safeguard Impact to Mission]:[Risk Treatment Safeguard Impact to Obligations]])*tblRiskRegister32[[#This Row],[Risk Treatment Safeguard Expectancy Score]],"") | AG48: =IF(tblRiskRegister32[[#This Row],[Risk Score]]>=AcceptableRisk,IF(tblRiskRegister32[[#This Row],[Risk Treatment Safeguard Risk Score]]<AcceptableRisk, IF(tblRiskRegister32[[#This Row],[Risk Treatment Safeguard Risk Score]]<tblRiskRegister32[[#This Row],[Risk Score]],"Yes","No"),"No"),"Yes") -> No
B49: Users | D49: 5.6 | E49: Centralize Account Management | G49: x | H49: Govern | M49: =IFERROR(VLOOKUP(tblRiskRegister32[[#This Row],[Asset Class]],tblVCDBIndex[],4,FALSE),"") -> 2 | N49: =IFERROR(VLOOKUP(10*tblRiskRegister32[[#This Row],[Safeguard Maturity Score]]+tblRiskRegister32[[#This Row],[VCDB Index]],tblHITIndexWeightTable[],4,FALSE),"") | O49: =VLOOKUP(tblRiskRegister32[[#This Row],[Asset Class]],tblInherentImpacts30[],2,FALSE) -> 0 | P49: =VLOOKUP(tblRiskRegister32[[#This Row],[Asset Class]],tblInherentImpacts30[],3,FALSE) -> 0 | Q49: =VLOOKUP(tblRiskRegister32[[#This Row],[Asset Class]],tblInherentImpacts30[],4,FALSE) -> 0 | R49: =VLOOKUP(tblRiskRegister32[[#This Row],[Asset Class]],tblInherentImpacts30[],5,FALSE) -> 0 | S49: =IFERROR(MAX(tblRiskRegister32[[#This Row],[Impact to Mission]:[Impact to Obligations]])*tblRiskRegister32[[#This Row],[Expectancy Score]],"") | T49: =tblRiskRegister32[[#This Row],[Risk Score]] | V49: 5.6 | W49: Centralize Account Management | X49: Centralize account management through a directory or identity service. | AA49: =IFERROR(VLOOKUP(10*tblRiskRegister32[[#This Row],[Risk Treatment Safeguard Maturity Score]]+tblRiskRegister32[[#This Row],[VCDB Index]],tblHITIndexWeightTable[],4,FALSE),"") | AB49: =VLOOKUP(tblRiskRegister32[[#This Row],[Asset Class]],tblInherentImpacts30[],2,FALSE) -> 0 | AC49: =VLOOKUP(tblRiskRegister32[[#This Row],[Asset Class]],tblInherentImpacts30[],3,FALSE) -> 0 | AD49: =VLOOKUP(tblRiskRegister32[[#This Row],[Asset Class]],tblInherentImpacts30[],4,FALSE) -> 0 | AE49: =VLOOKUP(tblRiskRegister32[[#This Row],[Asset Class]],tblInherentImpacts30[],5,FALSE) -> 0 | AF49: =IFERROR(MAX(tblRiskRegister32[[#This Row],[Risk Treatment Safeguard Impact to Mission]:[Risk Treatment Safeguard Impact to Obligations]])*tblRiskRegister32[[#This Row],[Risk Treatment Safeguard Expectancy Score]],"") | AG49: =IF(tblRiskRegister32[[#This Row],[Risk Score]]>=AcceptableRisk,IF(tblRiskRegister32[[#This Row],[Risk Treatment Safeguard Risk Score]]<AcceptableRisk, IF(tblRiskRegister32[[#This Row],[Risk Treatment Safeguard Risk Score]]<tblRiskRegister32[[#This Row],[Risk Score]],"Yes","No"),"No"),"Yes") -> No
B50: Documentation | D50: 6.1 | E50: Establish an Access Granting Process | F50: x | G50: x | H50: Govern | M50: =IFERROR(VLOOKUP(tblRiskRegister32[[#This Row],[Asset Class]],tblVCDBIndex[],4,FALSE),"") -> 2 | N50: =IFERROR(VLOOKUP(10*tblRiskRegister32[[#This Row],[Safeguard Maturity Score]]+tblRiskRegister32[[#This Row],[VCDB Index]],tblHITIndexWeightTable[],4,FALSE),"") | O50: =VLOOKUP(tblRiskRegister32[[#This Row],[Asset Class]],tblInherentImpacts30[],2,FALSE) -> 0 | P50: =VLOOKUP(tblRiskRegister32[[#This Row],[Asset Class]],tblInherentImpacts30[],3,FALSE) -> 0 | Q50: =VLOOKUP(tblRiskRegister32[[#This Row],[Asset Class]],tblInherentImpacts30[],4,FALSE) -> 0 | R50: =VLOOKUP(tblRiskRegister32[[#This Row],[Asset Class]],tblInherentImpacts30[],5,FALSE) -> 0 | S50: =IFERROR(MAX(tblRiskRegister32[[#This Row],[Impact to Mission]:[Impact to Obligations]])*tblRiskRegister32[[#This Row],[Expectancy Score]],"") | T50: =tblRiskRegister32[[#This Row],[Risk Score]] | V50: 6.1 | W50: Establish an Access Granting Process | X50: Establish and follow a documented process, preferably automated, for granting access to enterprise assets upon new hire or role change of a user. | AA50: =IFERROR(VLOOKUP(10*tblRiskRegister32[[#This Row],[Risk Treatment Safeguard Maturity Score]]+tblRiskRegister32[[#This Row],[VCDB Index]],tblHITIndexWeightTable[],4,FALSE),"") | AB50: =VLOOKUP(tblRiskRegister32[[#This Row],[Asset Class]],tblInherentImpacts30[],2,FALSE) -> 0 | AC50: =VLOOKUP(tblRiskRegister32[[#This Row],[Asset Class]],tblInherentImpacts30[],3,FALSE) -> 0 | AD50: =VLOOKUP(tblRiskRegister32[[#This Row],[Asset Class]],tblInherentImpacts30[],4,FALSE) -> 0 | AE50: =VLOOKUP(tblRiskRegister32[[#This Row],[Asset Class]],tblInherentImpacts30[],5,FALSE) -> 0 | AF50: =IFERROR(MAX(tblRiskRegister32[[#This Row],[Risk Treatment Safeguard Impact to Mission]:[Risk Treatment Safeguard Impact to Obligations]])*tblRiskRegister32[[#This Row],[Risk Treatment Safeguard Expectancy Score]],"") | AG50: =IF(tblRiskRegister32[[#This Row],[Risk Score]]>=AcceptableRisk,IF(tblRiskRegister32[[#This Row],[Risk Treatment Safeguard Risk Score]]<AcceptableRisk, IF(tblRiskRegister32[[#This Row],[Risk Treatment Safeguard Risk Score]]<tblRiskRegister32[[#This Row],[Risk Score]],"Yes","No"),"No"),"Yes") -> No
B51: Documentation | D51: 6.2 | E51: Establish an Access Revoking Process | F51: x | G51: x | H51: Govern | M51: =IFERROR(VLOOKUP(tblRiskRegister32[[#This Row],[Asset Class]],tblVCDBIndex[],4,FALSE),"") -> 2 | N51: =IFERROR(VLOOKUP(10*tblRiskRegister32[[#This Row],[Safeguard Maturity Score]]+tblRiskRegister32[[#This Row],[VCDB Index]],tblHITIndexWeightTable[],4,FALSE),"") | O51: =VLOOKUP(tblRiskRegister32[[#This Row],[Asset Class]],tblInherentImpacts30[],2,FALSE) -> 0 | P51: =VLOOKUP(tblRiskRegister32[[#This Row],[Asset Class]],tblInherentImpacts30[],3,FALSE) -> 0 | Q51: =VLOOKUP(tblRiskRegister32[[#This Row],[Asset Class]],tblInherentImpacts30[],4,FALSE) -> 0 | R51: =VLOOKUP(tblRiskRegister32[[#This Row],[Asset Class]],tblInherentImpacts30[],5,FALSE) -> 0 | S51: =IFERROR(MAX(tblRiskRegister32[[#This Row],[Impact to Mission]:[Impact to Obligations]])*tblRiskRegister32[[#This Row],[Expectancy Score]],"") | T51: =tblRiskRegister32[[#This Row],[Risk Score]] | V51: 6.2 | W51: Establish an Access Revoking Process | X51: Establish and follow a process, preferably automated, for revoking access to enterprise assets, through disabling accounts immediately upon termination, rights revocation, or role change of a user. Disabling accounts, instead of deleting accounts, may be necessary to preserve audit trails. | AA51: =IFERROR(VLOOKUP(10*tblRiskRegister32[[#This Row],[Risk Treatment Safeguard Maturity Score]]+tblRiskRegister32[[#This Row],[VCDB Index]],tblHITIndexWeightTable[],4,FALSE),"") | AB51: =VLOOKUP(tblRiskRegister32[[#This Row],[Asset Class]],tblInherentImpacts30[],2,FALSE) -> 0 | AC51: =VLOOKUP(tblRiskRegister32[[#This Row],[Asset Class]],tblInherentImpacts30[],3,FALSE) -> 0 | AD51: =VLOOKUP(tblRiskRegister32[[#This Row],[Asset Class]],tblInherentImpacts30[],4,FALSE) -> 0 | AE51: =VLOOKUP(tblRiskRegister32[[#This Row],[Asset Class]],tblInherentImpacts30[],5,FALSE) -> 0 | AF51: =IFERROR(MAX(tblRiskRegister32[[#This Row],[Risk Treatment Safeguard Impact to Mission]:[Risk Treatment Safeguard Impact to Obligations]])*tblRiskRegister32[[#This Row],[Risk Treatment Safeguard Expectancy Score]],"") | AG51: =IF(tblRiskRegister32[[#This Row],[Risk Score]]>=AcceptableRisk,IF(tblRiskRegister32[[#This Row],[Risk Treatment Safeguard Risk Score]]<AcceptableRisk, IF(tblRiskRegister32[[#This Row],[Risk Treatment Safeguard Risk Score]]<tblRiskRegister32[[#This Row],[Risk Score]],"Yes","No"),"No"),"Yes") -> No
B52: Users | D52: 6.3 | E52: Require MFA for Externally-Exposed Applications | F52: x | G52: x | H52: Protect | M52: =IFERROR(VLOOKUP(tblRiskRegister32[[#This Row],[Asset Class]],tblVCDBIndex[],4,FALSE),"") -> 2 | N52: =IFERROR(VLOOKUP(10*tblRiskRegister32[[#This Row],[Safeguard Maturity Score]]+tblRiskRegister32[[#This Row],[VCDB Index]],tblHITIndexWeightTable[],4,FALSE),"") | O52: =VLOOKUP(tblRiskRegister32[[#This Row],[Asset Class]],tblInherentImpacts30[],2,FALSE) -> 0 | P52: =VLOOKUP(tblRiskRegister32[[#This Row],[Asset Class]],tblInherentImpacts30[],3,FALSE) -> 0 | Q52: =VLOOKUP(tblRiskRegister32[[#This Row],[Asset Class]],tblInherentImpacts30[],4,FALSE) -> 0 | R52: =VLOOKUP(tblRiskRegister32[[#This Row],[Asset Class]],tblInherentImpacts30[],5,FALSE) -> 0 | S52: =IFERROR(MAX(tblRiskRegister32[[#This Row],[Impact to Mission]:[Impact to Obligations]])*tblRiskRegister32[[#This Row],[Expectancy Score]],"") | T52: =tblRiskRegister32[[#This Row],[Risk Score]] | V52: 6.3 | W52: Require MFA for Externally-Exposed Applications | X52: Require all externally-exposed enterprise or third-party applications to enforce MFA, where supported. Enforcing MFA through a directory service or SSO provider is a satisfactory implementation of this Safeguard. | AA52: =IFERROR(VLOOKUP(10*tblRiskRegister32[[#This Row],[Risk Treatment Safeguard Maturity Score]]+tblRiskRegister32[[#This Row],[VCDB Index]],tblHITIndexWeightTable[],4,FALSE),"") | AB52: =VLOOKUP(tblRiskRegister32[[#This Row],[Asset Class]],tblInherentImpacts30[],2,FALSE) -> 0 | AC52: =VLOOKUP(tblRiskRegister32[[#This Row],[Asset Class]],tblInherentImpacts30[],3,FALSE) -> 0 | AD52: =VLOOKUP(tblRiskRegister32[[#This Row],[Asset Class]],tblInherentImpacts30[],4,FALSE) -> 0 | AE52: =VLOOKUP(tblRiskRegister32[[#This Row],[Asset Class]],tblInherentImpacts30[],5,FALSE) -> 0 | AF52: =IFERROR(MAX(tblRiskRegister32[[#This Row],[Risk Treatment Safeguard Impact to Mission]:[Risk Treatment Safeguard Impact to Obligations]])*tblRiskRegister32[[#This Row],[Risk Treatment Safeguard Expectancy Score]],"") | AG52: =IF(tblRiskRegister32[[#This Row],[Risk Score]]>=AcceptableRisk,IF(tblRiskRegister32[[#This Row],[Risk Treatment Safeguard Risk Score]]<AcceptableRisk, IF(tblRiskRegister32[[#This Row],[Risk Treatment Safeguard Risk Score]]<tblRiskRegister32[[#This Row],[Risk Score]],"Yes","No"),"No"),"Yes") -> No
B53: Users | D53: 6.4 | E53: Require MFA for Remote Network Access | F53: x | G53: x | H53: Protect | M53: =IFERROR(VLOOKUP(tblRiskRegister32[[#This Row],[Asset Class]],tblVCDBIndex[],4,FALSE),"") -> 2 | N53: =IFERROR(VLOOKUP(10*tblRiskRegister32[[#This Row],[Safeguard Maturity Score]]+tblRiskRegister32[[#This Row],[VCDB Index]],tblHITIndexWeightTable[],4,FALSE),"") | O53: =VLOOKUP(tblRiskRegister32[[#This Row],[Asset Class]],tblInherentImpacts30[],2,FALSE) -> 0 | P53: =VLOOKUP(tblRiskRegister32[[#This Row],[Asset Class]],tblInherentImpacts30[],3,FALSE) -> 0 | Q53: =VLOOKUP(tblRiskRegister32[[#This Row],[Asset Class]],tblInherentImpacts30[],4,FALSE) -> 0 | R53: =VLOOKUP(tblRiskRegister32[[#This Row],[Asset Class]],tblInherentImpacts30[],5,FALSE) -> 0 | S53: =IFERROR(MAX(tblRiskRegister32[[#This Row],[Impact to Mission]:[Impact to Obligations]])*tblRiskRegister32[[#This Row],[Expectancy Score]],"") | T53: =tblRiskRegister32[[#This Row],[Risk Score]] | V53: 6.4 | W53: Require MFA for Remote Network Access | X53: Require MFA for remote network access. | AA53: =IFERROR(VLOOKUP(10*tblRiskRegister32[[#This Row],[Risk Treatment Safeguard Maturity Score]]+tblRiskRegister32[[#This Row],[VCDB Index]],tblHITIndexWeightTable[],4,FALSE),"") | AB53: =VLOOKUP(tblRiskRegister32[[#This Row],[Asset Class]],tblInherentImpacts30[],2,FALSE) -> 0 | AC53: =VLOOKUP(tblRiskRegister32[[#This Row],[Asset Class]],tblInherentImpacts30[],3,FALSE) -> 0 | AD53: =VLOOKUP(tblRiskRegister32[[#This Row],[Asset Class]],tblInherentImpacts30[],4,FALSE) -> 0 | AE53: =VLOOKUP(tblRiskRegister32[[#This Row],[Asset Class]],tblInherentImpacts30[],5,FALSE) -> 0 | AF53: =IFERROR(MAX(tblRiskRegister32[[#This Row],[Risk Treatment Safeguard Impact to Mission]:[Risk Treatment Safeguard Impact to Obligations]])*tblRiskRegister32[[#This Row],[Risk Treatment Safeguard Expectancy Score]],"") | AG53: =IF(tblRiskRegister32[[#This Row],[Risk Score]]>=AcceptableRisk,IF(tblRiskRegister32[[#This Row],[Risk Treatment Safeguard Risk Score]]<AcceptableRisk, IF(tblRiskRegister32[[#This Row],[Risk Treatment Safeguard Risk Score]]<tblRiskRegister32[[#This Row],[Risk Score]],"Yes","No"),"No"),"Yes") -> No
B54: Users | D54: 6.5 | E54: Require MFA for Administrative Access | F54: x | G54: x | H54: Protect | M54: =IFERROR(VLOOKUP(tblRiskRegister32[[#This Row],[Asset Class]],tblVCDBIndex[],4,FALSE),"") -> 2 | N54: =IFERROR(VLOOKUP(10*tblRiskRegister32[[#This Row],[Safeguard Maturity Score]]+tblRiskRegister32[[#This Row],[VCDB Index]],tblHITIndexWeightTable[],4,FALSE),"") | O54: =VLOOKUP(tblRiskRegister32[[#This Row],[Asset Class]],tblInherentImpacts30[],2,FALSE) -> 0 | P54: =VLOOKUP(tblRiskRegister32[[#This Row],[Asset Class]],tblInherentImpacts30[],3,FALSE) -> 0 | Q54: =VLOOKUP(tblRiskRegister32[[#This Row],[Asset Class]],tblInherentImpacts30[],4,FALSE) -> 0 | R54: =VLOOKUP(tblRiskRegister32[[#This Row],[Asset Class]],tblInherentImpacts30[],5,FALSE) -> 0 | S54: =IFERROR(MAX(tblRiskRegister32[[#This Row],[Impact to Mission]:[Impact to Obligations]])*tblRiskRegister32[[#This Row],[Expectancy Score]],"") | T54: =tblRiskRegister32[[#This Row],[Risk Score]] | V54: 6.5 | W54: Require MFA for Administrative Access | X54: Require MFA for all administrative access accounts, where supported, on all enterprise assets, whether managed on-site or through a service provider. | AA54: =IFERROR(VLOOKUP(10*tblRiskRegister32[[#This Row],[Risk Treatment Safeguard Maturity Score]]+tblRiskRegister32[[#This Row],[VCDB Index]],tblHITIndexWeightTable[],4,FALSE),"") | AB54: =VLOOKUP(tblRiskRegister32[[#This Row],[Asset Class]],tblInherentImpacts30[],2,FALSE) -> 0 | AC54: =VLOOKUP(tblRiskRegister32[[#This Row],[Asset Class]],tblInherentImpacts30[],3,FALSE) -> 0 | AD54: =VLOOKUP(tblRiskRegister32[[#This Row],[Asset Class]],tblInherentImpacts30[],4,FALSE) -> 0 | AE54: =VLOOKUP(tblRiskRegister32[[#This Row],[Asset Class]],tblInherentImpacts30[],5,FALSE) -> 0 | AF54: =IFERROR(MAX(tblRiskRegister32[[#This Row],[Risk Treatment Safeguard Impact to Mission]:[Risk Treatment Safeguard Impact to Obligations]])*tblRiskRegister32[[#This Row],[Risk Treatment Safeguard Expectancy Score]],"") | AG54: =IF(tblRiskRegister32[[#This Row],[Risk Score]]>=AcceptableRisk,IF(tblRiskRegister32[[#This Row],[Risk Treatment Safeguard Risk Score]]<AcceptableRisk, IF(tblRiskRegister32[[#This Row],[Risk Treatment Safeguard Risk Score]]<tblRiskRegister32[[#This Row],[Risk Score]],"Yes","No"),"No"),"Yes") -> No
B55: Software | D55: 6.6 | E55: Establish and Maintain an Inventory of Authentication and Authorization Systems | G55: x | H55: Identify | M55: =IFERROR(VLOOKUP(tblRiskRegister32[[#This Row],[Asset Class]],tblVCDBIndex[],4,FALSE),"") -> 2 | N55: =IFERROR(VLOOKUP(10*tblRiskRegister32[[#This Row],[Safeguard Maturity Score]]+tblRiskRegister32[[#This Row],[VCDB Index]],tblHITIndexWeightTable[],4,FALSE),"") | O55: =VLOOKUP(tblRiskRegister32[[#This Row],[Asset Class]],tblInherentImpacts30[],2,FALSE) -> 0 | P55: =VLOOKUP(tblRiskRegister32[[#This Row],[Asset Class]],tblInherentImpacts30[],3,FALSE) -> 0 | Q55: =VLOOKUP(tblRiskRegister32[[#This Row],[Asset Class]],tblInherentImpacts30[],4,FALSE) -> 0 | R55: =VLOOKUP(tblRiskRegister32[[#This Row],[Asset Class]],tblInherentImpacts30[],5,FALSE) -> 0 | S55: =IFERROR(MAX(tblRiskRegister32[[#This Row],[Impact to Mission]:[Impact to Obligations]])*tblRiskRegister32[[#This Row],[Expectancy Score]],"") | T55: =tblRiskRegister32[[#This Row],[Risk Score]] | V55: 6.6 | W55: Establish and Maintain an Inventory of Authentication and Authorization Systems | X55: Establish and maintain an inventory of the enterprise’s authentication and authorization systems, including those hosted on-site or at a remote service provider. Review and update the inventory, at a minimum, annually, or more frequently. | AA55: =IFERROR(VLOOKUP(10*tblRiskRegister32[[#This Row],[Risk Treatment Safeguard Maturity Score]]+tblRiskRegister32[[#This Row],[VCDB Index]],tblHITIndexWeightTable[],4,FALSE),"") | AB55: =VLOOKUP(tblRiskRegister32[[#This Row],[Asset Class]],tblInherentImpacts30[],2,FALSE) -> 0 | AC55: =VLOOKUP(tblRiskRegister32[[#This Row],[Asset Class]],tblInherentImpacts30[],3,FALSE) -> 0 | AD55: =VLOOKUP(tblRiskRegister32[[#This Row],[Asset Class]],tblInherentImpacts30[],4,FALSE) -> 0 | AE55: =VLOOKUP(tblRiskRegister32[[#This Row],[Asset Class]],tblInherentImpacts30[],5,FALSE) -> 0 | AF55: =IFERROR(MAX(tblRiskRegister32[[#This Row],[Risk Treatment Safeguard Impact to Mission]:[Risk Treatment Safeguard Impact to Obligations]])*tblRiskRegister32[[#This Row],[Risk Treatment Safeguard Expectancy Score]],"") | AG55: =IF(tblRiskRegister32[[#This Row],[Risk Score]]>=AcceptableRisk,IF(tblRiskRegister32[[#This Row],[Risk Treatment Safeguard Risk Score]]<AcceptableRisk, IF(tblRiskRegister32[[#This Row],[Risk Treatment Safeguard Risk Score]]<tblRiskRegister32[[#This Row],[Risk Score]],"Yes","No"),"No"),"Yes") -> No
B56: Users | D56: 6.7 | E56: Centralize Access Control | G56: x | H56: Protect | M56: =IFERROR(VLOOKUP(tblRiskRegister32[[#This Row],[Asset Class]],tblVCDBIndex[],4,FALSE),"") -> 2 | N56: =IFERROR(VLOOKUP(10*tblRiskRegister32[[#This Row],[Safeguard Maturity Score]]+tblRiskRegister32[[#This Row],[VCDB Index]],tblHITIndexWeightTable[],4,FALSE),"") | O56: =VLOOKUP(tblRiskRegister32[[#This Row],[Asset Class]],tblInherentImpacts30[],2,FALSE) -> 0 | P56: =VLOOKUP(tblRiskRegister32[[#This Row],[Asset Class]],tblInherentImpacts30[],3,FALSE) -> 0 | Q56: =VLOOKUP(tblRiskRegister32[[#This Row],[Asset Class]],tblInherentImpacts30[],4,FALSE) -> 0 | R56: =VLOOKUP(tblRiskRegister32[[#This Row],[Asset Class]],tblInherentImpacts30[],5,FALSE) -> 0 | S56: =IFERROR(MAX(tblRiskRegister32[[#This Row],[Impact to Mission]:[Impact to Obligations]])*tblRiskRegister32[[#This Row],[Expectancy Score]],"") | T56: =tblRiskRegister32[[#This Row],[Risk Score]] | V56: 6.7 | W56: Centralize Access Control | X56: Centralize access control for all enterprise assets through a directory service or SSO provider, where supported. | AA56: =IFERROR(VLOOKUP(10*tblRiskRegister32[[#This Row],[Risk Treatment Safeguard Maturity Score]]+tblRiskRegister32[[#This Row],[VCDB Index]],tblHITIndexWeightTable[],4,FALSE),"") | AB56: =VLOOKUP(tblRiskRegister32[[#This Row],[Asset Class]],tblInherentImpacts30[],2,FALSE) -> 0 | AC56: =VLOOKUP(tblRiskRegister32[[#This Row],[Asset Class]],tblInherentImpacts30[],3,FALSE) -> 0 | AD56: =VLOOKUP(tblRiskRegister32[[#This Row],[Asset Class]],tblInherentImpacts30[],4,FALSE) -> 0 | AE56: =VLOOKUP(tblRiskRegister32[[#This Row],[Asset Class]],tblInherentImpacts30[],5,FALSE) -> 0 | AF56: =IFERROR(MAX(tblRiskRegister32[[#This Row],[Risk Treatment Safeguard Impact to Mission]:[Risk Treatment Safeguard Impact to Obligations]])*tblRiskRegister32[[#This Row],[Risk Treatment Safeguard Expectancy Score]],"") | AG56: =IF(tblRiskRegister32[[#This Row],[Risk Score]]>=AcceptableRisk,IF(tblRiskRegister32[[#This Row],[Risk Treatment Safeguard Risk Score]]<AcceptableRisk, IF(tblRiskRegister32[[#This Row],[Risk Treatment Safeguard Risk Score]]<tblRiskRegister32[[#This Row],[Risk Score]],"Yes","No"),"No"),"Yes") -> No
B57: Documentation | D57: 7.1 | E57: Establish and Maintain a Vulnerability Management Process | F57: x | G57: x | H57: Govern | M57: =IFERROR(VLOOKUP(tblRiskRegister32[[#This Row],[Asset Class]],tblVCDBIndex[],4,FALSE),"") -> 2 | N57: =IFERROR(VLOOKUP(10*tblRiskRegister32[[#This Row],[Safeguard Maturity Score]]+tblRiskRegister32[[#This Row],[VCDB Index]],tblHITIndexWeightTable[],4,FALSE),"") | O57: =VLOOKUP(tblRiskRegister32[[#This Row],[Asset Class]],tblInherentImpacts30[],2,FALSE) -> 0 | P57: =VLOOKUP(tblRiskRegister32[[#This Row],[Asset Class]],tblInherentImpacts30[],3,FALSE) -> 0 | Q57: =VLOOKUP(tblRiskRegister32[[#This Row],[Asset Class]],tblInherentImpacts30[],4,FALSE) -> 0 | R57: =VLOOKUP(tblRiskRegister32[[#This Row],[Asset Class]],tblInherentImpacts30[],5,FALSE) -> 0 | S57: =IFERROR(MAX(tblRiskRegister32[[#This Row],[Impact to Mission]:[Impact to Obligations]])*tblRiskRegister32[[#This Row],[Expectancy Score]],"") | T57: =tblRiskRegister32[[#This Row],[Risk Score]] | V57: 7.1 | W57: Establish and Maintain a Vulnerability Management Process | X57: Establish and maintain a documented vulnerability management process for enterprise assets. Review and update documentation annually, or when significant enterprise changes occur that could impact this Safeguard. | AA57: =IFERROR(VLOOKUP(10*tblRiskRegister32[[#This Row],[Risk Treatment Safeguard Maturity Score]]+tblRiskRegister32[[#This Row],[VCDB Index]],tblHITIndexWeightTable[],4,FALSE),"") | AB57: =VLOOKUP(tblRiskRegister32[[#This Row],[Asset Class]],tblInherentImpacts30[],2,FALSE) -> 0 | AC57: =VLOOKUP(tblRiskRegister32[[#This Row],[Asset Class]],tblInherentImpacts30[],3,FALSE) -> 0 | AD57: =VLOOKUP(tblRiskRegister32[[#This Row],[Asset Class]],tblInherentImpacts30[],4,FALSE) -> 0 | AE57: =VLOOKUP(tblRiskRegister32[[#This Row],[Asset Class]],tblInherentImpacts30[],5,FALSE) -> 0 | AF57: =IFERROR(MAX(tblRiskRegister32[[#This Row],[Risk Treatment Safeguard Impact to Mission]:[Risk Treatment Safeguard Impact to Obligations]])*tblRiskRegister32[[#This Row],[Risk Treatment Safeguard Expectancy Score]],"") | AG57: =IF(tblRiskRegister32[[#This Row],[Risk Score]]>=AcceptableRisk,IF(tblRiskRegister32[[#This Row],[Risk Treatment Safeguard Risk Score]]<AcceptableRisk, IF(tblRiskRegister32[[#This Row],[Risk Treatment Safeguard Risk Score]]<tblRiskRegister32[[#This Row],[Risk Score]],"Yes","No"),"No"),"Yes") -> No
B58: Documentation | D58: 7.2 | E58: Establish and Maintain a Remediation Process | F58: x | G58: x | H58: Govern | M58: =IFERROR(VLOOKUP(tblRiskRegister32[[#This Row],[Asset Class]],tblVCDBIndex[],4,FALSE),"") -> 2 | N58: =IFERROR(VLOOKUP(10*tblRiskRegister32[[#This Row],[Safeguard Maturity Score]]+tblRiskRegister32[[#This Row],[VCDB Index]],tblHITIndexWeightTable[],4,FALSE),"") | O58: =VLOOKUP(tblRiskRegister32[[#This Row],[Asset Class]],tblInherentImpacts30[],2,FALSE) -> 0 | P58: =VLOOKUP(tblRiskRegister32[[#This Row],[Asset Class]],tblInherentImpacts30[],3,FALSE) -> 0 | Q58: =VLOOKUP(tblRiskRegister32[[#This Row],[Asset Class]],tblInherentImpacts30[],4,FALSE) -> 0 | R58: =VLOOKUP(tblRiskRegister32[[#This Row],[Asset Class]],tblInherentImpacts30[],5,FALSE) -> 0 | S58: =IFERROR(MAX(tblRiskRegister32[[#This Row],[Impact to Mission]:[Impact to Obligations]])*tblRiskRegister32[[#This Row],[Expectancy Score]],"") | T58: =tblRiskRegister32[[#This Row],[Risk Score]] | V58: 7.2 | W58: Establish and Maintain a Remediation Process | X58: Establish and maintain a risk-based remediation strategy documented in a remediation process, with monthly, or more frequent, reviews. | AA58: =IFERROR(VLOOKUP(10*tblRiskRegister32[[#This Row],[Risk Treatment Safeguard Maturity Score]]+tblRiskRegister32[[#This Row],[VCDB Index]],tblHITIndexWeightTable[],4,FALSE),"") | AB58: =VLOOKUP(tblRiskRegister32[[#This Row],[Asset Class]],tblInherentImpacts30[],2,FALSE) -> 0 | AC58: =VLOOKUP(tblRiskRegister32[[#This Row],[Asset Class]],tblInherentImpacts30[],3,FALSE) -> 0 | AD58: =VLOOKUP(tblRiskRegister32[[#This Row],[Asset Class]],tblInherentImpacts30[],4,FALSE) -> 0 | AE58: =VLOOKUP(tblRiskRegister32[[#This Row],[Asset Class]],tblInherentImpacts30[],5,FALSE) -> 0 | AF58: =IFERROR(MAX(tblRiskRegister32[[#This Row],[Risk Treatment Safeguard Impact to Mission]:[Risk Treatment Safeguard Impact to Obligations]])*tblRiskRegister32[[#This Row],[Risk Treatment Safeguard Expectancy Score]],"") | AG58: =IF(tblRiskRegister32[[#This Row],[Risk Score]]>=AcceptableRisk,IF(tblRiskRegister32[[#This Row],[Risk Treatment Safeguard Risk Score]]<AcceptableRisk, IF(tblRiskRegister32[[#This Row],[Risk Treatment Safeguard Risk Score]]<tblRiskRegister32[[#This Row],[Risk Score]],"Yes","No"),"No"),"Yes") -> No
B59: Software | D59: 7.3 | E59: Perform Automated Operating System Patch Management | F59: x | G59: x | H59: Protect | M59: =IFERROR(VLOOKUP(tblRiskRegister32[[#This Row],[Asset Class]],tblVCDBIndex[],4,FALSE),"") -> 2 | N59: =IFERROR(VLOOKUP(10*tblRiskRegister32[[#This Row],[Safeguard Maturity Score]]+tblRiskRegister32[[#This Row],[VCDB Index]],tblHITIndexWeightTable[],4,FALSE),"") | O59: =VLOOKUP(tblRiskRegister32[[#This Row],[Asset Class]],tblInherentImpacts30[],2,FALSE) -> 0 | P59: =VLOOKUP(tblRiskRegister32[[#This Row],[Asset Class]],tblInherentImpacts30[],3,FALSE) -> 0 | Q59: =VLOOKUP(tblRiskRegister32[[#This Row],[Asset Class]],tblInherentImpacts30[],4,FALSE) -> 0 | R59: =VLOOKUP(tblRiskRegister32[[#This Row],[Asset Class]],tblInherentImpacts30[],5,FALSE) -> 0 | S59: =IFERROR(MAX(tblRiskRegister32[[#This Row],[Impact to Mission]:[Impact to Obligations]])*tblRiskRegister32[[#This Row],[Expectancy Score]],"") | T59: =tblRiskRegister32[[#This Row],[Risk Score]] | V59: 7.3 | W59: Perform Automated Operating System Patch Management | X59: Perform operating system updates on enterprise assets through automated patch management on a monthly, or more frequent, basis. | AA59: =IFERROR(VLOOKUP(10*tblRiskRegister32[[#This Row],[Risk Treatment Safeguard Maturity Score]]+tblRiskRegister32[[#This Row],[VCDB Index]],tblHITIndexWeightTable[],4,FALSE),"") | AB59: =VLOOKUP(tblRiskRegister32[[#This Row],[Asset Class]],tblInherentImpacts30[],2,FALSE) -> 0 | AC59: =VLOOKUP(tblRiskRegister32[[#This Row],[Asset Class]],tblInherentImpacts30[],3,FALSE) -> 0 | AD59: =VLOOKUP(tblRiskRegister32[[#This Row],[Asset Class]],tblInherentImpacts30[],4,FALSE) -> 0 | AE59: =VLOOKUP(tblRiskRegister32[[#This Row],[Asset Class]],tblInherentImpacts30[],5,FALSE) -> 0 | AF59: =IFERROR(MAX(tblRiskRegister32[[#This Row],[Risk Treatment Safeguard Impact to Mission]:[Risk Treatment Safeguard Impact to Obligations]])*tblRiskRegister32[[#This Row],[Risk Treatment Safeguard Expectancy Score]],"") | AG59: =IF(tblRiskRegister32[[#This Row],[Risk Score]]>=AcceptableRisk,IF(tblRiskRegister32[[#This Row],[Risk Treatment Safeguard Risk Score]]<AcceptableRisk, IF(tblRiskRegister32[[#This Row],[Risk Treatment Safeguard Risk Score]]<tblRiskRegister32[[#This Row],[Risk Score]],"Yes","No"),"No"),"Yes") -> No
B60: Software | D60: 7.4 | E60: Perform Automated Application Patch Management | F60: x | G60: x | H60: Protect | M60: =IFERROR(VLOOKUP(tblRiskRegister32[[#This Row],[Asset Class]],tblVCDBIndex[],4,FALSE),"") -> 2 | N60: =IFERROR(VLOOKUP(10*tblRiskRegister32[[#This Row],[Safeguard Maturity Score]]+tblRiskRegister32[[#This Row],[VCDB Index]],tblHITIndexWeightTable[],4,FALSE),"") | O60: =VLOOKUP(tblRiskRegister32[[#This Row],[Asset Class]],tblInherentImpacts30[],2,FALSE) -> 0 | P60: =VLOOKUP(tblRiskRegister32[[#This Row],[Asset Class]],tblInherentImpacts30[],3,FALSE) -> 0 | Q60: =VLOOKUP(tblRiskRegister32[[#This Row],[Asset Class]],tblInherentImpacts30[],4,FALSE) -> 0 | R60: =VLOOKUP(tblRiskRegister32[[#This Row],[Asset Class]],tblInherentImpacts30[],5,FALSE) -> 0 | S60: =IFERROR(MAX(tblRiskRegister32[[#This Row],[Impact to Mission]:[Impact to Obligations]])*tblRiskRegister32[[#This Row],[Expectancy Score]],"") | T60: =tblRiskRegister32[[#This Row],[Risk Score]] | V60: 7.4 | W60: Perform Automated Application Patch Management | X60: Perform application updates on enterprise assets through automated patch management on a monthly, or more frequent, basis. | AA60: =IFERROR(VLOOKUP(10*tblRiskRegister32[[#This Row],[Risk Treatment Safeguard Maturity Score]]+tblRiskRegister32[[#This Row],[VCDB Index]],tblHITIndexWeightTable[],4,FALSE),"") | AB60: =VLOOKUP(tblRiskRegister32[[#This Row],[Asset Class]],tblInherentImpacts30[],2,FALSE) -> 0 | AC60: =VLOOKUP(tblRiskRegister32[[#This Row],[Asset Class]],tblInherentImpacts30[],3,FALSE) -> 0 | AD60: =VLOOKUP(tblRiskRegister32[[#This Row],[Asset Class]],tblInherentImpacts30[],4,FALSE) -> 0 | AE60: =VLOOKUP(tblRiskRegister32[[#This Row],[Asset Class]],tblInherentImpacts30[],5,FALSE) -> 0 | AF60: =IFERROR(MAX(tblRiskRegister32[[#This Row],[Risk Treatment Safeguard Impact to Mission]:[Risk Treatment Safeguard Impact to Obligations]])*tblRiskRegister32[[#This Row],[Risk Treatment Safeguard Expectancy Score]],"") | AG60: =IF(tblRiskRegister32[[#This Row],[Risk Score]]>=AcceptableRisk,IF(tblRiskRegister32[[#This Row],[Risk Treatment Safeguard Risk Score]]<AcceptableRisk, IF(tblRiskRegister32[[#This Row],[Risk Treatment Safeguard Risk Score]]<tblRiskRegister32[[#This Row],[Risk Score]],"Yes","No"),"No"),"Yes") -> No
B61: Software | D61: 7.5 | E61: Perform Automated Vulnerability Scans of Internal Enterprise Assets | G61: x | H61: Identify | M61: =IFERROR(VLOOKUP(tblRiskRegister32[[#This Row],[Asset Class]],tblVCDBIndex[],4,FALSE),"") -> 2 | N61: =IFERROR(VLOOKUP(10*tblRiskRegister32[[#This Row],[Safeguard Maturity Score]]+tblRiskRegister32[[#This Row],[VCDB Index]],tblHITIndexWeightTable[],4,FALSE),"") | O61: =VLOOKUP(tblRiskRegister32[[#This Row],[Asset Class]],tblInherentImpacts30[],2,FALSE) -> 0 | P61: =VLOOKUP(tblRiskRegister32[[#This Row],[Asset Class]],tblInherentImpacts30[],3,FALSE) -> 0 | Q61: =VLOOKUP(tblRiskRegister32[[#This Row],[Asset Class]],tblInherentImpacts30[],4,FALSE) -> 0 | R61: =VLOOKUP(tblRiskRegister32[[#This Row],[Asset Class]],tblInherentImpacts30[],5,FALSE) -> 0 | S61: =IFERROR(MAX(tblRiskRegister32[[#This Row],[Impact to Mission]:[Impact to Obligations]])*tblRiskRegister32[[#This Row],[Expectancy Score]],"") | T61: =tblRiskRegister32[[#This Row],[Risk Score]] | V61: 7.5 | W61: Perform Automated Vulnerability Scans of Internal Enterprise Assets | X61: Perform automated vulnerability scans of internal enterprise assets on a quarterly, or more frequent, basis. Conduct both authenticated and unauthenticated scans. | AA61: =IFERROR(VLOOKUP(10*tblRiskRegister32[[#This Row],[Risk Treatment Safeguard Maturity Score]]+tblRiskRegister32[[#This Row],[VCDB Index]],tblHITIndexWeightTable[],4,FALSE),"") | AB61: =VLOOKUP(tblRiskRegister32[[#This Row],[Asset Class]],tblInherentImpacts30[],2,FALSE) -> 0 | AC61: =VLOOKUP(tblRiskRegister32[[#This Row],[Asset Class]],tblInherentImpacts30[],3,FALSE) -> 0 | AD61: =VLOOKUP(tblRiskRegister32[[#This Row],[Asset Class]],tblInherentImpacts30[],4,FALSE) -> 0 | AE61: =VLOOKUP(tblRiskRegister32[[#This Row],[Asset Class]],tblInherentImpacts30[],5,FALSE) -> 0 | AF61: =IFERROR(MAX(tblRiskRegister32[[#This Row],[Risk Treatment Safeguard Impact to Mission]:[Risk Treatment Safeguard Impact to Obligations]])*tblRiskRegister32[[#This Row],[Risk Treatment Safeguard Expectancy Score]],"") | AG61: =IF(tblRiskRegister32[[#This Row],[Risk Score]]>=AcceptableRisk,IF(tblRiskRegister32[[#This Row],[Risk Treatment Safeguard Risk Score]]<AcceptableRisk, IF(tblRiskRegister32[[#This Row],[Risk Treatment Safeguard Risk Score]]<tblRiskRegister32[[#This Row],[Risk Score]],"Yes","No"),"No"),"Yes") -> No
B62: Software | D62: 7.6 | E62: Perform Automated Vulnerability Scans of Externally-Exposed Enterprise Assets | G62: x | H62: Identify | M62: =IFERROR(VLOOKUP(tblRiskRegister32[[#This Row],[Asset Class]],tblVCDBIndex[],4,FALSE),"") -> 2 | N62: =IFERROR(VLOOKUP(10*tblRiskRegister32[[#This Row],[Safeguard Maturity Score]]+tblRiskRegister32[[#This Row],[VCDB Index]],tblHITIndexWeightTable[],4,FALSE),"") | O62: =VLOOKUP(tblRiskRegister32[[#This Row],[Asset Class]],tblInherentImpacts30[],2,FALSE) -> 0 | P62: =VLOOKUP(tblRiskRegister32[[#This Row],[Asset Class]],tblInherentImpacts30[],3,FALSE) -> 0 | Q62: =VLOOKUP(tblRiskRegister32[[#This Row],[Asset Class]],tblInherentImpacts30[],4,FALSE) -> 0 | R62: =VLOOKUP(tblRiskRegister32[[#This Row],[Asset Class]],tblInherentImpacts30[],5,FALSE) -> 0 | S62: =IFERROR(MAX(tblRiskRegister32[[#This Row],[Impact to Mission]:[Impact to Obligations]])*tblRiskRegister32[[#This Row],[Expectancy Score]],"") | T62: =tblRiskRegister32[[#This Row],[Risk Score]] | V62: 7.6 | W62: Perform Automated Vulnerability Scans of Externally-Exposed Enterprise Assets | X62: Perform automated vulnerability scans of externally-exposed enterprise assets. Perform scans on a monthly, or more frequent, basis. | AA62: =IFERROR(VLOOKUP(10*tblRiskRegister32[[#This Row],[Risk Treatment Safeguard Maturity Score]]+tblRiskRegister32[[#This Row],[VCDB Index]],tblHITIndexWeightTable[],4,FALSE),"") | AB62: =VLOOKUP(tblRiskRegister32[[#This Row],[Asset Class]],tblInherentImpacts30[],2,FALSE) -> 0 | AC62: =VLOOKUP(tblRiskRegister32[[#This Row],[Asset Class]],tblInherentImpacts30[],3,FALSE) -> 0 | AD62: =VLOOKUP(tblRiskRegister32[[#This Row],[Asset Class]],tblInherentImpacts30[],4,FALSE) -> 0 | AE62: =VLOOKUP(tblRiskRegister32[[#This Row],[Asset Class]],tblInherentImpacts30[],5,FALSE) -> 0 | AF62: =IFERROR(MAX(tblRiskRegister32[[#This Row],[Risk Treatment Safeguard Impact to Mission]:[Risk Treatment Safeguard Impact to Obligations]])*tblRiskRegister32[[#This Row],[Risk Treatment Safeguard Expectancy Score]],"") | AG62: =IF(tblRiskRegister32[[#This Row],[Risk Score]]>=AcceptableRisk,IF(tblRiskRegister32[[#This Row],[Risk Treatment Safeguard Risk Score]]<AcceptableRisk, IF(tblRiskRegister32[[#This Row],[Risk Treatment Safeguard Risk Score]]<tblRiskRegister32[[#This Row],[Risk Score]],"Yes","No"),"No"),"Yes") -> No
B63: Software | D63: 7.7 | E63: Remediate Detected Vulnerabilities | G63: x | H63: Respond | M63: =IFERROR(VLOOKUP(tblRiskRegister32[[#This Row],[Asset Class]],tblVCDBIndex[],4,FALSE),"") -> 2 | N63: =IFERROR(VLOOKUP(10*tblRiskRegister32[[#This Row],[Safeguard Maturity Score]]+tblRiskRegister32[[#This Row],[VCDB Index]],tblHITIndexWeightTable[],4,FALSE),"") | O63: =VLOOKUP(tblRiskRegister32[[#This Row],[Asset Class]],tblInherentImpacts30[],2,FALSE) -> 0 | P63: =VLOOKUP(tblRiskRegister32[[#This Row],[Asset Class]],tblInherentImpacts30[],3,FALSE) -> 0 | Q63: =VLOOKUP(tblRiskRegister32[[#This Row],[Asset Class]],tblInherentImpacts30[],4,FALSE) -> 0 | R63: =VLOOKUP(tblRiskRegister32[[#This Row],[Asset Class]],tblInherentImpacts30[],5,FALSE) -> 0 | S63: =IFERROR(MAX(tblRiskRegister32[[#This Row],[Impact to Mission]:[Impact to Obligations]])*tblRiskRegister32[[#This Row],[Expectancy Score]],"") | T63: =tblRiskRegister32[[#This Row],[Risk Score]] | V63: 7.7 | W63: Remediate Detected Vulnerabilities | X63: Remediate detected vulnerabilities in software through processes and tooling on a monthly, or more frequent, basis, based on the remediation process. | AA63: =IFERROR(VLOOKUP(10*tblRiskRegister32[[#This Row],[Risk Treatment Safeguard Maturity Score]]+tblRiskRegister32[[#This Row],[VCDB Index]],tblHITIndexWeightTable[],4,FALSE),"") | AB63: =VLOOKUP(tblRiskRegister32[[#This Row],[Asset Class]],tblInherentImpacts30[],2,FALSE) -> 0 | AC63: =VLOOKUP(tblRiskRegister32[[#This Row],[Asset Class]],tblInherentImpacts30[],3,FALSE) -> 0 | AD63: =VLOOKUP(tblRiskRegister32[[#This Row],[Asset Class]],tblInherentImpacts30[],4,FALSE) -> 0 | AE63: =VLOOKUP(tblRiskRegister32[[#This Row],[Asset Class]],tblInherentImpacts30[],5,FALSE) -> 0 | AF63: =IFERROR(MAX(tblRiskRegister32[[#This Row],[Risk Treatment Safeguard Impact to Mission]:[Risk Treatment Safeguard Impact to Obligations]])*tblRiskRegister32[[#This Row],[Risk Treatment Safeguard Expectancy Score]],"") | AG63: =IF(tblRiskRegister32[[#This Row],[Risk Score]]>=AcceptableRisk,IF(tblRiskRegister32[[#This Row],[Risk Treatment Safeguard Risk Score]]<AcceptableRisk, IF(tblRiskRegister32[[#This Row],[Risk Treatment Safeguard Risk Score]]<tblRiskRegister32[[#This Row],[Risk Score]],"Yes","No"),"No"),"Yes") -> No
B64: Documentation | D64: 8.1 | E64: Establish and Maintain an Audit Log Management Process | F64: x | G64: x | H64: Govern | M64: =IFERROR(VLOOKUP(tblRiskRegister32[[#This Row],[Asset Class]],tblVCDBIndex[],4,FALSE),"") -> 2 | N64: =IFERROR(VLOOKUP(10*tblRiskRegister32[[#This Row],[Safeguard Maturity Score]]+tblRiskRegister32[[#This Row],[VCDB Index]],tblHITIndexWeightTable[],4,FALSE),"") | O64: =VLOOKUP(tblRiskRegister32[[#This Row],[Asset Class]],tblInherentImpacts30[],2,FALSE) -> 0 | P64: =VLOOKUP(tblRiskRegister32[[#This Row],[Asset Class]],tblInherentImpacts30[],3,FALSE) -> 0 | Q64: =VLOOKUP(tblRiskRegister32[[#This Row],[Asset Class]],tblInherentImpacts30[],4,FALSE) -> 0 | R64: =VLOOKUP(tblRiskRegister32[[#This Row],[Asset Class]],tblInherentImpacts30[],5,FALSE) -> 0 | S64: =IFERROR(MAX(tblRiskRegister32[[#This Row],[Impact to Mission]:[Impact to Obligations]])*tblRiskRegister32[[#This Row],[Expectancy Score]],"") | T64: =tblRiskRegister32[[#This Row],[Risk Score]] | V64: 8.1 | W64: Establish and Maintain an Audit Log Management Process | X64: Establish and maintain a documented audit log management process that defines the enterprise’s logging requirements. At a minimum, address the collection, review, and retention of audit logs for enterprise assets. Review and update documentation annually, or when significant enterprise changes occur that could impact this Safeguard. | AA64: =IFERROR(VLOOKUP(10*tblRiskRegister32[[#This Row],[Risk Treatment Safeguard Maturity Score]]+tblRiskRegister32[[#This Row],[VCDB Index]],tblHITIndexWeightTable[],4,FALSE),"") | AB64: =VLOOKUP(tblRiskRegister32[[#This Row],[Asset Class]],tblInherentImpacts30[],2,FALSE) -> 0 | AC64: =VLOOKUP(tblRiskRegister32[[#This Row],[Asset Class]],tblInherentImpacts30[],3,FALSE) -> 0 | AD64: =VLOOKUP(tblRiskRegister32[[#This Row],[Asset Class]],tblInherentImpacts30[],4,FALSE) -> 0 | AE64: =VLOOKUP(tblRiskRegister32[[#This Row],[Asset Class]],tblInherentImpacts30[],5,FALSE) -> 0 | AF64: =IFERROR(MAX(tblRiskRegister32[[#This Row],[Risk Treatment Safeguard Impact to Mission]:[Risk Treatment Safeguard Impact to Obligations]])*tblRiskRegister32[[#This Row],[Risk Treatment Safeguard Expectancy Score]],"") | AG64: =IF(tblRiskRegister32[[#This Row],[Risk Score]]>=AcceptableRisk,IF(tblRiskRegister32[[#This Row],[Risk Treatment Safeguard Risk Score]]<AcceptableRisk, IF(tblRiskRegister32[[#This Row],[Risk Treatment Safeguard Risk Score]]<tblRiskRegister32[[#This Row],[Risk Score]],"Yes","No"),"No"),"Yes") -> No
B65: Data | D65: 8.2 | E65: Collect Audit Logs | F65: x | G65: x | H65: Protect | M65: =IFERROR(VLOOKUP(tblRiskRegister32[[#This Row],[Asset Class]],tblVCDBIndex[],4,FALSE),"") -> 2 | N65: =IFERROR(VLOOKUP(10*tblRiskRegister32[[#This Row],[Safeguard Maturity Score]]+tblRiskRegister32[[#This Row],[VCDB Index]],tblHITIndexWeightTable[],4,FALSE),"") | O65: =VLOOKUP(tblRiskRegister32[[#This Row],[Asset Class]],tblInherentImpacts30[],2,FALSE) -> 0 | P65: =VLOOKUP(tblRiskRegister32[[#This Row],[Asset Class]],tblInherentImpacts30[],3,FALSE) -> 0 | Q65: =VLOOKUP(tblRiskRegister32[[#This Row],[Asset Class]],tblInherentImpacts30[],4,FALSE) -> 0 | R65: =VLOOKUP(tblRiskRegister32[[#This Row],[Asset Class]],tblInherentImpacts30[],5,FALSE) -> 0 | S65: =IFERROR(MAX(tblRiskRegister32[[#This Row],[Impact to Mission]:[Impact to Obligations]])*tblRiskRegister32[[#This Row],[Expectancy Score]],"") | T65: =tblRiskRegister32[[#This Row],[Risk Score]] | V65: 8.2 | W65: Collect Audit Logs | X65: Collect audit logs. Ensure that logging, per the enterprise’s audit log management process, has been enabled across enterprise assets. | AA65: =IFERROR(VLOOKUP(10*tblRiskRegister32[[#This Row],[Risk Treatment Safeguard Maturity Score]]+tblRiskRegister32[[#This Row],[VCDB Index]],tblHITIndexWeightTable[],4,FALSE),"") | AB65: =VLOOKUP(tblRiskRegister32[[#This Row],[Asset Class]],tblInherentImpacts30[],2,FALSE) -> 0 | AC65: =VLOOKUP(tblRiskRegister32[[#This Row],[Asset Class]],tblInherentImpacts30[],3,FALSE) -> 0 | AD65: =VLOOKUP(tblRiskRegister32[[#This Row],[Asset Class]],tblInherentImpacts30[],4,FALSE) -> 0 | AE65: =VLOOKUP(tblRiskRegister32[[#This Row],[Asset Class]],tblInherentImpacts30[],5,FALSE) -> 0 | AF65: =IFERROR(MAX(tblRiskRegister32[[#This Row],[Risk Treatment Safeguard Impact to Mission]:[Risk Treatment Safeguard Impact to Obligations]])*tblRiskRegister32[[#This Row],[Risk Treatment Safeguard Expectancy Score]],"") | AG65: =IF(tblRiskRegister32[[#This Row],[Risk Score]]>=AcceptableRisk,IF(tblRiskRegister32[[#This Row],[Risk Treatment Safeguard Risk Score]]<AcceptableRisk, IF(tblRiskRegister32[[#This Row],[Risk Treatment Safeguard Risk Score]]<tblRiskRegister32[[#This Row],[Risk Score]],"Yes","No"),"No"),"Yes") -> No
B66: Network | D66: 8.3 | E66: Ensure Adequate Audit Log Storage | F66: x | G66: x | H66: Protect | M66: =IFERROR(VLOOKUP(tblRiskRegister32[[#This Row],[Asset Class]],tblVCDBIndex[],4,FALSE),"") -> 1 | N66: =IFERROR(VLOOKUP(10*tblRiskRegister32[[#This Row],[Safeguard Maturity Score]]+tblRiskRegister32[[#This Row],[VCDB Index]],tblHITIndexWeightTable[],4,FALSE),"") | O66: =VLOOKUP(tblRiskRegister32[[#This Row],[Asset Class]],tblInherentImpacts30[],2,FALSE) -> 0 | P66: =VLOOKUP(tblRiskRegister32[[#This Row],[Asset Class]],tblInherentImpacts30[],3,FALSE) -> 0 | Q66: =VLOOKUP(tblRiskRegister32[[#This Row],[Asset Class]],tblInherentImpacts30[],4,FALSE) -> 0 | R66: =VLOOKUP(tblRiskRegister32[[#This Row],[Asset Class]],tblInherentImpacts30[],5,FALSE) -> 0 | S66: =IFERROR(MAX(tblRiskRegister32[[#This Row],[Impact to Mission]:[Impact to Obligations]])*tblRiskRegister32[[#This Row],[Expectancy Score]],"") | T66: =tblRiskRegister32[[#This Row],[Risk Score]] | V66: 8.3 | W66: Ensure Adequate Audit Log Storage | X66: Ensure that logging destinations maintain adequate storage to comply with the enterprise’s audit log management process. | AA66: =IFERROR(VLOOKUP(10*tblRiskRegister32[[#This Row],[Risk Treatment Safeguard Maturity Score]]+tblRiskRegister32[[#This Row],[VCDB Index]],tblHITIndexWeightTable[],4,FALSE),"") | AB66: =VLOOKUP(tblRiskRegister32[[#This Row],[Asset Class]],tblInherentImpacts30[],2,FALSE) -> 0 | AC66: =VLOOKUP(tblRiskRegister32[[#This Row],[Asset Class]],tblInherentImpacts30[],3,FALSE) -> 0 | AD66: =VLOOKUP(tblRiskRegister32[[#This Row],[Asset Class]],tblInherentImpacts30[],4,FALSE) -> 0 | AE66: =VLOOKUP(tblRiskRegister32[[#This Row],[Asset Class]],tblInherentImpacts30[],5,FALSE) -> 0 | AF66: =IFERROR(MAX(tblRiskRegister32[[#This Row],[Risk Treatment Safeguard Impact to Mission]:[Risk Treatment Safeguard Impact to Obligations]])*tblRiskRegister32[[#This Row],[Risk Treatment Safeguard Expectancy Score]],"") | AG66: =IF(tblRiskRegister32[[#This Row],[Risk Score]]>=AcceptableRisk,IF(tblRiskRegister32[[#This Row],[Risk Treatment Safeguard Risk Score]]<AcceptableRisk, IF(tblRiskRegister32[[#This Row],[Risk Treatment Safeguard Risk Score]]<tblRiskRegister32[[#This Row],[Risk Score]],"Yes","No"),"No"),"Yes") -> No
B67: Data | D67: 8.4 | E67: Standardize Time Synchronization | G67: x | H67: Detect | M67: =IFERROR(VLOOKUP(tblRiskRegister32[[#This Row],[Asset Class]],tblVCDBIndex[],4,FALSE),"") -> 2 | N67: =IFERROR(VLOOKUP(10*tblRiskRegister32[[#This Row],[Safeguard Maturity Score]]+tblRiskRegister32[[#This Row],[VCDB Index]],tblHITIndexWeightTable[],4,FALSE),"") | O67: =VLOOKUP(tblRiskRegister32[[#This Row],[Asset Class]],tblInherentImpacts30[],2,FALSE) -> 0 | P67: =VLOOKUP(tblRiskRegister32[[#This Row],[Asset Class]],tblInherentImpacts30[],3,FALSE) -> 0 | Q67: =VLOOKUP(tblRiskRegister32[[#This Row],[Asset Class]],tblInherentImpacts30[],4,FALSE) -> 0 | R67: =VLOOKUP(tblRiskRegister32[[#This Row],[Asset Class]],tblInherentImpacts30[],5,FALSE) -> 0 | S67: =IFERROR(MAX(tblRiskRegister32[[#This Row],[Impact to Mission]:[Impact to Obligations]])*tblRiskRegister32[[#This Row],[Expectancy Score]],"") | T67: =tblRiskRegister32[[#This Row],[Risk Score]] | V67: 8.4 | W67: Standardize Time Synchronization | X67: Standardize time synchronization. Configure at least two synchronized time sources across enterprise assets, where supported. | AA67: =IFERROR(VLOOKUP(10*tblRiskRegister32[[#This Row],[Risk Treatment Safeguard Maturity Score]]+tblRiskRegister32[[#This Row],[VCDB Index]],tblHITIndexWeightTable[],4,FALSE),"") | AB67: =VLOOKUP(tblRiskRegister32[[#This Row],[Asset Class]],tblInherentImpacts30[],2,FALSE) -> 0 | AC67: =VLOOKUP(tblRiskRegister32[[#This Row],[Asset Class]],tblInherentImpacts30[],3,FALSE) -> 0 | AD67: =VLOOKUP(tblRiskRegister32[[#This Row],[Asset Class]],tblInherentImpacts30[],4,FALSE) -> 0 | AE67: =VLOOKUP(tblRiskRegister32[[#This Row],[Asset Class]],tblInherentImpacts30[],5,FALSE) -> 0 | AF67: =IFERROR(MAX(tblRiskRegister32[[#This Row],[Risk Treatment Safeguard Impact to Mission]:[Risk Treatment Safeguard Impact to Obligations]])*tblRiskRegister32[[#This Row],[Risk Treatment Safeguard Expectancy Score]],"") | AG67: =IF(tblRiskRegister32[[#This Row],[Risk Score]]>=AcceptableRisk,IF(tblRiskRegister32[[#This Row],[Risk Treatment Safeguard Risk Score]]<AcceptableRisk, IF(tblRiskRegister32[[#This Row],[Risk Treatment Safeguard Risk Score]]<tblRiskRegister32[[#This Row],[Risk Score]],"Yes","No"),"No"),"Yes") -> No
B68: Data | D68: 8.5 | E68: Collect Detailed Audit Logs | G68: x | H68: Detect | M68: =IFERROR(VLOOKUP(tblRiskRegister32[[#This Row],[Asset Class]],tblVCDBIndex[],4,FALSE),"") -> 2 | N68: =IFERROR(VLOOKUP(10*tblRiskRegister32[[#This Row],[Safeguard Maturity Score]]+tblRiskRegister32[[#This Row],[VCDB Index]],tblHITIndexWeightTable[],4,FALSE),"") | O68: =VLOOKUP(tblRiskRegister32[[#This Row],[Asset Class]],tblInherentImpacts30[],2,FALSE) -> 0 | P68: =VLOOKUP(tblRiskRegister32[[#This Row],[Asset Class]],tblInherentImpacts30[],3,FALSE) -> 0 | Q68: =VLOOKUP(tblRiskRegister32[[#This Row],[Asset Class]],tblInherentImpacts30[],4,FALSE) -> 0 | R68: =VLOOKUP(tblRiskRegister32[[#This Row],[Asset Class]],tblInherentImpacts30[],5,FALSE) -> 0 | S68: =IFERROR(MAX(tblRiskRegister32[[#This Row],[Impact to Mission]:[Impact to Obligations]])*tblRiskRegister32[[#This Row],[Expectancy Score]],"") | T68: =tblRiskRegister32[[#This Row],[Risk Score]] | V68: 8.5 | W68: Collect Detailed Audit Logs | X68: Configure detailed audit logging for enterprise assets containing sensitive data. Include event source, date, username, timestamp, source addresses, destination addresses, and other useful elements that could assist in a forensic investigation. | AA68: =IFERROR(VLOOKUP(10*tblRiskRegister32[[#This Row],[Risk Treatment Safeguard Maturity Score]]+tblRiskRegister32[[#This Row],[VCDB Index]],tblHITIndexWeightTable[],4,FALSE),"") | AB68: =VLOOKUP(tblRiskRegister32[[#This Row],[Asset Class]],tblInherentImpacts30[],2,FALSE) -> 0 | AC68: =VLOOKUP(tblRiskRegister32[[#This Row],[Asset Class]],tblInherentImpacts30[],3,FALSE) -> 0 | AD68: =VLOOKUP(tblRiskRegister32[[#This Row],[Asset Class]],tblInherentImpacts30[],4,FALSE) -> 0 | AE68: =VLOOKUP(tblRiskRegister32[[#This Row],[Asset Class]],tblInherentImpacts30[],5,FALSE) -> 0 | AF68: =IFERROR(MAX(tblRiskRegister32[[#This Row],[Risk Treatment Safeguard Impact to Mission]:[Risk Treatment Safeguard Impact to Obligations]])*tblRiskRegister32[[#This Row],[Risk Treatment Safeguard Expectancy Score]],"") | AG68: =IF(tblRiskRegister32[[#This Row],[Risk Score]]>=AcceptableRisk,IF(tblRiskRegister32[[#This Row],[Risk Treatment Safeguard Risk Score]]<AcceptableRisk, IF(tblRiskRegister32[[#This Row],[Risk Treatment Safeguard Risk Score]]<tblRiskRegister32[[#This Row],[Risk Score]],"Yes","No"),"No"),"Yes") -> No
B69: Data | D69: 8.6 | E69: Collect DNS Query Audit Logs | G69: x | H69: Detect | M69: =IFERROR(VLOOKUP(tblRiskRegister32[[#This Row],[Asset Class]],tblVCDBIndex[],4,FALSE),"") -> 2 | N69: =IFERROR(VLOOKUP(10*tblRiskRegister32[[#This Row],[Safeguard Maturity Score]]+tblRiskRegister32[[#This Row],[VCDB Index]],tblHITIndexWeightTable[],4,FALSE),"") | O69: =VLOOKUP(tblRiskRegister32[[#This Row],[Asset Class]],tblInherentImpacts30[],2,FALSE) -> 0 | P69: =VLOOKUP(tblRiskRegister32[[#This Row],[Asset Class]],tblInherentImpacts30[],3,FALSE) -> 0 | Q69: =VLOOKUP(tblRiskRegister32[[#This Row],[Asset Class]],tblInherentImpacts30[],4,FALSE) -> 0 | R69: =VLOOKUP(tblRiskRegister32[[#This Row],[Asset Class]],tblInherentImpacts30[],5,FALSE) -> 0 | S69: =IFERROR(MAX(tblRiskRegister32[[#This Row],[Impact to Mission]:[Impact to Obligations]])*tblRiskRegister32[[#This Row],[Expectancy Score]],"") | T69: =tblRiskRegister32[[#This Row],[Risk Score]] | V69: 8.6 | W69: Collect DNS Query Audit Logs | X69: Collect DNS query audit logs on enterprise assets, where appropriate and supported. | AA69: =IFERROR(VLOOKUP(10*tblRiskRegister32[[#This Row],[Risk Treatment Safeguard Maturity Score]]+tblRiskRegister32[[#This Row],[VCDB Index]],tblHITIndexWeightTable[],4,FALSE),"") | AB69: =VLOOKUP(tblRiskRegister32[[#This Row],[Asset Class]],tblInherentImpacts30[],2,FALSE) -> 0 | AC69: =VLOOKUP(tblRiskRegister32[[#This Row],[Asset Class]],tblInherentImpacts30[],3,FALSE) -> 0 | AD69: =VLOOKUP(tblRiskRegister32[[#This Row],[Asset Class]],tblInherentImpacts30[],4,FALSE) -> 0 | AE69: =VLOOKUP(tblRiskRegister32[[#This Row],[Asset Class]],tblInherentImpacts30[],5,FALSE) -> 0 | AF69: =IFERROR(MAX(tblRiskRegister32[[#This Row],[Risk Treatment Safeguard Impact to Mission]:[Risk Treatment Safeguard Impact to Obligations]])*tblRiskRegister32[[#This Row],[Risk Treatment Safeguard Expectancy Score]],"") | AG69: =IF(tblRiskRegister32[[#This Row],[Risk Score]]>=AcceptableRisk,IF(tblRiskRegister32[[#This Row],[Risk Treatment Safeguard Risk Score]]<AcceptableRisk, IF(tblRiskRegister32[[#This Row],[Risk Treatment Safeguard Risk Score]]<tblRiskRegister32[[#This Row],[Risk Score]],"Yes","No"),"No"),"Yes") -> No
B70: Data | D70: 8.7 | E70: Collect URL Request Audit Logs | G70: x | H70: Detect | M70: =IFERROR(VLOOKUP(tblRiskRegister32[[#This Row],[Asset Class]],tblVCDBIndex[],4,FALSE),"") -> 2 | N70: =IFERROR(VLOOKUP(10*tblRiskRegister32[[#This Row],[Safeguard Maturity Score]]+tblRiskRegister32[[#This Row],[VCDB Index]],tblHITIndexWeightTable[],4,FALSE),"") | O70: =VLOOKUP(tblRiskRegister32[[#This Row],[Asset Class]],tblInherentImpacts30[],2,FALSE) -> 0 | P70: =VLOOKUP(tblRiskRegister32[[#This Row],[Asset Class]],tblInherentImpacts30[],3,FALSE) -> 0 | Q70: =VLOOKUP(tblRiskRegister32[[#This Row],[Asset Class]],tblInherentImpacts30[],4,FALSE) -> 0 | R70: =VLOOKUP(tblRiskRegister32[[#This Row],[Asset Class]],tblInherentImpacts30[],5,FALSE) -> 0 | S70: =IFERROR(MAX(tblRiskRegister32[[#This Row],[Impact to Mission]:[Impact to Obligations]])*tblRiskRegister32[[#This Row],[Expectancy Score]],"") | T70: =tblRiskRegister32[[#This Row],[Risk Score]] | V70: 8.7 | W70: Collect URL Request Audit Logs | X70: Collect URL request audit logs on enterprise assets, where appropriate and supported. | AA70: =IFERROR(VLOOKUP(10*tblRiskRegister32[[#This Row],[Risk Treatment Safeguard Maturity Score]]+tblRiskRegister32[[#This Row],[VCDB Index]],tblHITIndexWeightTable[],4,FALSE),"") | AB70: =VLOOKUP(tblRiskRegister32[[#This Row],[Asset Class]],tblInherentImpacts30[],2,FALSE) -> 0 | AC70: =VLOOKUP(tblRiskRegister32[[#This Row],[Asset Class]],tblInherentImpacts30[],3,FALSE) -> 0 | AD70: =VLOOKUP(tblRiskRegister32[[#This Row],[Asset Class]],tblInherentImpacts30[],4,FALSE) -> 0 | AE70: =VLOOKUP(tblRiskRegister32[[#This Row],[Asset Class]],tblInherentImpacts30[],5,FALSE) -> 0 | AF70: =IFERROR(MAX(tblRiskRegister32[[#This Row],[Risk Treatment Safeguard Impact to Mission]:[Risk Treatment Safeguard Impact to Obligations]])*tblRiskRegister32[[#This Row],[Risk Treatment Safeguard Expectancy Score]],"") | AG70: =IF(tblRiskRegister32[[#This Row],[Risk Score]]>=AcceptableRisk,IF(tblRiskRegister32[[#This Row],[Risk Treatment Safeguard Risk Score]]<AcceptableRisk, IF(tblRiskRegister32[[#This Row],[Risk Treatment Safeguard Risk Score]]<tblRiskRegister32[[#This Row],[Risk Score]],"Yes","No"),"No"),"Yes") -> No
B71: Data | D71: 8.8 | E71: Collect Command-Line Audit Logs | G71: x | H71: Detect | M71: =IFERROR(VLOOKUP(tblRiskRegister32[[#This Row],[Asset Class]],tblVCDBIndex[],4,FALSE),"") -> 2 | N71: =IFERROR(VLOOKUP(10*tblRiskRegister32[[#This Row],[Safeguard Maturity Score]]+tblRiskRegister32[[#This Row],[VCDB Index]],tblHITIndexWeightTable[],4,FALSE),"") | O71: =VLOOKUP(tblRiskRegister32[[#This Row],[Asset Class]],tblInherentImpacts30[],2,FALSE) -> 0 | P71: =VLOOKUP(tblRiskRegister32[[#This Row],[Asset Class]],tblInherentImpacts30[],3,FALSE) -> 0 | Q71: =VLOOKUP(tblRiskRegister32[[#This Row],[Asset Class]],tblInherentImpacts30[],4,FALSE) -> 0 | R71: =VLOOKUP(tblRiskRegister32[[#This Row],[Asset Class]],tblInherentImpacts30[],5,FALSE) -> 0 | S71: =IFERROR(MAX(tblRiskRegister32[[#This Row],[Impact to Mission]:[Impact to Obligations]])*tblRiskRegister32[[#This Row],[Expectancy Score]],"") | T71: =tblRiskRegister32[[#This Row],[Risk Score]] | V71: 8.8 | W71: Collect Command-Line Audit Logs | X71: Collect command-line audit logs. Example implementations include collecting audit logs from PowerShell®, BASH™, and remote administrative terminals. | AA71: =IFERROR(VLOOKUP(10*tblRiskRegister32[[#This Row],[Risk Treatment Safeguard Maturity Score]]+tblRiskRegister32[[#This Row],[VCDB Index]],tblHITIndexWeightTable[],4,FALSE),"") | AB71: =VLOOKUP(tblRiskRegister32[[#This Row],[Asset Class]],tblInherentImpacts30[],2,FALSE) -> 0 | AC71: =VLOOKUP(tblRiskRegister32[[#This Row],[Asset Class]],tblInherentImpacts30[],3,FALSE) -> 0 | AD71: =VLOOKUP(tblRiskRegister32[[#This Row],[Asset Class]],tblInherentImpacts30[],4,FALSE) -> 0 | AE71: =VLOOKUP(tblRiskRegister32[[#This Row],[Asset Class]],tblInherentImpacts30[],5,FALSE) -> 0 | AF71: =IFERROR(MAX(tblRiskRegister32[[#This Row],[Risk Treatment Safeguard Impact to Mission]:[Risk Treatment Safeguard Impact to Obligations]])*tblRiskRegister32[[#This Row],[Risk Treatment Safeguard Expectancy Score]],"") | AG71: =IF(tblRiskRegister32[[#This Row],[Risk Score]]>=AcceptableRisk,IF(tblRiskRegister32[[#This Row],[Risk Treatment Safeguard Risk Score]]<AcceptableRisk, IF(tblRiskRegister32[[#This Row],[Risk Treatment Safeguard Risk Score]]<tblRiskRegister32[[#This Row],[Risk Score]],"Yes","No"),"No"),"Yes") -> No
B72: Data | D72: 8.9 | E72: Centralize Audit Logs | G72: x | H72: Protect | M72: =IFERROR(VLOOKUP(tblRiskRegister32[[#This Row],[Asset Class]],tblVCDBIndex[],4,FALSE),"") -> 2 | N72: =IFERROR(VLOOKUP(10*tblRiskRegister32[[#This Row],[Safeguard Maturity Score]]+tblRiskRegister32[[#This Row],[VCDB Index]],tblHITIndexWeightTable[],4,FALSE),"") | O72: =VLOOKUP(tblRiskRegister32[[#This Row],[Asset Class]],tblInherentImpacts30[],2,FALSE) -> 0 | P72: =VLOOKUP(tblRiskRegister32[[#This Row],[Asset Class]],tblInherentImpacts30[],3,FALSE) -> 0 | Q72: =VLOOKUP(tblRiskRegister32[[#This Row],[Asset Class]],tblInherentImpacts30[],4,FALSE) -> 0 | R72: =VLOOKUP(tblRiskRegister32[[#This Row],[Asset Class]],tblInherentImpacts30[],5,FALSE) -> 0 | S72: =IFERROR(MAX(tblRiskRegister32[[#This Row],[Impact to Mission]:[Impact to Obligations]])*tblRiskRegister32[[#This Row],[Expectancy Score]],"") | T72: =tblRiskRegister32[[#This Row],[Risk Score]] | V72: 8.9 | W72: Centralize Audit Logs | X72: Centralize, to the extent possible, audit log collection and retention across enterprise assets in accordance with the documented audit log management process. Example implementations primarily include leveraging a SIEM tool to centralize multiple log sources. | AA72: =IFERROR(VLOOKUP(10*tblRiskRegister32[[#This Row],[Risk Treatment Safeguard Maturity Score]]+tblRiskRegister32[[#This Row],[VCDB Index]],tblHITIndexWeightTable[],4,FALSE),"") | AB72: =VLOOKUP(tblRiskRegister32[[#This Row],[Asset Class]],tblInherentImpacts30[],2,FALSE) -> 0 | AC72: =VLOOKUP(tblRiskRegister32[[#This Row],[Asset Class]],tblInherentImpacts30[],3,FALSE) -> 0 | AD72: =VLOOKUP(tblRiskRegister32[[#This Row],[Asset Class]],tblInherentImpacts30[],4,FALSE) -> 0 | AE72: =VLOOKUP(tblRiskRegister32[[#This Row],[Asset Class]],tblInherentImpacts30[],5,FALSE) -> 0 | AF72: =IFERROR(MAX(tblRiskRegister32[[#This Row],[Risk Treatment Safeguard Impact to Mission]:[Risk Treatment Safeguard Impact to Obligations]])*tblRiskRegister32[[#This Row],[Risk Treatment Safeguard Expectancy Score]],"") | AG72: =IF(tblRiskRegister32[[#This Row],[Risk Score]]>=AcceptableRisk,IF(tblRiskRegister32[[#This Row],[Risk Treatment Safeguard Risk Score]]<AcceptableRisk, IF(tblRiskRegister32[[#This Row],[Risk Treatment Safeguard Risk Score]]<tblRiskRegister32[[#This Row],[Risk Score]],"Yes","No"),"No"),"Yes") -> No
B73: Data | D73: 8.1 | E73: Retain Audit Logs | G73: x | H73: Detect | M73: =IFERROR(VLOOKUP(tblRiskRegister32[[#This Row],[Asset Class]],tblVCDBIndex[],4,FALSE),"") -> 2 | N73: =IFERROR(VLOOKUP(10*tblRiskRegister32[[#This Row],[Safeguard Maturity Score]]+tblRiskRegister32[[#This Row],[VCDB Index]],tblHITIndexWeightTable[],4,FALSE),"") | O73: =VLOOKUP(tblRiskRegister32[[#This Row],[Asset Class]],tblInherentImpacts30[],2,FALSE) -> 0 | P73: =VLOOKUP(tblRiskRegister32[[#This Row],[Asset Class]],tblInherentImpacts30[],3,FALSE) -> 0 | Q73: =VLOOKUP(tblRiskRegister32[[#This Row],[Asset Class]],tblInherentImpacts30[],4,FALSE) -> 0 | R73: =VLOOKUP(tblRiskRegister32[[#This Row],[Asset Class]],tblInherentImpacts30[],5,FALSE) -> 0 | S73: =IFERROR(MAX(tblRiskRegister32[[#This Row],[Impact to Mission]:[Impact to Obligations]])*tblRiskRegister32[[#This Row],[Expectancy Score]],"") | T73: =tblRiskRegister32[[#This Row],[Risk Score]] | V73: 8.1 | W73: Retain Audit Logs | X73: Retain audit logs across enterprise assets for a minimum of 90 days. | AA73: =IFERROR(VLOOKUP(10*tblRiskRegister32[[#This Row],[Risk Treatment Safeguard Maturity Score]]+tblRiskRegister32[[#This Row],[VCDB Index]],tblHITIndexWeightTable[],4,FALSE),"") | AB73: =VLOOKUP(tblRiskRegister32[[#This Row],[Asset Class]],tblInherentImpacts30[],2,FALSE) -> 0 | AC73: =VLOOKUP(tblRiskRegister32[[#This Row],[Asset Class]],tblInherentImpacts30[],3,FALSE) -> 0 | AD73: =VLOOKUP(tblRiskRegister32[[#This Row],[Asset Class]],tblInherentImpacts30[],4,FALSE) -> 0 | AE73: =VLOOKUP(tblRiskRegister32[[#This Row],[Asset Class]],tblInherentImpacts30[],5,FALSE) -> 0 | AF73: =IFERROR(MAX(tblRiskRegister32[[#This Row],[Risk Treatment Safeguard Impact to Mission]:[Risk Treatment Safeguard Impact to Obligations]])*tblRiskRegister32[[#This Row],[Risk Treatment Safeguard Expectancy Score]],"") | AG73: =IF(tblRiskRegister32[[#This Row],[Risk Score]]>=AcceptableRisk,IF(tblRiskRegister32[[#This Row],[Risk Treatment Safeguard Risk Score]]<AcceptableRisk, IF(tblRiskRegister32[[#This Row],[Risk Treatment Safeguard Risk Score]]<tblRiskRegister32[[#This Row],[Risk Score]],"Yes","No"),"No"),"Yes") -> No
B74: Data | D74: 8.11 | E74: Conduct Audit Log Reviews | G74: x | H74: Detect | M74: =IFERROR(VLOOKUP(tblRiskRegister32[[#This Row],[Asset Class]],tblVCDBIndex[],4,FALSE),"") -> 2 | N74: =IFERROR(VLOOKUP(10*tblRiskRegister32[[#This Row],[Safeguard Maturity Score]]+tblRiskRegister32[[#This Row],[VCDB Index]],tblHITIndexWeightTable[],4,FALSE),"") | O74: =VLOOKUP(tblRiskRegister32[[#This Row],[Asset Class]],tblInherentImpacts30[],2,FALSE) -> 0 | P74: =VLOOKUP(tblRiskRegister32[[#This Row],[Asset Class]],tblInherentImpacts30[],3,FALSE) -> 0 | Q74: =VLOOKUP(tblRiskRegister32[[#This Row],[Asset Class]],tblInherentImpacts30[],4,FALSE) -> 0 | R74: =VLOOKUP(tblRiskRegister32[[#This Row],[Asset Class]],tblInherentImpacts30[],5,FALSE) -> 0 | S74: =IFERROR(MAX(tblRiskRegister32[[#This Row],[Impact to Mission]:[Impact to Obligations]])*tblRiskRegister32[[#This Row],[Expectancy Score]],"") | T74: =tblRiskRegister32[[#This Row],[Risk Score]] | V74: 8.11 | W74: Conduct Audit Log Reviews | X74: Conduct reviews of audit logs to detect anomalies or abnormal events that could indicate a potential threat. Conduct reviews on a weekly, or more frequent, basis. | AA74: =IFERROR(VLOOKUP(10*tblRiskRegister32[[#This Row],[Risk Treatment Safeguard Maturity Score]]+tblRiskRegister32[[#This Row],[VCDB Index]],tblHITIndexWeightTable[],4,FALSE),"") | AB74: =VLOOKUP(tblRiskRegister32[[#This Row],[Asset Class]],tblInherentImpacts30[],2,FALSE) -> 0 | AC74: =VLOOKUP(tblRiskRegister32[[#This Row],[Asset Class]],tblInherentImpacts30[],3,FALSE) -> 0 | AD74: =VLOOKUP(tblRiskRegister32[[#This Row],[Asset Class]],tblInherentImpacts30[],4,FALSE) -> 0 | AE74: =VLOOKUP(tblRiskRegister32[[#This Row],[Asset Class]],tblInherentImpacts30[],5,FALSE) -> 0 | AF74: =IFERROR(MAX(tblRiskRegister32[[#This Row],[Risk Treatment Safeguard Impact to Mission]:[Risk Treatment Safeguard Impact to Obligations]])*tblRiskRegister32[[#This Row],[Risk Treatment Safeguard Expectancy Score]],"") | AG74: =IF(tblRiskRegister32[[#This Row],[Risk Score]]>=AcceptableRisk,IF(tblRiskRegister32[[#This Row],[Risk Treatment Safeguard Risk Score]]<AcceptableRisk, IF(tblRiskRegister32[[#This Row],[Risk Treatment Safeguard Risk Score]]<tblRiskRegister32[[#This Row],[Risk Score]],"Yes","No"),"No"),"Yes") -> No
B75: Software | D75: 9.1 | E75: Ensure Use of Only Fully Supported Browsers and Email Clients | F75: x | G75: x | H75: Protect | M75: =IFERROR(VLOOKUP(tblRiskRegister32[[#This Row],[Asset Class]],tblVCDBIndex[],4,FALSE),"") -> 2 | N75: =IFERROR(VLOOKUP(10*tblRiskRegister32[[#This Row],[Safeguard Maturity Score]]+tblRiskRegister32[[#This Row],[VCDB Index]],tblHITIndexWeightTable[],4,FALSE),"") | O75: =VLOOKUP(tblRiskRegister32[[#This Row],[Asset Class]],tblInherentImpacts30[],2,FALSE) -> 0 | P75: =VLOOKUP(tblRiskRegister32[[#This Row],[Asset Class]],tblInherentImpacts30[],3,FALSE) -> 0 | Q75: =VLOOKUP(tblRiskRegister32[[#This Row],[Asset Class]],tblInherentImpacts30[],4,FALSE) -> 0 | R75: =VLOOKUP(tblRiskRegister32[[#This Row],[Asset Class]],tblInherentImpacts30[],5,FALSE) -> 0 | S75: =IFERROR(MAX(tblRiskRegister32[[#This Row],[Impact to Mission]:[Impact to Obligations]])*tblRiskRegister32[[#This Row],[Expectancy Score]],"") | T75: =tblRiskRegister32[[#This Row],[Risk Score]] | V75: 9.1 | W75: Ensure Use of Only Fully Supported Browsers and Email Clients | X75: Ensure only fully supported browsers and email clients are allowed to execute in the enterprise, only using the latest version of browsers and email clients provided through the vendor. | AA75: =IFERROR(VLOOKUP(10*tblRiskRegister32[[#This Row],[Risk Treatment Safeguard Maturity Score]]+tblRiskRegister32[[#This Row],[VCDB Index]],tblHITIndexWeightTable[],4,FALSE),"") | AB75: =VLOOKUP(tblRiskRegister32[[#This Row],[Asset Class]],tblInherentImpacts30[],2,FALSE) -> 0 | AC75: =VLOOKUP(tblRiskRegister32[[#This Row],[Asset Class]],tblInherentImpacts30[],3,FALSE) -> 0 | AD75: =VLOOKUP(tblRiskRegister32[[#This Row],[Asset Class]],tblInherentImpacts30[],4,FALSE) -> 0 | AE75: =VLOOKUP(tblRiskRegister32[[#This Row],[Asset Class]],tblInherentImpacts30[],5,FALSE) -> 0 | AF75: =IFERROR(MAX(tblRiskRegister32[[#This Row],[Risk Treatment Safeguard Impact to Mission]:[Risk Treatment Safeguard Impact to Obligations]])*tblRiskRegister32[[#This Row],[Risk Treatment Safeguard Expectancy Score]],"") | AG75: =IF(tblRiskRegister32[[#This Row],[Risk Score]]>=AcceptableRisk,IF(tblRiskRegister32[[#This Row],[Risk Treatment Safeguard Risk Score]]<AcceptableRisk, IF(tblRiskRegister32[[#This Row],[Risk Treatment Safeguard Risk Score]]<tblRiskRegister32[[#This Row],[Risk Score]],"Yes","No"),"No"),"Yes") -> No
B76: Devices | D76: 9.2 | E76: Use DNS Filtering Services | F76: x | G76: x | H76: Protect | M76: =IFERROR(VLOOKUP(tblRiskRegister32[[#This Row],[Asset Class]],tblVCDBIndex[],4,FALSE),"") -> 4 | N76: =IFERROR(VLOOKUP(10*tblRiskRegister32[[#This Row],[Safeguard Maturity Score]]+tblRiskRegister32[[#This Row],[VCDB Index]],tblHITIndexWeightTable[],4,FALSE),"") | O76: =VLOOKUP(tblRiskRegister32[[#This Row],[Asset Class]],tblInherentImpacts30[],2,FALSE) -> 0 | P76: =VLOOKUP(tblRiskRegister32[[#This Row],[Asset Class]],tblInherentImpacts30[],3,FALSE) -> 0 | Q76: =VLOOKUP(tblRiskRegister32[[#This Row],[Asset Class]],tblInherentImpacts30[],4,FALSE) -> 0 | R76: =VLOOKUP(tblRiskRegister32[[#This Row],[Asset Class]],tblInherentImpacts30[],5,FALSE) -> 0 | S76: =IFERROR(MAX(tblRiskRegister32[[#This Row],[Impact to Mission]:[Impact to Obligations]])*tblRiskRegister32[[#This Row],[Expectancy Score]],"") | T76: =tblRiskRegister32[[#This Row],[Risk Score]] | V76: 9.2 | W76: Use DNS Filtering Services | X76: Use DNS filtering services on all end-user devices, including remote and on-premises assets, to block access to known malicious domains. | AA76: =IFERROR(VLOOKUP(10*tblRiskRegister32[[#This Row],[Risk Treatment Safeguard Maturity Score]]+tblRiskRegister32[[#This Row],[VCDB Index]],tblHITIndexWeightTable[],4,FALSE),"") | AB76: =VLOOKUP(tblRiskRegister32[[#This Row],[Asset Class]],tblInherentImpacts30[],2,FALSE) -> 0 | AC76: =VLOOKUP(tblRiskRegister32[[#This Row],[Asset Class]],tblInherentImpacts30[],3,FALSE) -> 0 | AD76: =VLOOKUP(tblRiskRegister32[[#This Row],[Asset Class]],tblInherentImpacts30[],4,FALSE) -> 0 | AE76: =VLOOKUP(tblRiskRegister32[[#This Row],[Asset Class]],tblInherentImpacts30[],5,FALSE) -> 0 | AF76: =IFERROR(MAX(tblRiskRegister32[[#This Row],[Risk Treatment Safeguard Impact to Mission]:[Risk Treatment Safeguard Impact to Obligations]])*tblRiskRegister32[[#This Row],[Risk Treatment Safeguard Expectancy Score]],"") | AG76: =IF(tblRiskRegister32[[#This Row],[Risk Score]]>=AcceptableRisk,IF(tblRiskRegister32[[#This Row],[Risk Treatment Safeguard Risk Score]]<AcceptableRisk, IF(tblRiskRegister32[[#This Row],[Risk Treatment Safeguard Risk Score]]<tblRiskRegister32[[#This Row],[Risk Score]],"Yes","No"),"No"),"Yes") -> No
B77: Network | D77: 9.3 | E77: Maintain and Enforce Network-Based URL Filters | G77: x | H77: Protect | M77: =IFERROR(VLOOKUP(tblRiskRegister32[[#This Row],[Asset Class]],tblVCDBIndex[],4,FALSE),"") -> 1 | N77: =IFERROR(VLOOKUP(10*tblRiskRegister32[[#This Row],[Safeguard Maturity Score]]+tblRiskRegister32[[#This Row],[VCDB Index]],tblHITIndexWeightTable[],4,FALSE),"") | O77: =VLOOKUP(tblRiskRegister32[[#This Row],[Asset Class]],tblInherentImpacts30[],2,FALSE) -> 0 | P77: =VLOOKUP(tblRiskRegister32[[#This Row],[Asset Class]],tblInherentImpacts30[],3,FALSE) -> 0 | Q77: =VLOOKUP(tblRiskRegister32[[#This Row],[Asset Class]],tblInherentImpacts30[],4,FALSE) -> 0 | R77: =VLOOKUP(tblRiskRegister32[[#This Row],[Asset Class]],tblInherentImpacts30[],5,FALSE) -> 0 | S77: =IFERROR(MAX(tblRiskRegister32[[#This Row],[Impact to Mission]:[Impact to Obligations]])*tblRiskRegister32[[#This Row],[Expectancy Score]],"") | T77: =tblRiskRegister32[[#This Row],[Risk Score]] | V77: 9.3 | W77: Maintain and Enforce Network-Based URL Filters | X77: Enforce and update network-based URL filters to limit an enterprise asset from connecting to potentially malicious or unapproved websites. Example implementations include category-based filtering, reputation-based filtering, or through the use of block lists. Enforce filters for all enterprise assets. | AA77: =IFERROR(VLOOKUP(10*tblRiskRegister32[[#This Row],[Risk Treatment Safeguard Maturity Score]]+tblRiskRegister32[[#This Row],[VCDB Index]],tblHITIndexWeightTable[],4,FALSE),"") | AB77: =VLOOKUP(tblRiskRegister32[[#This Row],[Asset Class]],tblInherentImpacts30[],2,FALSE) -> 0 | AC77: =VLOOKUP(tblRiskRegister32[[#This Row],[Asset Class]],tblInherentImpacts30[],3,FALSE) -> 0 | AD77: =VLOOKUP(tblRiskRegister32[[#This Row],[Asset Class]],tblInherentImpacts30[],4,FALSE) -> 0 | AE77: =VLOOKUP(tblRiskRegister32[[#This Row],[Asset Class]],tblInherentImpacts30[],5,FALSE) -> 0 | AF77: =IFERROR(MAX(tblRiskRegister32[[#This Row],[Risk Treatment Safeguard Impact to Mission]:[Risk Treatment Safeguard Impact to Obligations]])*tblRiskRegister32[[#This Row],[Risk Treatment Safeguard Expectancy Score]],"") | AG77: =IF(tblRiskRegister32[[#This Row],[Risk Score]]>=AcceptableRisk,IF(tblRiskRegister32[[#This Row],[Risk Treatment Safeguard Risk Score]]<AcceptableRisk, IF(tblRiskRegister32[[#This Row],[Risk Treatment Safeguard Risk Score]]<tblRiskRegister32[[#This Row],[Risk Score]],"Yes","No"),"No"),"Yes") -> No
B78: Software | D78: 9.4 | E78: Restrict Unnecessary or Unauthorized Browser and Email Client Extensions | G78: x | H78: Protect | M78: =IFERROR(VLOOKUP(tblRiskRegister32[[#This Row],[Asset Class]],tblVCDBIndex[],4,FALSE),"") -> 2 | N78: =IFERROR(VLOOKUP(10*tblRiskRegister32[[#This Row],[Safeguard Maturity Score]]+tblRiskRegister32[[#This Row],[VCDB Index]],tblHITIndexWeightTable[],4,FALSE),"") | O78: =VLOOKUP(tblRiskRegister32[[#This Row],[Asset Class]],tblInherentImpacts30[],2,FALSE) -> 0 | P78: =VLOOKUP(tblRiskRegister32[[#This Row],[Asset Class]],tblInherentImpacts30[],3,FALSE) -> 0 | Q78: =VLOOKUP(tblRiskRegister32[[#This Row],[Asset Class]],tblInherentImpacts30[],4,FALSE) -> 0 | R78: =VLOOKUP(tblRiskRegister32[[#This Row],[Asset Class]],tblInherentImpacts30[],5,FALSE) -> 0 | S78: =IFERROR(MAX(tblRiskRegister32[[#This Row],[Impact to Mission]:[Impact to Obligations]])*tblRiskRegister32[[#This Row],[Expectancy Score]],"") | T78: =tblRiskRegister32[[#This Row],[Risk Score]] | V78: 9.4 | W78: Restrict Unnecessary or Unauthorized Browser and Email Client Extensions | X78: Restrict, either through uninstalling or disabling, any unauthorized or unnecessary browser or email client plugins, extensions, and add-on applications. | AA78: =IFERROR(VLOOKUP(10*tblRiskRegister32[[#This Row],[Risk Treatment Safeguard Maturity Score]]+tblRiskRegister32[[#This Row],[VCDB Index]],tblHITIndexWeightTable[],4,FALSE),"") | AB78: =VLOOKUP(tblRiskRegister32[[#This Row],[Asset Class]],tblInherentImpacts30[],2,FALSE) -> 0 | AC78: =VLOOKUP(tblRiskRegister32[[#This Row],[Asset Class]],tblInherentImpacts30[],3,FALSE) -> 0 | AD78: =VLOOKUP(tblRiskRegister32[[#This Row],[Asset Class]],tblInherentImpacts30[],4,FALSE) -> 0 | AE78: =VLOOKUP(tblRiskRegister32[[#This Row],[Asset Class]],tblInherentImpacts30[],5,FALSE) -> 0 | AF78: =IFERROR(MAX(tblRiskRegister32[[#This Row],[Risk Treatment Safeguard Impact to Mission]:[Risk Treatment Safeguard Impact to Obligations]])*tblRiskRegister32[[#This Row],[Risk Treatment Safeguard Expectancy Score]],"") | AG78: =IF(tblRiskRegister32[[#This Row],[Risk Score]]>=AcceptableRisk,IF(tblRiskRegister32[[#This Row],[Risk Treatment Safeguard Risk Score]]<AcceptableRisk, IF(tblRiskRegister32[[#This Row],[Risk Treatment Safeguard Risk Score]]<tblRiskRegister32[[#This Row],[Risk Score]],"Yes","No"),"No"),"Yes") -> No
B79: Network | D79: 9.5 | E79: Implement DMARC | G79: x | H79: Protect | M79: =IFERROR(VLOOKUP(tblRiskRegister32[[#This Row],[Asset Class]],tblVCDBIndex[],4,FALSE),"") -> 1 | N79: =IFERROR(VLOOKUP(10*tblRiskRegister32[[#This Row],[Safeguard Maturity Score]]+tblRiskRegister32[[#This Row],[VCDB Index]],tblHITIndexWeightTable[],4,FALSE),"") | O79: =VLOOKUP(tblRiskRegister32[[#This Row],[Asset Class]],tblInherentImpacts30[],2,FALSE) -> 0 | P79: =VLOOKUP(tblRiskRegister32[[#This Row],[Asset Class]],tblInherentImpacts30[],3,FALSE) -> 0 | Q79: =VLOOKUP(tblRiskRegister32[[#This Row],[Asset Class]],tblInherentImpacts30[],4,FALSE) -> 0 | R79: =VLOOKUP(tblRiskRegister32[[#This Row],[Asset Class]],tblInherentImpacts30[],5,FALSE) -> 0 | S79: =IFERROR(MAX(tblRiskRegister32[[#This Row],[Impact to Mission]:[Impact to Obligations]])*tblRiskRegister32[[#This Row],[Expectancy Score]],"") | T79: =tblRiskRegister32[[#This Row],[Risk Score]] | V79: 9.5 | W79: Implement DMARC | X79: To lower the chance of spoofed or modified emails from valid domains, implement DMARC policy and verification, starting with implementing the Sender Policy Framework (SPF) and the DomainKeys Identified Mail (DKIM) standards. | AA79: =IFERROR(VLOOKUP(10*tblRiskRegister32[[#This Row],[Risk Treatment Safeguard Maturity Score]]+tblRiskRegister32[[#This Row],[VCDB Index]],tblHITIndexWeightTable[],4,FALSE),"") | AB79: =VLOOKUP(tblRiskRegister32[[#This Row],[Asset Class]],tblInherentImpacts30[],2,FALSE) -> 0 | AC79: =VLOOKUP(tblRiskRegister32[[#This Row],[Asset Class]],tblInherentImpacts30[],3,FALSE) -> 0 | AD79: =VLOOKUP(tblRiskRegister32[[#This Row],[Asset Class]],tblInherentImpacts30[],4,FALSE) -> 0 | AE79: =VLOOKUP(tblRiskRegister32[[#This Row],[Asset Class]],tblInherentImpacts30[],5,FALSE) -> 0 | AF79: =IFERROR(MAX(tblRiskRegister32[[#This Row],[Risk Treatment Safeguard Impact to Mission]:[Risk Treatment Safeguard Impact to Obligations]])*tblRiskRegister32[[#This Row],[Risk Treatment Safeguard Expectancy Score]],"") | AG79: =IF(tblRiskRegister32[[#This Row],[Risk Score]]>=AcceptableRisk,IF(tblRiskRegister32[[#This Row],[Risk Treatment Safeguard Risk Score]]<AcceptableRisk, IF(tblRiskRegister32[[#This Row],[Risk Treatment Safeguard Risk Score]]<tblRiskRegister32[[#This Row],[Risk Score]],"Yes","No"),"No"),"Yes") -> No
B80: Network | D80: 9.6 | E80: Block Unnecessary File Types | G80: x | H80: Protect | M80: =IFERROR(VLOOKUP(tblRiskRegister32[[#This Row],[Asset Class]],tblVCDBIndex[],4,FALSE),"") -> 1 | N80: =IFERROR(VLOOKUP(10*tblRiskRegister32[[#This Row],[Safeguard Maturity Score]]+tblRiskRegister32[[#This Row],[VCDB Index]],tblHITIndexWeightTable[],4,FALSE),"") | O80: =VLOOKUP(tblRiskRegister32[[#This Row],[Asset Class]],tblInherentImpacts30[],2,FALSE) -> 0 | P80: =VLOOKUP(tblRiskRegister32[[#This Row],[Asset Class]],tblInherentImpacts30[],3,FALSE) -> 0 | Q80: =VLOOKUP(tblRiskRegister32[[#This Row],[Asset Class]],tblInherentImpacts30[],4,FALSE) -> 0 | R80: =VLOOKUP(tblRiskRegister32[[#This Row],[Asset Class]],tblInherentImpacts30[],5,FALSE) -> 0 | S80: =IFERROR(MAX(tblRiskRegister32[[#This Row],[Impact to Mission]:[Impact to Obligations]])*tblRiskRegister32[[#This Row],[Expectancy Score]],"") | T80: =tblRiskRegister32[[#This Row],[Risk Score]] | V80: 9.6 | W80: Block Unnecessary File Types | X80: Block unnecessary file types attempting to enter the enterprise’s email gateway. | AA80: =IFERROR(VLOOKUP(10*tblRiskRegister32[[#This Row],[Risk Treatment Safeguard Maturity Score]]+tblRiskRegister32[[#This Row],[VCDB Index]],tblHITIndexWeightTable[],4,FALSE),"") | AB80: =VLOOKUP(tblRiskRegister32[[#This Row],[Asset Class]],tblInherentImpacts30[],2,FALSE) -> 0 | AC80: =VLOOKUP(tblRiskRegister32[[#This Row],[Asset Class]],tblInherentImpacts30[],3,FALSE) -> 0 | AD80: =VLOOKUP(tblRiskRegister32[[#This Row],[Asset Class]],tblInherentImpacts30[],4,FALSE) -> 0 | AE80: =VLOOKUP(tblRiskRegister32[[#This Row],[Asset Class]],tblInherentImpacts30[],5,FALSE) -> 0 | AF80: =IFERROR(MAX(tblRiskRegister32[[#This Row],[Risk Treatment Safeguard Impact to Mission]:[Risk Treatment Safeguard Impact to Obligations]])*tblRiskRegister32[[#This Row],[Risk Treatment Safeguard Expectancy Score]],"") | AG80: =IF(tblRiskRegister32[[#This Row],[Risk Score]]>=AcceptableRisk,IF(tblRiskRegister32[[#This Row],[Risk Treatment Safeguard Risk Score]]<AcceptableRisk, IF(tblRiskRegister32[[#This Row],[Risk Treatment Safeguard Risk Score]]<tblRiskRegister32[[#This Row],[Risk Score]],"Yes","No"),"No"),"Yes") -> No
B81: Devices | D81: 10.1 | E81: Deploy and Maintain Anti-Malware Software | F81: x | G81: x | H81: Detect | M81: =IFERROR(VLOOKUP(tblRiskRegister32[[#This Row],[Asset Class]],tblVCDBIndex[],4,FALSE),"") -> 4 | N81: =IFERROR(VLOOKUP(10*tblRiskRegister32[[#This Row],[Safeguard Maturity Score]]+tblRiskRegister32[[#This Row],[VCDB Index]],tblHITIndexWeightTable[],4,FALSE),"") | O81: =VLOOKUP(tblRiskRegister32[[#This Row],[Asset Class]],tblInherentImpacts30[],2,FALSE) -> 0 | P81: =VLOOKUP(tblRiskRegister32[[#This Row],[Asset Class]],tblInherentImpacts30[],3,FALSE) -> 0 | Q81: =VLOOKUP(tblRiskRegister32[[#This Row],[Asset Class]],tblInherentImpacts30[],4,FALSE) -> 0 | R81: =VLOOKUP(tblRiskRegister32[[#This Row],[Asset Class]],tblInherentImpacts30[],5,FALSE) -> 0 | S81: =IFERROR(MAX(tblRiskRegister32[[#This Row],[Impact to Mission]:[Impact to Obligations]])*tblRiskRegister32[[#This Row],[Expectancy Score]],"") | T81: =tblRiskRegister32[[#This Row],[Risk Score]] | V81: 10.1 | W81: Deploy and Maintain Anti-Malware Software | X81: Deploy and maintain anti-malware software on all enterprise assets. | AA81: =IFERROR(VLOOKUP(10*tblRiskRegister32[[#This Row],[Risk Treatment Safeguard Maturity Score]]+tblRiskRegister32[[#This Row],[VCDB Index]],tblHITIndexWeightTable[],4,FALSE),"") | AB81: =VLOOKUP(tblRiskRegister32[[#This Row],[Asset Class]],tblInherentImpacts30[],2,FALSE) -> 0 | AC81: =VLOOKUP(tblRiskRegister32[[#This Row],[Asset Class]],tblInherentImpacts30[],3,FALSE) -> 0 | AD81: =VLOOKUP(tblRiskRegister32[[#This Row],[Asset Class]],tblInherentImpacts30[],4,FALSE) -> 0 | AE81: =VLOOKUP(tblRiskRegister32[[#This Row],[Asset Class]],tblInherentImpacts30[],5,FALSE) -> 0 | AF81: =IFERROR(MAX(tblRiskRegister32[[#This Row],[Risk Treatment Safeguard Impact to Mission]:[Risk Treatment Safeguard Impact to Obligations]])*tblRiskRegister32[[#This Row],[Risk Treatment Safeguard Expectancy Score]],"") | AG81: =IF(tblRiskRegister32[[#This Row],[Risk Score]]>=AcceptableRisk,IF(tblRiskRegister32[[#This Row],[Risk Treatment Safeguard Risk Score]]<AcceptableRisk, IF(tblRiskRegister32[[#This Row],[Risk Treatment Safeguard Risk Score]]<tblRiskRegister32[[#This Row],[Risk Score]],"Yes","No"),"No"),"Yes") -> No
B82: Devices | D82: 10.2 | E82: Configure Automatic Anti-Malware Signature Updates | F82: x | G82: x | H82: Protect | M82: =IFERROR(VLOOKUP(tblRiskRegister32[[#This Row],[Asset Class]],tblVCDBIndex[],4,FALSE),"") -> 4 | N82: =IFERROR(VLOOKUP(10*tblRiskRegister32[[#This Row],[Safeguard Maturity Score]]+tblRiskRegister32[[#This Row],[VCDB Index]],tblHITIndexWeightTable[],4,FALSE),"") | O82: =VLOOKUP(tblRiskRegister32[[#This Row],[Asset Class]],tblInherentImpacts30[],2,FALSE) -> 0 | P82: =VLOOKUP(tblRiskRegister32[[#This Row],[Asset Class]],tblInherentImpacts30[],3,FALSE) -> 0 | Q82: =VLOOKUP(tblRiskRegister32[[#This Row],[Asset Class]],tblInherentImpacts30[],4,FALSE) -> 0 | R82: =VLOOKUP(tblRiskRegister32[[#This Row],[Asset Class]],tblInherentImpacts30[],5,FALSE) -> 0 | S82: =IFERROR(MAX(tblRiskRegister32[[#This Row],[Impact to Mission]:[Impact to Obligations]])*tblRiskRegister32[[#This Row],[Expectancy Score]],"") | T82: =tblRiskRegister32[[#This Row],[Risk Score]] | V82: 10.2 | W82: Configure Automatic Anti-Malware Signature Updates | X82: Configure automatic updates for anti-malware signature files on all enterprise assets. | AA82: =IFERROR(VLOOKUP(10*tblRiskRegister32[[#This Row],[Risk Treatment Safeguard Maturity Score]]+tblRiskRegister32[[#This Row],[VCDB Index]],tblHITIndexWeightTable[],4,FALSE),"") | AB82: =VLOOKUP(tblRiskRegister32[[#This Row],[Asset Class]],tblInherentImpacts30[],2,FALSE) -> 0 | AC82: =VLOOKUP(tblRiskRegister32[[#This Row],[Asset Class]],tblInherentImpacts30[],3,FALSE) -> 0 | AD82: =VLOOKUP(tblRiskRegister32[[#This Row],[Asset Class]],tblInherentImpacts30[],4,FALSE) -> 0 | AE82: =VLOOKUP(tblRiskRegister32[[#This Row],[Asset Class]],tblInherentImpacts30[],5,FALSE) -> 0 | AF82: =IFERROR(MAX(tblRiskRegister32[[#This Row],[Risk Treatment Safeguard Impact to Mission]:[Risk Treatment Safeguard Impact to Obligations]])*tblRiskRegister32[[#This Row],[Risk Treatment Safeguard Expectancy Score]],"") | AG82: =IF(tblRiskRegister32[[#This Row],[Risk Score]]>=AcceptableRisk,IF(tblRiskRegister32[[#This Row],[Risk Treatment Safeguard Risk Score]]<AcceptableRisk, IF(tblRiskRegister32[[#This Row],[Risk Treatment Safeguard Risk Score]]<tblRiskRegister32[[#This Row],[Risk Score]],"Yes","No"),"No"),"Yes") -> No
B83: Devices | D83: 10.3 | E83: Disable Autorun and Autoplay for Removable Media | F83: x | G83: x | H83: Protect | M83: =IFERROR(VLOOKUP(tblRiskRegister32[[#This Row],[Asset Class]],tblVCDBIndex[],4,FALSE),"") -> 4 | N83: =IFERROR(VLOOKUP(10*tblRiskRegister32[[#This Row],[Safeguard Maturity Score]]+tblRiskRegister32[[#This Row],[VCDB Index]],tblHITIndexWeightTable[],4,FALSE),"") | O83: =VLOOKUP(tblRiskRegister32[[#This Row],[Asset Class]],tblInherentImpacts30[],2,FALSE) -> 0 | P83: =VLOOKUP(tblRiskRegister32[[#This Row],[Asset Class]],tblInherentImpacts30[],3,FALSE) -> 0 | Q83: =VLOOKUP(tblRiskRegister32[[#This Row],[Asset Class]],tblInherentImpacts30[],4,FALSE) -> 0 | R83: =VLOOKUP(tblRiskRegister32[[#This Row],[Asset Class]],tblInherentImpacts30[],5,FALSE) -> 0 | S83: =IFERROR(MAX(tblRiskRegister32[[#This Row],[Impact to Mission]:[Impact to Obligations]])*tblRiskRegister32[[#This Row],[Expectancy Score]],"") | T83: =tblRiskRegister32[[#This Row],[Risk Score]] | V83: 10.3 | W83: Disable Autorun and Autoplay for Removable Media | X83: Disable autorun and autoplay auto-execute functionality for removable media. | AA83: =IFERROR(VLOOKUP(10*tblRiskRegister32[[#This Row],[Risk Treatment Safeguard Maturity Score]]+tblRiskRegister32[[#This Row],[VCDB Index]],tblHITIndexWeightTable[],4,FALSE),"") | AB83: =VLOOKUP(tblRiskRegister32[[#This Row],[Asset Class]],tblInherentImpacts30[],2,FALSE) -> 0 | AC83: =VLOOKUP(tblRiskRegister32[[#This Row],[Asset Class]],tblInherentImpacts30[],3,FALSE) -> 0 | AD83: =VLOOKUP(tblRiskRegister32[[#This Row],[Asset Class]],tblInherentImpacts30[],4,FALSE) -> 0 | AE83: =VLOOKUP(tblRiskRegister32[[#This Row],[Asset Class]],tblInherentImpacts30[],5,FALSE) -> 0 | AF83: =IFERROR(MAX(tblRiskRegister32[[#This Row],[Risk Treatment Safeguard Impact to Mission]:[Risk Treatment Safeguard Impact to Obligations]])*tblRiskRegister32[[#This Row],[Risk Treatment Safeguard Expectancy Score]],"") | AG83: =IF(tblRiskRegister32[[#This Row],[Risk Score]]>=AcceptableRisk,IF(tblRiskRegister32[[#This Row],[Risk Treatment Safeguard Risk Score]]<AcceptableRisk, IF(tblRiskRegister32[[#This Row],[Risk Treatment Safeguard Risk Score]]<tblRiskRegister32[[#This Row],[Risk Score]],"Yes","No"),"No"),"Yes") -> No
B84: Devices | D84: 10.4 | E84: Configure Automatic Anti-Malware Scanning of Removable Media | G84: x | H84: Detect | M84: =IFERROR(VLOOKUP(tblRiskRegister32[[#This Row],[Asset Class]],tblVCDBIndex[],4,FALSE),"") -> 4 | N84: =IFERROR(VLOOKUP(10*tblRiskRegister32[[#This Row],[Safeguard Maturity Score]]+tblRiskRegister32[[#This Row],[VCDB Index]],tblHITIndexWeightTable[],4,FALSE),"") | O84: =VLOOKUP(tblRiskRegister32[[#This Row],[Asset Class]],tblInherentImpacts30[],2,FALSE) -> 0 | P84: =VLOOKUP(tblRiskRegister32[[#This Row],[Asset Class]],tblInherentImpacts30[],3,FALSE) -> 0 | Q84: =VLOOKUP(tblRiskRegister32[[#This Row],[Asset Class]],tblInherentImpacts30[],4,FALSE) -> 0 | R84: =VLOOKUP(tblRiskRegister32[[#This Row],[Asset Class]],tblInherentImpacts30[],5,FALSE) -> 0 | S84: =IFERROR(MAX(tblRiskRegister32[[#This Row],[Impact to Mission]:[Impact to Obligations]])*tblRiskRegister32[[#This Row],[Expectancy Score]],"") | T84: =tblRiskRegister32[[#This Row],[Risk Score]] | V84: 10.4 | W84: Configure Automatic Anti-Malware Scanning of Removable Media | X84: Configure anti-malware software to automatically scan removable media. | AA84: =IFERROR(VLOOKUP(10*tblRiskRegister32[[#This Row],[Risk Treatment Safeguard Maturity Score]]+tblRiskRegister32[[#This Row],[VCDB Index]],tblHITIndexWeightTable[],4,FALSE),"") | AB84: =VLOOKUP(tblRiskRegister32[[#This Row],[Asset Class]],tblInherentImpacts30[],2,FALSE) -> 0 | AC84: =VLOOKUP(tblRiskRegister32[[#This Row],[Asset Class]],tblInherentImpacts30[],3,FALSE) -> 0 | AD84: =VLOOKUP(tblRiskRegister32[[#This Row],[Asset Class]],tblInherentImpacts30[],4,FALSE) -> 0 | AE84: =VLOOKUP(tblRiskRegister32[[#This Row],[Asset Class]],tblInherentImpacts30[],5,FALSE) -> 0 | AF84: =IFERROR(MAX(tblRiskRegister32[[#This Row],[Risk Treatment Safeguard Impact to Mission]:[Risk Treatment Safeguard Impact to Obligations]])*tblRiskRegister32[[#This Row],[Risk Treatment Safeguard Expectancy Score]],"") | AG84: =IF(tblRiskRegister32[[#This Row],[Risk Score]]>=AcceptableRisk,IF(tblRiskRegister32[[#This Row],[Risk Treatment Safeguard Risk Score]]<AcceptableRisk, IF(tblRiskRegister32[[#This Row],[Risk Treatment Safeguard Risk Score]]<tblRiskRegister32[[#This Row],[Risk Score]],"Yes","No"),"No"),"Yes") -> No
B85: Devices | D85: 10.5 | E85: Enable Anti-Exploitation Features | G85: x | H85: Protect | M85: =IFERROR(VLOOKUP(tblRiskRegister32[[#This Row],[Asset Class]],tblVCDBIndex[],4,FALSE),"") -> 4 | N85: =IFERROR(VLOOKUP(10*tblRiskRegister32[[#This Row],[Safeguard Maturity Score]]+tblRiskRegister32[[#This Row],[VCDB Index]],tblHITIndexWeightTable[],4,FALSE),"") | O85: =VLOOKUP(tblRiskRegister32[[#This Row],[Asset Class]],tblInherentImpacts30[],2,FALSE) -> 0 | P85: =VLOOKUP(tblRiskRegister32[[#This Row],[Asset Class]],tblInherentImpacts30[],3,FALSE) -> 0 | Q85: =VLOOKUP(tblRiskRegister32[[#This Row],[Asset Class]],tblInherentImpacts30[],4,FALSE) -> 0 | R85: =VLOOKUP(tblRiskRegister32[[#This Row],[Asset Class]],tblInherentImpacts30[],5,FALSE) -> 0 | S85: =IFERROR(MAX(tblRiskRegister32[[#This Row],[Impact to Mission]:[Impact to Obligations]])*tblRiskRegister32[[#This Row],[Expectancy Score]],"") | T85: =tblRiskRegister32[[#This Row],[Risk Score]] | V85: 10.5 | W85: Enable Anti-Exploitation Features | X85: Enable anti-exploitation features on enterprise assets and software, where possible, such as Microsoft® Data Execution Prevention (DEP), Windows® Defender Exploit Guard (WDEG), or Apple® System Integrity Protection (SIP) and Gatekeeper™. | AA85: =IFERROR(VLOOKUP(10*tblRiskRegister32[[#This Row],[Risk Treatment Safeguard Maturity Score]]+tblRiskRegister32[[#This Row],[VCDB Index]],tblHITIndexWeightTable[],4,FALSE),"") | AB85: =VLOOKUP(tblRiskRegister32[[#This Row],[Asset Class]],tblInherentImpacts30[],2,FALSE) -> 0 | AC85: =VLOOKUP(tblRiskRegister32[[#This Row],[Asset Class]],tblInherentImpacts30[],3,FALSE) -> 0 | AD85: =VLOOKUP(tblRiskRegister32[[#This Row],[Asset Class]],tblInherentImpacts30[],4,FALSE) -> 0 | AE85: =VLOOKUP(tblRiskRegister32[[#This Row],[Asset Class]],tblInherentImpacts30[],5,FALSE) -> 0 | AF85: =IFERROR(MAX(tblRiskRegister32[[#This Row],[Risk Treatment Safeguard Impact to Mission]:[Risk Treatment Safeguard Impact to Obligations]])*tblRiskRegister32[[#This Row],[Risk Treatment Safeguard Expectancy Score]],"") | AG85: =IF(tblRiskRegister32[[#This Row],[Risk Score]]>=AcceptableRisk,IF(tblRiskRegister32[[#This Row],[Risk Treatment Safeguard Risk Score]]<AcceptableRisk, IF(tblRiskRegister32[[#This Row],[Risk Treatment Safeguard Risk Score]]<tblRiskRegister32[[#This Row],[Risk Score]],"Yes","No"),"No"),"Yes") -> No
B86: Devices | D86: 10.6 | E86: Centrally Manage Anti-Malware Software | G86: x | H86: Protect | M86: =IFERROR(VLOOKUP(tblRiskRegister32[[#This Row],[Asset Class]],tblVCDBIndex[],4,FALSE),"") -> 4 | N86: =IFERROR(VLOOKUP(10*tblRiskRegister32[[#This Row],[Safeguard Maturity Score]]+tblRiskRegister32[[#This Row],[VCDB Index]],tblHITIndexWeightTable[],4,FALSE),"") | O86: =VLOOKUP(tblRiskRegister32[[#This Row],[Asset Class]],tblInherentImpacts30[],2,FALSE) -> 0 | P86: =VLOOKUP(tblRiskRegister32[[#This Row],[Asset Class]],tblInherentImpacts30[],3,FALSE) -> 0 | Q86: =VLOOKUP(tblRiskRegister32[[#This Row],[Asset Class]],tblInherentImpacts30[],4,FALSE) -> 0 | R86: =VLOOKUP(tblRiskRegister32[[#This Row],[Asset Class]],tblInherentImpacts30[],5,FALSE) -> 0 | S86: =IFERROR(MAX(tblRiskRegister32[[#This Row],[Impact to Mission]:[Impact to Obligations]])*tblRiskRegister32[[#This Row],[Expectancy Score]],"") | T86: =tblRiskRegister32[[#This Row],[Risk Score]] | V86: 10.6 | W86: Centrally Manage Anti-Malware Software | X86: Centrally manage anti-malware software. | AA86: =IFERROR(VLOOKUP(10*tblRiskRegister32[[#This Row],[Risk Treatment Safeguard Maturity Score]]+tblRiskRegister32[[#This Row],[VCDB Index]],tblHITIndexWeightTable[],4,FALSE),"") | AB86: =VLOOKUP(tblRiskRegister32[[#This Row],[Asset Class]],tblInherentImpacts30[],2,FALSE) -> 0 | AC86: =VLOOKUP(tblRiskRegister32[[#This Row],[Asset Class]],tblInherentImpacts30[],3,FALSE) -> 0 | AD86: =VLOOKUP(tblRiskRegister32[[#This Row],[Asset Class]],tblInherentImpacts30[],4,FALSE) -> 0 | AE86: =VLOOKUP(tblRiskRegister32[[#This Row],[Asset Class]],tblInherentImpacts30[],5,FALSE) -> 0 | AF86: =IFERROR(MAX(tblRiskRegister32[[#This Row],[Risk Treatment Safeguard Impact to Mission]:[Risk Treatment Safeguard Impact to Obligations]])*tblRiskRegister32[[#This Row],[Risk Treatment Safeguard Expectancy Score]],"") | AG86: =IF(tblRiskRegister32[[#This Row],[Risk Score]]>=AcceptableRisk,IF(tblRiskRegister32[[#This Row],[Risk Treatment Safeguard Risk Score]]<AcceptableRisk, IF(tblRiskRegister32[[#This Row],[Risk Treatment Safeguard Risk Score]]<tblRiskRegister32[[#This Row],[Risk Score]],"Yes","No"),"No"),"Yes") -> No
B87: Devices | D87: 10.7 | E87: Use Behavior-Based Anti-Malware Software | G87: x | H87: Detect | M87: =IFERROR(VLOOKUP(tblRiskRegister32[[#This Row],[Asset Class]],tblVCDBIndex[],4,FALSE),"") -> 4 | N87: =IFERROR(VLOOKUP(10*tblRiskRegister32[[#This Row],[Safeguard Maturity Score]]+tblRiskRegister32[[#This Row],[VCDB Index]],tblHITIndexWeightTable[],4,FALSE),"") | O87: =VLOOKUP(tblRiskRegister32[[#This Row],[Asset Class]],tblInherentImpacts30[],2,FALSE) -> 0 | P87: =VLOOKUP(tblRiskRegister32[[#This Row],[Asset Class]],tblInherentImpacts30[],3,FALSE) -> 0 | Q87: =VLOOKUP(tblRiskRegister32[[#This Row],[Asset Class]],tblInherentImpacts30[],4,FALSE) -> 0 | R87: =VLOOKUP(tblRiskRegister32[[#This Row],[Asset Class]],tblInherentImpacts30[],5,FALSE) -> 0 | S87: =IFERROR(MAX(tblRiskRegister32[[#This Row],[Impact to Mission]:[Impact to Obligations]])*tblRiskRegister32[[#This Row],[Expectancy Score]],"") | T87: =tblRiskRegister32[[#This Row],[Risk Score]] | V87: 10.7 | W87: Use Behavior-Based Anti-Malware Software | X87: Use behavior-based anti-malware software. | AA87: =IFERROR(VLOOKUP(10*tblRiskRegister32[[#This Row],[Risk Treatment Safeguard Maturity Score]]+tblRiskRegister32[[#This Row],[VCDB Index]],tblHITIndexWeightTable[],4,FALSE),"") | AB87: =VLOOKUP(tblRiskRegister32[[#This Row],[Asset Class]],tblInherentImpacts30[],2,FALSE) -> 0 | AC87: =VLOOKUP(tblRiskRegister32[[#This Row],[Asset Class]],tblInherentImpacts30[],3,FALSE) -> 0 | AD87: =VLOOKUP(tblRiskRegister32[[#This Row],[Asset Class]],tblInherentImpacts30[],4,FALSE) -> 0 | AE87: =VLOOKUP(tblRiskRegister32[[#This Row],[Asset Class]],tblInherentImpacts30[],5,FALSE) -> 0 | AF87: =IFERROR(MAX(tblRiskRegister32[[#This Row],[Risk Treatment Safeguard Impact to Mission]:[Risk Treatment Safeguard Impact to Obligations]])*tblRiskRegister32[[#This Row],[Risk Treatment Safeguard Expectancy Score]],"") | AG87: =IF(tblRiskRegister32[[#This Row],[Risk Score]]>=AcceptableRisk,IF(tblRiskRegister32[[#This Row],[Risk Treatment Safeguard Risk Score]]<AcceptableRisk, IF(tblRiskRegister32[[#This Row],[Risk Treatment Safeguard Risk Score]]<tblRiskRegister32[[#This Row],[Risk Score]],"Yes","No"),"No"),"Yes") -> No
